package com.google.protobuf;

import android.support.v4.media.session.b;
import java.lang.reflect.Field;
import java.util.Arrays;
import java.util.Collection;
import java.util.Iterator;
import java.util.List;
import java.util.Map;
import java.util.Map.Entry;
import sun.misc.Unsafe;

final class w0
  implements l1
{
  private static final int[] r = new int[0];
  private static final Unsafe s = x1.F();
  private final int[] a;
  private final Object[] b;
  private final int c;
  private final int d;
  private final t0 e;
  private final boolean f;
  private final boolean g;
  private final boolean h;
  private final boolean i;
  private final int[] j;
  private final int k;
  private final int l;
  private final y0 m;
  private final j0 n;
  private final t1 o;
  private final s p;
  private final o0 q;
  
  private w0(int[] paramArrayOfInt1, Object[] paramArrayOfObject, int paramInt1, int paramInt2, t0 paramT0, boolean paramBoolean1, boolean paramBoolean2, int[] paramArrayOfInt2, int paramInt3, int paramInt4, y0 paramY0, j0 paramJ0, t1 paramT1, s paramS, o0 paramO0)
  {
    a = paramArrayOfInt1;
    b = paramArrayOfObject;
    c = paramInt1;
    d = paramInt2;
    g = (paramT0 instanceof z);
    h = paramBoolean1;
    if ((paramS != null) && (paramS.e(paramT0))) {
      paramBoolean1 = true;
    } else {
      paramBoolean1 = false;
    }
    f = paramBoolean1;
    i = paramBoolean2;
    j = paramArrayOfInt2;
    k = paramInt3;
    l = paramInt4;
    m = paramY0;
    n = paramJ0;
    o = paramT1;
    p = paramS;
    e = paramT0;
    q = paramO0;
  }
  
  private static boolean A(int paramInt)
  {
    return (paramInt & 0x20000000) != 0;
  }
  
  private boolean B(Object paramObject, int paramInt)
  {
    int i1 = h0(paramInt);
    long l1 = 0xFFFFF & i1;
    boolean bool2 = false;
    boolean bool3 = false;
    boolean bool4 = false;
    boolean bool5 = false;
    boolean bool6 = false;
    boolean bool7 = false;
    boolean bool8 = false;
    boolean bool9 = false;
    boolean bool10 = false;
    boolean bool11 = false;
    boolean bool12 = false;
    boolean bool13 = false;
    boolean bool14 = false;
    boolean bool15 = false;
    boolean bool16 = false;
    boolean bool1 = false;
    if (l1 == 1048575L)
    {
      paramInt = r0(paramInt);
      l1 = U(paramInt);
      switch (q0(paramInt))
      {
      default: 
        throw new IllegalArgumentException();
      case 17: 
        if (x1.E(paramObject, l1) != null) {
          bool1 = true;
        }
        return bool1;
      case 16: 
        bool1 = bool2;
        if (x1.C(paramObject, l1) != 0L) {
          bool1 = true;
        }
        return bool1;
      case 15: 
        bool1 = bool3;
        if (x1.A(paramObject, l1) != 0) {
          bool1 = true;
        }
        return bool1;
      case 14: 
        bool1 = bool4;
        if (x1.C(paramObject, l1) != 0L) {
          bool1 = true;
        }
        return bool1;
      case 13: 
        bool1 = bool5;
        if (x1.A(paramObject, l1) != 0) {
          bool1 = true;
        }
        return bool1;
      case 12: 
        bool1 = bool6;
        if (x1.A(paramObject, l1) != 0) {
          bool1 = true;
        }
        return bool1;
      case 11: 
        bool1 = bool7;
        if (x1.A(paramObject, l1) != 0) {
          bool1 = true;
        }
        return bool1;
      case 10: 
        return j.f.equals(x1.E(paramObject, l1)) ^ true;
      case 9: 
        bool1 = bool8;
        if (x1.E(paramObject, l1) != null) {
          bool1 = true;
        }
        return bool1;
      case 8: 
        paramObject = x1.E(paramObject, l1);
        if ((paramObject instanceof String)) {
          return ((String)paramObject).isEmpty() ^ true;
        }
        if ((paramObject instanceof j)) {
          return j.f.equals(paramObject) ^ true;
        }
        throw new IllegalArgumentException();
      case 7: 
        return x1.r(paramObject, l1);
      case 6: 
        bool1 = bool9;
        if (x1.A(paramObject, l1) != 0) {
          bool1 = true;
        }
        return bool1;
      case 5: 
        bool1 = bool10;
        if (x1.C(paramObject, l1) != 0L) {
          bool1 = true;
        }
        return bool1;
      case 4: 
        bool1 = bool11;
        if (x1.A(paramObject, l1) != 0) {
          bool1 = true;
        }
        return bool1;
      case 3: 
        bool1 = bool12;
        if (x1.C(paramObject, l1) != 0L) {
          bool1 = true;
        }
        return bool1;
      case 2: 
        bool1 = bool13;
        if (x1.C(paramObject, l1) != 0L) {
          bool1 = true;
        }
        return bool1;
      case 1: 
        bool1 = bool14;
        if (x1.z(paramObject, l1) != 0.0F) {
          bool1 = true;
        }
        return bool1;
      }
      bool1 = bool15;
      if (x1.y(paramObject, l1) != 0.0D) {
        bool1 = true;
      }
      return bool1;
    }
    bool1 = bool16;
    if ((x1.A(paramObject, l1) & 1 << (i1 >>> 20)) != 0) {
      bool1 = true;
    }
    return bool1;
  }
  
  private boolean C(Object paramObject, int paramInt1, int paramInt2, int paramInt3, int paramInt4)
  {
    if (paramInt2 == 1048575) {
      return B(paramObject, paramInt1);
    }
    return (paramInt3 & paramInt4) != 0;
  }
  
  private static boolean D(Object paramObject, int paramInt, l1 paramL1)
  {
    return paramL1.d(x1.E(paramObject, U(paramInt)));
  }
  
  private boolean E(Object paramObject, int paramInt1, int paramInt2)
  {
    paramObject = (List)x1.E(paramObject, U(paramInt1));
    if (paramObject.isEmpty()) {
      return true;
    }
    l1 localL1 = u(paramInt2);
    paramInt1 = 0;
    while (paramInt1 < paramObject.size())
    {
      if (!localL1.d(paramObject.get(paramInt1))) {
        return false;
      }
      paramInt1 += 1;
    }
    return true;
  }
  
  private boolean F(Object paramObject, int paramInt1, int paramInt2)
  {
    paramObject = q.g(x1.E(paramObject, U(paramInt1)));
    if (paramObject.isEmpty()) {
      return true;
    }
    Object localObject1 = t(paramInt2);
    if (q.f(localObject1).c.a() != z1.c.n) {
      return true;
    }
    Iterator localIterator = paramObject.values().iterator();
    paramObject = null;
    while (localIterator.hasNext())
    {
      Object localObject2 = localIterator.next();
      localObject1 = paramObject;
      if (paramObject == null) {
        localObject1 = g1.a().d(localObject2.getClass());
      }
      paramObject = localObject1;
      if (!((l1)localObject1).d(localObject2)) {
        return false;
      }
    }
    return true;
  }
  
  private boolean G(Object paramObject1, Object paramObject2, int paramInt)
  {
    long l1 = h0(paramInt) & 0xFFFFF;
    return x1.A(paramObject1, l1) == x1.A(paramObject2, l1);
  }
  
  private boolean H(Object paramObject, int paramInt1, int paramInt2)
  {
    return x1.A(paramObject, h0(paramInt2) & 0xFFFFF) == paramInt1;
  }
  
  private static boolean I(int paramInt)
  {
    return (paramInt & 0x10000000) != 0;
  }
  
  private static List J(Object paramObject, long paramLong)
  {
    return (List)x1.E(paramObject, paramLong);
  }
  
  private static long K(Object paramObject, long paramLong)
  {
    return x1.C(paramObject, paramLong);
  }
  
  /* Error */
  private void L(t1 paramT1, s paramS, Object paramObject, j1 paramJ1, r paramR)
  {
    // Byte code:
    //   0: aconst_null
    //   1: astore 13
    //   3: aload 13
    //   5: astore 17
    //   7: aload 13
    //   9: astore 14
    //   11: aload 4
    //   13: invokeinterface 256 1 0
    //   18: istore 8
    //   20: aload 13
    //   22: astore 14
    //   24: aload_0
    //   25: iload 8
    //   27: invokespecial 259	com/google/protobuf/w0:f0	(I)I
    //   30: istore 6
    //   32: iload 6
    //   34: ifge +291 -> 325
    //   37: iload 8
    //   39: ldc_w 260
    //   42: if_icmpne +57 -> 99
    //   45: aload_0
    //   46: getfield 82	com/google/protobuf/w0:k	I
    //   49: istore 6
    //   51: iload 6
    //   53: aload_0
    //   54: getfield 84	com/google/protobuf/w0:l	I
    //   57: if_icmpge +29 -> 86
    //   60: aload_0
    //   61: aload_3
    //   62: aload_0
    //   63: getfield 80	com/google/protobuf/w0:j	[I
    //   66: iload 6
    //   68: iaload
    //   69: aload 13
    //   71: aload_1
    //   72: invokespecial 263	com/google/protobuf/w0:q	(Ljava/lang/Object;ILjava/lang/Object;Lcom/google/protobuf/t1;)Ljava/lang/Object;
    //   75: astore 13
    //   77: iload 6
    //   79: iconst_1
    //   80: iadd
    //   81: istore 6
    //   83: goto -32 -> 51
    //   86: aload 13
    //   88: ifnull +10 -> 98
    //   91: aload_1
    //   92: aload_3
    //   93: aload 13
    //   95: invokevirtual 268	com/google/protobuf/t1:o	(Ljava/lang/Object;Ljava/lang/Object;)V
    //   98: return
    //   99: aload 13
    //   101: astore 14
    //   103: aload_0
    //   104: getfield 76	com/google/protobuf/w0:f	Z
    //   107: ifne +9 -> 116
    //   110: aconst_null
    //   111: astore 15
    //   113: goto +21 -> 134
    //   116: aload 13
    //   118: astore 14
    //   120: aload_2
    //   121: aload 5
    //   123: aload_0
    //   124: getfield 94	com/google/protobuf/w0:e	Lcom/google/protobuf/t0;
    //   127: iload 8
    //   129: invokevirtual 271	com/google/protobuf/s:b	(Lcom/google/protobuf/r;Lcom/google/protobuf/t0;I)Ljava/lang/Object;
    //   132: astore 15
    //   134: aload 15
    //   136: ifnull +51 -> 187
    //   139: aload 17
    //   141: astore 16
    //   143: aload 17
    //   145: ifnonnull +14 -> 159
    //   148: aload 13
    //   150: astore 14
    //   152: aload_2
    //   153: aload_3
    //   154: invokevirtual 274	com/google/protobuf/s:d	(Ljava/lang/Object;)Lcom/google/protobuf/v;
    //   157: astore 16
    //   159: aload 13
    //   161: astore 14
    //   163: aload_2
    //   164: aload 4
    //   166: aload 15
    //   168: aload 5
    //   170: aload 16
    //   172: aload 13
    //   174: aload_1
    //   175: invokevirtual 277	com/google/protobuf/s:g	(Lcom/google/protobuf/j1;Ljava/lang/Object;Lcom/google/protobuf/r;Lcom/google/protobuf/v;Ljava/lang/Object;Lcom/google/protobuf/t1;)Ljava/lang/Object;
    //   178: astore 13
    //   180: aload 16
    //   182: astore 17
    //   184: goto -177 -> 7
    //   187: aload 13
    //   189: astore 14
    //   191: aload_1
    //   192: aload 4
    //   194: invokevirtual 280	com/google/protobuf/t1:q	(Lcom/google/protobuf/j1;)Z
    //   197: ifeq +24 -> 221
    //   200: aload 13
    //   202: astore 16
    //   204: aload 13
    //   206: astore 14
    //   208: aload 4
    //   210: invokeinterface 282 1 0
    //   215: ifeq +56 -> 271
    //   218: goto -211 -> 7
    //   221: aload 13
    //   223: astore 15
    //   225: aload 13
    //   227: ifnonnull +14 -> 241
    //   230: aload 13
    //   232: astore 14
    //   234: aload_1
    //   235: aload_3
    //   236: invokevirtual 285	com/google/protobuf/t1:f	(Ljava/lang/Object;)Ljava/lang/Object;
    //   239: astore 15
    //   241: aload 15
    //   243: astore 14
    //   245: aload_1
    //   246: aload 15
    //   248: aload 4
    //   250: invokevirtual 288	com/google/protobuf/t1:m	(Ljava/lang/Object;Lcom/google/protobuf/j1;)Z
    //   253: istore 10
    //   255: aload 15
    //   257: astore 16
    //   259: iload 10
    //   261: ifeq +10 -> 271
    //   264: aload 15
    //   266: astore 13
    //   268: goto -261 -> 7
    //   271: aload_0
    //   272: getfield 82	com/google/protobuf/w0:k	I
    //   275: istore 6
    //   277: iload 6
    //   279: aload_0
    //   280: getfield 84	com/google/protobuf/w0:l	I
    //   283: if_icmpge +29 -> 312
    //   286: aload_0
    //   287: aload_3
    //   288: aload_0
    //   289: getfield 80	com/google/protobuf/w0:j	[I
    //   292: iload 6
    //   294: iaload
    //   295: aload 16
    //   297: aload_1
    //   298: invokespecial 263	com/google/protobuf/w0:q	(Ljava/lang/Object;ILjava/lang/Object;Lcom/google/protobuf/t1;)Ljava/lang/Object;
    //   301: astore 16
    //   303: iload 6
    //   305: iconst_1
    //   306: iadd
    //   307: istore 6
    //   309: goto -32 -> 277
    //   312: aload 16
    //   314: ifnull +10 -> 324
    //   317: aload_1
    //   318: aload_3
    //   319: aload 16
    //   321: invokevirtual 268	com/google/protobuf/t1:o	(Ljava/lang/Object;Ljava/lang/Object;)V
    //   324: return
    //   325: aload 13
    //   327: astore 14
    //   329: aload_0
    //   330: iload 6
    //   332: invokespecial 111	com/google/protobuf/w0:r0	(I)I
    //   335: istore 7
    //   337: aload 13
    //   339: astore 14
    //   341: aload 13
    //   343: astore 15
    //   345: iload 7
    //   347: invokestatic 118	com/google/protobuf/w0:q0	(I)I
    //   350: tableswitch	default:+3190->3540, 0:+2835->3185, 1:+2808->3158, 2:+2781->3131, 3:+2754->3104, 4:+2727->3077, 5:+2700->3050, 6:+2673->3023, 7:+2646->2996, 8:+2626->2976, 9:+2518->2868, 10:+2491->2841, 11:+2464->2814, 12:+2410->2760, 13:+2383->2733, 14:+2356->2706, 15:+2329->2679, 16:+2302->2652, 17:+2163->2513, 18:+2137->2487, 19:+2111->2461, 20:+2085->2435, 21:+2059->2409, 22:+2033->2383, 23:+2007->2357, 24:+1981->2331, 25:+1955->2305, 26:+1935->2285, 27:+1907->2257, 28:+1876->2226, 29:+1850->2200, 30:+1792->2142, 31:+1766->2116, 32:+1740->2090, 33:+1714->2064, 34:+1688->2038, 35:+1645->1995, 36:+1602->1952, 37:+1559->1909, 38:+1516->1866, 39:+1473->1823, 40:+1430->1780, 41:+1387->1737, 42:+1344->1694, 43:+1301->1651, 44:+1222->1572, 45:+1179->1529, 46:+1136->1486, 47:+1093->1443, 48:+1050->1400, 49:+1019->1369, 50:+991->1341, 51:+961->1311, 52:+931->1281, 53:+901->1251, 54:+871->1221, 55:+841->1191, 56:+811->1161, 57:+781->1131, 58:+751->1101, 59:+731->1081, 60:+602->952, 61:+575->925, 62:+545->895, 63:+488->838, 64:+458->808, 65:+428->778, 66:+398->748, 67:+368->718, 68:+316->666
    //   640: aload 13
    //   642: astore 16
    //   644: aload 13
    //   646: ifnonnull +2566 -> 3212
    //   649: aload 13
    //   651: astore 14
    //   653: aload 13
    //   655: astore 15
    //   657: aload_1
    //   658: invokevirtual 290	com/google/protobuf/t1:n	()Ljava/lang/Object;
    //   661: astore 16
    //   663: goto +2880 -> 3543
    //   666: aload 13
    //   668: astore 14
    //   670: aload 13
    //   672: astore 15
    //   674: aload_3
    //   675: iload 7
    //   677: invokestatic 115	com/google/protobuf/w0:U	(I)J
    //   680: aload 4
    //   682: aload_0
    //   683: iload 6
    //   685: invokespecial 173	com/google/protobuf/w0:u	(I)Lcom/google/protobuf/l1;
    //   688: aload 5
    //   690: invokeinterface 293 3 0
    //   695: invokestatic 297	com/google/protobuf/x1:S	(Ljava/lang/Object;JLjava/lang/Object;)V
    //   698: aload 13
    //   700: astore 14
    //   702: aload 13
    //   704: astore 15
    //   706: aload_0
    //   707: aload_3
    //   708: iload 8
    //   710: iload 6
    //   712: invokespecial 301	com/google/protobuf/w0:o0	(Ljava/lang/Object;II)V
    //   715: goto -708 -> 7
    //   718: aload 13
    //   720: astore 14
    //   722: aload 13
    //   724: astore 15
    //   726: aload_3
    //   727: iload 7
    //   729: invokestatic 115	com/google/protobuf/w0:U	(I)J
    //   732: aload 4
    //   734: invokeinterface 304 1 0
    //   739: invokestatic 310	java/lang/Long:valueOf	(J)Ljava/lang/Long;
    //   742: invokestatic 297	com/google/protobuf/x1:S	(Ljava/lang/Object;JLjava/lang/Object;)V
    //   745: goto -47 -> 698
    //   748: aload 13
    //   750: astore 14
    //   752: aload 13
    //   754: astore 15
    //   756: aload_3
    //   757: iload 7
    //   759: invokestatic 115	com/google/protobuf/w0:U	(I)J
    //   762: aload 4
    //   764: invokeinterface 312 1 0
    //   769: invokestatic 317	java/lang/Integer:valueOf	(I)Ljava/lang/Integer;
    //   772: invokestatic 297	com/google/protobuf/x1:S	(Ljava/lang/Object;JLjava/lang/Object;)V
    //   775: goto -77 -> 698
    //   778: aload 13
    //   780: astore 14
    //   782: aload 13
    //   784: astore 15
    //   786: aload_3
    //   787: iload 7
    //   789: invokestatic 115	com/google/protobuf/w0:U	(I)J
    //   792: aload 4
    //   794: invokeinterface 320 1 0
    //   799: invokestatic 310	java/lang/Long:valueOf	(J)Ljava/lang/Long;
    //   802: invokestatic 297	com/google/protobuf/x1:S	(Ljava/lang/Object;JLjava/lang/Object;)V
    //   805: goto -107 -> 698
    //   808: aload 13
    //   810: astore 14
    //   812: aload 13
    //   814: astore 15
    //   816: aload_3
    //   817: iload 7
    //   819: invokestatic 115	com/google/protobuf/w0:U	(I)J
    //   822: aload 4
    //   824: invokeinterface 322 1 0
    //   829: invokestatic 317	java/lang/Integer:valueOf	(I)Ljava/lang/Integer;
    //   832: invokestatic 297	com/google/protobuf/x1:S	(Ljava/lang/Object;JLjava/lang/Object;)V
    //   835: goto -137 -> 698
    //   838: aload 13
    //   840: astore 14
    //   842: aload 13
    //   844: astore 15
    //   846: aload 4
    //   848: invokeinterface 324 1 0
    //   853: istore 9
    //   855: aload 13
    //   857: astore 14
    //   859: aload 13
    //   861: astore 15
    //   863: aload_0
    //   864: iload 6
    //   866: invokespecial 327	com/google/protobuf/w0:s	(I)Lcom/google/protobuf/c0$e;
    //   869: pop
    //   870: aload 13
    //   872: astore 14
    //   874: aload 13
    //   876: astore 15
    //   878: aload_3
    //   879: iload 7
    //   881: invokestatic 115	com/google/protobuf/w0:U	(I)J
    //   884: iload 9
    //   886: invokestatic 317	java/lang/Integer:valueOf	(I)Ljava/lang/Integer;
    //   889: invokestatic 297	com/google/protobuf/x1:S	(Ljava/lang/Object;JLjava/lang/Object;)V
    //   892: goto -194 -> 698
    //   895: aload 13
    //   897: astore 14
    //   899: aload 13
    //   901: astore 15
    //   903: aload_3
    //   904: iload 7
    //   906: invokestatic 115	com/google/protobuf/w0:U	(I)J
    //   909: aload 4
    //   911: invokeinterface 329 1 0
    //   916: invokestatic 317	java/lang/Integer:valueOf	(I)Ljava/lang/Integer;
    //   919: invokestatic 297	com/google/protobuf/x1:S	(Ljava/lang/Object;JLjava/lang/Object;)V
    //   922: goto -224 -> 698
    //   925: aload 13
    //   927: astore 14
    //   929: aload 13
    //   931: astore 15
    //   933: aload_3
    //   934: iload 7
    //   936: invokestatic 115	com/google/protobuf/w0:U	(I)J
    //   939: aload 4
    //   941: invokeinterface 332 1 0
    //   946: invokestatic 297	com/google/protobuf/x1:S	(Ljava/lang/Object;JLjava/lang/Object;)V
    //   949: goto -251 -> 698
    //   952: aload 13
    //   954: astore 14
    //   956: aload 13
    //   958: astore 15
    //   960: aload_0
    //   961: aload_3
    //   962: iload 8
    //   964: iload 6
    //   966: invokespecial 334	com/google/protobuf/w0:H	(Ljava/lang/Object;II)Z
    //   969: ifeq +62 -> 1031
    //   972: aload 13
    //   974: astore 14
    //   976: aload 13
    //   978: astore 15
    //   980: aload_3
    //   981: iload 7
    //   983: invokestatic 115	com/google/protobuf/w0:U	(I)J
    //   986: invokestatic 125	com/google/protobuf/x1:E	(Ljava/lang/Object;J)Ljava/lang/Object;
    //   989: aload 4
    //   991: aload_0
    //   992: iload 6
    //   994: invokespecial 173	com/google/protobuf/w0:u	(I)Lcom/google/protobuf/l1;
    //   997: aload 5
    //   999: invokeinterface 337 3 0
    //   1004: invokestatic 342	com/google/protobuf/c0:h	(Ljava/lang/Object;Ljava/lang/Object;)Ljava/lang/Object;
    //   1007: astore 16
    //   1009: aload 13
    //   1011: astore 14
    //   1013: aload 13
    //   1015: astore 15
    //   1017: aload_3
    //   1018: iload 7
    //   1020: invokestatic 115	com/google/protobuf/w0:U	(I)J
    //   1023: aload 16
    //   1025: invokestatic 297	com/google/protobuf/x1:S	(Ljava/lang/Object;JLjava/lang/Object;)V
    //   1028: goto -330 -> 698
    //   1031: aload 13
    //   1033: astore 14
    //   1035: aload 13
    //   1037: astore 15
    //   1039: aload_3
    //   1040: iload 7
    //   1042: invokestatic 115	com/google/protobuf/w0:U	(I)J
    //   1045: aload 4
    //   1047: aload_0
    //   1048: iload 6
    //   1050: invokespecial 173	com/google/protobuf/w0:u	(I)Lcom/google/protobuf/l1;
    //   1053: aload 5
    //   1055: invokeinterface 337 3 0
    //   1060: invokestatic 297	com/google/protobuf/x1:S	(Ljava/lang/Object;JLjava/lang/Object;)V
    //   1063: aload 13
    //   1065: astore 14
    //   1067: aload 13
    //   1069: astore 15
    //   1071: aload_0
    //   1072: aload_3
    //   1073: iload 6
    //   1075: invokespecial 346	com/google/protobuf/w0:n0	(Ljava/lang/Object;I)V
    //   1078: goto -380 -> 698
    //   1081: aload 13
    //   1083: astore 14
    //   1085: aload 13
    //   1087: astore 15
    //   1089: aload_0
    //   1090: aload_3
    //   1091: iload 7
    //   1093: aload 4
    //   1095: invokespecial 350	com/google/protobuf/w0:k0	(Ljava/lang/Object;ILcom/google/protobuf/j1;)V
    //   1098: goto -400 -> 698
    //   1101: aload 13
    //   1103: astore 14
    //   1105: aload 13
    //   1107: astore 15
    //   1109: aload_3
    //   1110: iload 7
    //   1112: invokestatic 115	com/google/protobuf/w0:U	(I)J
    //   1115: aload 4
    //   1117: invokeinterface 352 1 0
    //   1122: invokestatic 357	java/lang/Boolean:valueOf	(Z)Ljava/lang/Boolean;
    //   1125: invokestatic 297	com/google/protobuf/x1:S	(Ljava/lang/Object;JLjava/lang/Object;)V
    //   1128: goto -430 -> 698
    //   1131: aload 13
    //   1133: astore 14
    //   1135: aload 13
    //   1137: astore 15
    //   1139: aload_3
    //   1140: iload 7
    //   1142: invokestatic 115	com/google/protobuf/w0:U	(I)J
    //   1145: aload 4
    //   1147: invokeinterface 359 1 0
    //   1152: invokestatic 317	java/lang/Integer:valueOf	(I)Ljava/lang/Integer;
    //   1155: invokestatic 297	com/google/protobuf/x1:S	(Ljava/lang/Object;JLjava/lang/Object;)V
    //   1158: goto -460 -> 698
    //   1161: aload 13
    //   1163: astore 14
    //   1165: aload 13
    //   1167: astore 15
    //   1169: aload_3
    //   1170: iload 7
    //   1172: invokestatic 115	com/google/protobuf/w0:U	(I)J
    //   1175: aload 4
    //   1177: invokeinterface 361 1 0
    //   1182: invokestatic 310	java/lang/Long:valueOf	(J)Ljava/lang/Long;
    //   1185: invokestatic 297	com/google/protobuf/x1:S	(Ljava/lang/Object;JLjava/lang/Object;)V
    //   1188: goto -490 -> 698
    //   1191: aload 13
    //   1193: astore 14
    //   1195: aload 13
    //   1197: astore 15
    //   1199: aload_3
    //   1200: iload 7
    //   1202: invokestatic 115	com/google/protobuf/w0:U	(I)J
    //   1205: aload 4
    //   1207: invokeinterface 363 1 0
    //   1212: invokestatic 317	java/lang/Integer:valueOf	(I)Ljava/lang/Integer;
    //   1215: invokestatic 297	com/google/protobuf/x1:S	(Ljava/lang/Object;JLjava/lang/Object;)V
    //   1218: goto -520 -> 698
    //   1221: aload 13
    //   1223: astore 14
    //   1225: aload 13
    //   1227: astore 15
    //   1229: aload_3
    //   1230: iload 7
    //   1232: invokestatic 115	com/google/protobuf/w0:U	(I)J
    //   1235: aload 4
    //   1237: invokeinterface 365 1 0
    //   1242: invokestatic 310	java/lang/Long:valueOf	(J)Ljava/lang/Long;
    //   1245: invokestatic 297	com/google/protobuf/x1:S	(Ljava/lang/Object;JLjava/lang/Object;)V
    //   1248: goto -550 -> 698
    //   1251: aload 13
    //   1253: astore 14
    //   1255: aload 13
    //   1257: astore 15
    //   1259: aload_3
    //   1260: iload 7
    //   1262: invokestatic 115	com/google/protobuf/w0:U	(I)J
    //   1265: aload 4
    //   1267: invokeinterface 367 1 0
    //   1272: invokestatic 310	java/lang/Long:valueOf	(J)Ljava/lang/Long;
    //   1275: invokestatic 297	com/google/protobuf/x1:S	(Ljava/lang/Object;JLjava/lang/Object;)V
    //   1278: goto -580 -> 698
    //   1281: aload 13
    //   1283: astore 14
    //   1285: aload 13
    //   1287: astore 15
    //   1289: aload_3
    //   1290: iload 7
    //   1292: invokestatic 115	com/google/protobuf/w0:U	(I)J
    //   1295: aload 4
    //   1297: invokeinterface 371 1 0
    //   1302: invokestatic 376	java/lang/Float:valueOf	(F)Ljava/lang/Float;
    //   1305: invokestatic 297	com/google/protobuf/x1:S	(Ljava/lang/Object;JLjava/lang/Object;)V
    //   1308: goto -610 -> 698
    //   1311: aload 13
    //   1313: astore 14
    //   1315: aload 13
    //   1317: astore 15
    //   1319: aload_3
    //   1320: iload 7
    //   1322: invokestatic 115	com/google/protobuf/w0:U	(I)J
    //   1325: aload 4
    //   1327: invokeinterface 380 1 0
    //   1332: invokestatic 385	java/lang/Double:valueOf	(D)Ljava/lang/Double;
    //   1335: invokestatic 297	com/google/protobuf/x1:S	(Ljava/lang/Object;JLjava/lang/Object;)V
    //   1338: goto -640 -> 698
    //   1341: aload 13
    //   1343: astore 14
    //   1345: aload 13
    //   1347: astore 15
    //   1349: aload_0
    //   1350: aload_3
    //   1351: iload 6
    //   1353: aload_0
    //   1354: iload 6
    //   1356: invokespecial 192	com/google/protobuf/w0:t	(I)Ljava/lang/Object;
    //   1359: aload 5
    //   1361: aload 4
    //   1363: invokespecial 389	com/google/protobuf/w0:M	(Ljava/lang/Object;ILjava/lang/Object;Lcom/google/protobuf/r;Lcom/google/protobuf/j1;)V
    //   1366: goto -1359 -> 7
    //   1369: aload 13
    //   1371: astore 14
    //   1373: aload 13
    //   1375: astore 15
    //   1377: aload_0
    //   1378: aload_3
    //   1379: iload 7
    //   1381: invokestatic 115	com/google/protobuf/w0:U	(I)J
    //   1384: aload 4
    //   1386: aload_0
    //   1387: iload 6
    //   1389: invokespecial 173	com/google/protobuf/w0:u	(I)Lcom/google/protobuf/l1;
    //   1392: aload 5
    //   1394: invokespecial 393	com/google/protobuf/w0:i0	(Ljava/lang/Object;JLcom/google/protobuf/j1;Lcom/google/protobuf/l1;Lcom/google/protobuf/r;)V
    //   1397: goto -1390 -> 7
    //   1400: aload 13
    //   1402: astore 14
    //   1404: aload 13
    //   1406: astore 15
    //   1408: aload_0
    //   1409: getfield 88	com/google/protobuf/w0:n	Lcom/google/protobuf/j0;
    //   1412: aload_3
    //   1413: iload 7
    //   1415: invokestatic 115	com/google/protobuf/w0:U	(I)J
    //   1418: invokevirtual 397	com/google/protobuf/j0:e	(Ljava/lang/Object;J)Ljava/util/List;
    //   1421: astore 16
    //   1423: aload 13
    //   1425: astore 14
    //   1427: aload 13
    //   1429: astore 15
    //   1431: aload 4
    //   1433: aload 16
    //   1435: invokeinterface 400 2 0
    //   1440: goto -1433 -> 7
    //   1443: aload 13
    //   1445: astore 14
    //   1447: aload 13
    //   1449: astore 15
    //   1451: aload_0
    //   1452: getfield 88	com/google/protobuf/w0:n	Lcom/google/protobuf/j0;
    //   1455: aload_3
    //   1456: iload 7
    //   1458: invokestatic 115	com/google/protobuf/w0:U	(I)J
    //   1461: invokevirtual 397	com/google/protobuf/j0:e	(Ljava/lang/Object;J)Ljava/util/List;
    //   1464: astore 16
    //   1466: aload 13
    //   1468: astore 14
    //   1470: aload 13
    //   1472: astore 15
    //   1474: aload 4
    //   1476: aload 16
    //   1478: invokeinterface 402 2 0
    //   1483: goto -1476 -> 7
    //   1486: aload 13
    //   1488: astore 14
    //   1490: aload 13
    //   1492: astore 15
    //   1494: aload_0
    //   1495: getfield 88	com/google/protobuf/w0:n	Lcom/google/protobuf/j0;
    //   1498: aload_3
    //   1499: iload 7
    //   1501: invokestatic 115	com/google/protobuf/w0:U	(I)J
    //   1504: invokevirtual 397	com/google/protobuf/j0:e	(Ljava/lang/Object;J)Ljava/util/List;
    //   1507: astore 16
    //   1509: aload 13
    //   1511: astore 14
    //   1513: aload 13
    //   1515: astore 15
    //   1517: aload 4
    //   1519: aload 16
    //   1521: invokeinterface 404 2 0
    //   1526: goto -1519 -> 7
    //   1529: aload 13
    //   1531: astore 14
    //   1533: aload 13
    //   1535: astore 15
    //   1537: aload_0
    //   1538: getfield 88	com/google/protobuf/w0:n	Lcom/google/protobuf/j0;
    //   1541: aload_3
    //   1542: iload 7
    //   1544: invokestatic 115	com/google/protobuf/w0:U	(I)J
    //   1547: invokevirtual 397	com/google/protobuf/j0:e	(Ljava/lang/Object;J)Ljava/util/List;
    //   1550: astore 16
    //   1552: aload 13
    //   1554: astore 14
    //   1556: aload 13
    //   1558: astore 15
    //   1560: aload 4
    //   1562: aload 16
    //   1564: invokeinterface 406 2 0
    //   1569: goto -1562 -> 7
    //   1572: aload 13
    //   1574: astore 14
    //   1576: aload 13
    //   1578: astore 15
    //   1580: aload_0
    //   1581: getfield 88	com/google/protobuf/w0:n	Lcom/google/protobuf/j0;
    //   1584: aload_3
    //   1585: iload 7
    //   1587: invokestatic 115	com/google/protobuf/w0:U	(I)J
    //   1590: invokevirtual 397	com/google/protobuf/j0:e	(Ljava/lang/Object;J)Ljava/util/List;
    //   1593: astore 16
    //   1595: aload 13
    //   1597: astore 14
    //   1599: aload 13
    //   1601: astore 15
    //   1603: aload 4
    //   1605: aload 16
    //   1607: invokeinterface 409 2 0
    //   1612: aload 13
    //   1614: astore 14
    //   1616: aload 13
    //   1618: astore 15
    //   1620: aload_0
    //   1621: iload 6
    //   1623: invokespecial 327	com/google/protobuf/w0:s	(I)Lcom/google/protobuf/c0$e;
    //   1626: pop
    //   1627: aload 13
    //   1629: astore 14
    //   1631: aload 13
    //   1633: astore 15
    //   1635: iload 8
    //   1637: aload 16
    //   1639: aconst_null
    //   1640: aload 13
    //   1642: aload_1
    //   1643: invokestatic 414	com/google/protobuf/n1:A	(ILjava/util/List;Lcom/google/protobuf/c0$e;Ljava/lang/Object;Lcom/google/protobuf/t1;)Ljava/lang/Object;
    //   1646: astore 13
    //   1648: goto -1641 -> 7
    //   1651: aload 13
    //   1653: astore 14
    //   1655: aload 13
    //   1657: astore 15
    //   1659: aload_0
    //   1660: getfield 88	com/google/protobuf/w0:n	Lcom/google/protobuf/j0;
    //   1663: aload_3
    //   1664: iload 7
    //   1666: invokestatic 115	com/google/protobuf/w0:U	(I)J
    //   1669: invokevirtual 397	com/google/protobuf/j0:e	(Ljava/lang/Object;J)Ljava/util/List;
    //   1672: astore 16
    //   1674: aload 13
    //   1676: astore 14
    //   1678: aload 13
    //   1680: astore 15
    //   1682: aload 4
    //   1684: aload 16
    //   1686: invokeinterface 416 2 0
    //   1691: goto -1684 -> 7
    //   1694: aload 13
    //   1696: astore 14
    //   1698: aload 13
    //   1700: astore 15
    //   1702: aload_0
    //   1703: getfield 88	com/google/protobuf/w0:n	Lcom/google/protobuf/j0;
    //   1706: aload_3
    //   1707: iload 7
    //   1709: invokestatic 115	com/google/protobuf/w0:U	(I)J
    //   1712: invokevirtual 397	com/google/protobuf/j0:e	(Ljava/lang/Object;J)Ljava/util/List;
    //   1715: astore 16
    //   1717: aload 13
    //   1719: astore 14
    //   1721: aload 13
    //   1723: astore 15
    //   1725: aload 4
    //   1727: aload 16
    //   1729: invokeinterface 418 2 0
    //   1734: goto -1727 -> 7
    //   1737: aload 13
    //   1739: astore 14
    //   1741: aload 13
    //   1743: astore 15
    //   1745: aload_0
    //   1746: getfield 88	com/google/protobuf/w0:n	Lcom/google/protobuf/j0;
    //   1749: aload_3
    //   1750: iload 7
    //   1752: invokestatic 115	com/google/protobuf/w0:U	(I)J
    //   1755: invokevirtual 397	com/google/protobuf/j0:e	(Ljava/lang/Object;J)Ljava/util/List;
    //   1758: astore 16
    //   1760: aload 13
    //   1762: astore 14
    //   1764: aload 13
    //   1766: astore 15
    //   1768: aload 4
    //   1770: aload 16
    //   1772: invokeinterface 420 2 0
    //   1777: goto -1770 -> 7
    //   1780: aload 13
    //   1782: astore 14
    //   1784: aload 13
    //   1786: astore 15
    //   1788: aload_0
    //   1789: getfield 88	com/google/protobuf/w0:n	Lcom/google/protobuf/j0;
    //   1792: aload_3
    //   1793: iload 7
    //   1795: invokestatic 115	com/google/protobuf/w0:U	(I)J
    //   1798: invokevirtual 397	com/google/protobuf/j0:e	(Ljava/lang/Object;J)Ljava/util/List;
    //   1801: astore 16
    //   1803: aload 13
    //   1805: astore 14
    //   1807: aload 13
    //   1809: astore 15
    //   1811: aload 4
    //   1813: aload 16
    //   1815: invokeinterface 423 2 0
    //   1820: goto -1813 -> 7
    //   1823: aload 13
    //   1825: astore 14
    //   1827: aload 13
    //   1829: astore 15
    //   1831: aload_0
    //   1832: getfield 88	com/google/protobuf/w0:n	Lcom/google/protobuf/j0;
    //   1835: aload_3
    //   1836: iload 7
    //   1838: invokestatic 115	com/google/protobuf/w0:U	(I)J
    //   1841: invokevirtual 397	com/google/protobuf/j0:e	(Ljava/lang/Object;J)Ljava/util/List;
    //   1844: astore 16
    //   1846: aload 13
    //   1848: astore 14
    //   1850: aload 13
    //   1852: astore 15
    //   1854: aload 4
    //   1856: aload 16
    //   1858: invokeinterface 426 2 0
    //   1863: goto -1856 -> 7
    //   1866: aload 13
    //   1868: astore 14
    //   1870: aload 13
    //   1872: astore 15
    //   1874: aload_0
    //   1875: getfield 88	com/google/protobuf/w0:n	Lcom/google/protobuf/j0;
    //   1878: aload_3
    //   1879: iload 7
    //   1881: invokestatic 115	com/google/protobuf/w0:U	(I)J
    //   1884: invokevirtual 397	com/google/protobuf/j0:e	(Ljava/lang/Object;J)Ljava/util/List;
    //   1887: astore 16
    //   1889: aload 13
    //   1891: astore 14
    //   1893: aload 13
    //   1895: astore 15
    //   1897: aload 4
    //   1899: aload 16
    //   1901: invokeinterface 428 2 0
    //   1906: goto -1899 -> 7
    //   1909: aload 13
    //   1911: astore 14
    //   1913: aload 13
    //   1915: astore 15
    //   1917: aload_0
    //   1918: getfield 88	com/google/protobuf/w0:n	Lcom/google/protobuf/j0;
    //   1921: aload_3
    //   1922: iload 7
    //   1924: invokestatic 115	com/google/protobuf/w0:U	(I)J
    //   1927: invokevirtual 397	com/google/protobuf/j0:e	(Ljava/lang/Object;J)Ljava/util/List;
    //   1930: astore 16
    //   1932: aload 13
    //   1934: astore 14
    //   1936: aload 13
    //   1938: astore 15
    //   1940: aload 4
    //   1942: aload 16
    //   1944: invokeinterface 430 2 0
    //   1949: goto -1942 -> 7
    //   1952: aload 13
    //   1954: astore 14
    //   1956: aload 13
    //   1958: astore 15
    //   1960: aload_0
    //   1961: getfield 88	com/google/protobuf/w0:n	Lcom/google/protobuf/j0;
    //   1964: aload_3
    //   1965: iload 7
    //   1967: invokestatic 115	com/google/protobuf/w0:U	(I)J
    //   1970: invokevirtual 397	com/google/protobuf/j0:e	(Ljava/lang/Object;J)Ljava/util/List;
    //   1973: astore 16
    //   1975: aload 13
    //   1977: astore 14
    //   1979: aload 13
    //   1981: astore 15
    //   1983: aload 4
    //   1985: aload 16
    //   1987: invokeinterface 432 2 0
    //   1992: goto -1985 -> 7
    //   1995: aload 13
    //   1997: astore 14
    //   1999: aload 13
    //   2001: astore 15
    //   2003: aload_0
    //   2004: getfield 88	com/google/protobuf/w0:n	Lcom/google/protobuf/j0;
    //   2007: aload_3
    //   2008: iload 7
    //   2010: invokestatic 115	com/google/protobuf/w0:U	(I)J
    //   2013: invokevirtual 397	com/google/protobuf/j0:e	(Ljava/lang/Object;J)Ljava/util/List;
    //   2016: astore 16
    //   2018: aload 13
    //   2020: astore 14
    //   2022: aload 13
    //   2024: astore 15
    //   2026: aload 4
    //   2028: aload 16
    //   2030: invokeinterface 434 2 0
    //   2035: goto -2028 -> 7
    //   2038: aload 13
    //   2040: astore 14
    //   2042: aload 13
    //   2044: astore 15
    //   2046: aload_0
    //   2047: getfield 88	com/google/protobuf/w0:n	Lcom/google/protobuf/j0;
    //   2050: aload_3
    //   2051: iload 7
    //   2053: invokestatic 115	com/google/protobuf/w0:U	(I)J
    //   2056: invokevirtual 397	com/google/protobuf/j0:e	(Ljava/lang/Object;J)Ljava/util/List;
    //   2059: astore 16
    //   2061: goto -638 -> 1423
    //   2064: aload 13
    //   2066: astore 14
    //   2068: aload 13
    //   2070: astore 15
    //   2072: aload_0
    //   2073: getfield 88	com/google/protobuf/w0:n	Lcom/google/protobuf/j0;
    //   2076: aload_3
    //   2077: iload 7
    //   2079: invokestatic 115	com/google/protobuf/w0:U	(I)J
    //   2082: invokevirtual 397	com/google/protobuf/j0:e	(Ljava/lang/Object;J)Ljava/util/List;
    //   2085: astore 16
    //   2087: goto -621 -> 1466
    //   2090: aload 13
    //   2092: astore 14
    //   2094: aload 13
    //   2096: astore 15
    //   2098: aload_0
    //   2099: getfield 88	com/google/protobuf/w0:n	Lcom/google/protobuf/j0;
    //   2102: aload_3
    //   2103: iload 7
    //   2105: invokestatic 115	com/google/protobuf/w0:U	(I)J
    //   2108: invokevirtual 397	com/google/protobuf/j0:e	(Ljava/lang/Object;J)Ljava/util/List;
    //   2111: astore 16
    //   2113: goto -604 -> 1509
    //   2116: aload 13
    //   2118: astore 14
    //   2120: aload 13
    //   2122: astore 15
    //   2124: aload_0
    //   2125: getfield 88	com/google/protobuf/w0:n	Lcom/google/protobuf/j0;
    //   2128: aload_3
    //   2129: iload 7
    //   2131: invokestatic 115	com/google/protobuf/w0:U	(I)J
    //   2134: invokevirtual 397	com/google/protobuf/j0:e	(Ljava/lang/Object;J)Ljava/util/List;
    //   2137: astore 16
    //   2139: goto -587 -> 1552
    //   2142: aload 13
    //   2144: astore 14
    //   2146: aload 13
    //   2148: astore 15
    //   2150: aload_0
    //   2151: getfield 88	com/google/protobuf/w0:n	Lcom/google/protobuf/j0;
    //   2154: aload_3
    //   2155: iload 7
    //   2157: invokestatic 115	com/google/protobuf/w0:U	(I)J
    //   2160: invokevirtual 397	com/google/protobuf/j0:e	(Ljava/lang/Object;J)Ljava/util/List;
    //   2163: astore 16
    //   2165: aload 13
    //   2167: astore 14
    //   2169: aload 13
    //   2171: astore 15
    //   2173: aload 4
    //   2175: aload 16
    //   2177: invokeinterface 409 2 0
    //   2182: aload 13
    //   2184: astore 14
    //   2186: aload 13
    //   2188: astore 15
    //   2190: aload_0
    //   2191: iload 6
    //   2193: invokespecial 327	com/google/protobuf/w0:s	(I)Lcom/google/protobuf/c0$e;
    //   2196: pop
    //   2197: goto -570 -> 1627
    //   2200: aload 13
    //   2202: astore 14
    //   2204: aload 13
    //   2206: astore 15
    //   2208: aload_0
    //   2209: getfield 88	com/google/protobuf/w0:n	Lcom/google/protobuf/j0;
    //   2212: aload_3
    //   2213: iload 7
    //   2215: invokestatic 115	com/google/protobuf/w0:U	(I)J
    //   2218: invokevirtual 397	com/google/protobuf/j0:e	(Ljava/lang/Object;J)Ljava/util/List;
    //   2221: astore 16
    //   2223: goto -549 -> 1674
    //   2226: aload 13
    //   2228: astore 14
    //   2230: aload 13
    //   2232: astore 15
    //   2234: aload 4
    //   2236: aload_0
    //   2237: getfield 88	com/google/protobuf/w0:n	Lcom/google/protobuf/j0;
    //   2240: aload_3
    //   2241: iload 7
    //   2243: invokestatic 115	com/google/protobuf/w0:U	(I)J
    //   2246: invokevirtual 397	com/google/protobuf/j0:e	(Ljava/lang/Object;J)Ljava/util/List;
    //   2249: invokeinterface 436 2 0
    //   2254: goto -2247 -> 7
    //   2257: aload 13
    //   2259: astore 14
    //   2261: aload 13
    //   2263: astore 15
    //   2265: aload_0
    //   2266: aload_3
    //   2267: iload 7
    //   2269: aload 4
    //   2271: aload_0
    //   2272: iload 6
    //   2274: invokespecial 173	com/google/protobuf/w0:u	(I)Lcom/google/protobuf/l1;
    //   2277: aload 5
    //   2279: invokespecial 440	com/google/protobuf/w0:j0	(Ljava/lang/Object;ILcom/google/protobuf/j1;Lcom/google/protobuf/l1;Lcom/google/protobuf/r;)V
    //   2282: goto -2275 -> 7
    //   2285: aload 13
    //   2287: astore 14
    //   2289: aload 13
    //   2291: astore 15
    //   2293: aload_0
    //   2294: aload_3
    //   2295: iload 7
    //   2297: aload 4
    //   2299: invokespecial 443	com/google/protobuf/w0:l0	(Ljava/lang/Object;ILcom/google/protobuf/j1;)V
    //   2302: goto -2295 -> 7
    //   2305: aload 13
    //   2307: astore 14
    //   2309: aload 13
    //   2311: astore 15
    //   2313: aload_0
    //   2314: getfield 88	com/google/protobuf/w0:n	Lcom/google/protobuf/j0;
    //   2317: aload_3
    //   2318: iload 7
    //   2320: invokestatic 115	com/google/protobuf/w0:U	(I)J
    //   2323: invokevirtual 397	com/google/protobuf/j0:e	(Ljava/lang/Object;J)Ljava/util/List;
    //   2326: astore 16
    //   2328: goto -611 -> 1717
    //   2331: aload 13
    //   2333: astore 14
    //   2335: aload 13
    //   2337: astore 15
    //   2339: aload_0
    //   2340: getfield 88	com/google/protobuf/w0:n	Lcom/google/protobuf/j0;
    //   2343: aload_3
    //   2344: iload 7
    //   2346: invokestatic 115	com/google/protobuf/w0:U	(I)J
    //   2349: invokevirtual 397	com/google/protobuf/j0:e	(Ljava/lang/Object;J)Ljava/util/List;
    //   2352: astore 16
    //   2354: goto -594 -> 1760
    //   2357: aload 13
    //   2359: astore 14
    //   2361: aload 13
    //   2363: astore 15
    //   2365: aload_0
    //   2366: getfield 88	com/google/protobuf/w0:n	Lcom/google/protobuf/j0;
    //   2369: aload_3
    //   2370: iload 7
    //   2372: invokestatic 115	com/google/protobuf/w0:U	(I)J
    //   2375: invokevirtual 397	com/google/protobuf/j0:e	(Ljava/lang/Object;J)Ljava/util/List;
    //   2378: astore 16
    //   2380: goto -577 -> 1803
    //   2383: aload 13
    //   2385: astore 14
    //   2387: aload 13
    //   2389: astore 15
    //   2391: aload_0
    //   2392: getfield 88	com/google/protobuf/w0:n	Lcom/google/protobuf/j0;
    //   2395: aload_3
    //   2396: iload 7
    //   2398: invokestatic 115	com/google/protobuf/w0:U	(I)J
    //   2401: invokevirtual 397	com/google/protobuf/j0:e	(Ljava/lang/Object;J)Ljava/util/List;
    //   2404: astore 16
    //   2406: goto -560 -> 1846
    //   2409: aload 13
    //   2411: astore 14
    //   2413: aload 13
    //   2415: astore 15
    //   2417: aload_0
    //   2418: getfield 88	com/google/protobuf/w0:n	Lcom/google/protobuf/j0;
    //   2421: aload_3
    //   2422: iload 7
    //   2424: invokestatic 115	com/google/protobuf/w0:U	(I)J
    //   2427: invokevirtual 397	com/google/protobuf/j0:e	(Ljava/lang/Object;J)Ljava/util/List;
    //   2430: astore 16
    //   2432: goto -543 -> 1889
    //   2435: aload 13
    //   2437: astore 14
    //   2439: aload 13
    //   2441: astore 15
    //   2443: aload_0
    //   2444: getfield 88	com/google/protobuf/w0:n	Lcom/google/protobuf/j0;
    //   2447: aload_3
    //   2448: iload 7
    //   2450: invokestatic 115	com/google/protobuf/w0:U	(I)J
    //   2453: invokevirtual 397	com/google/protobuf/j0:e	(Ljava/lang/Object;J)Ljava/util/List;
    //   2456: astore 16
    //   2458: goto -526 -> 1932
    //   2461: aload 13
    //   2463: astore 14
    //   2465: aload 13
    //   2467: astore 15
    //   2469: aload_0
    //   2470: getfield 88	com/google/protobuf/w0:n	Lcom/google/protobuf/j0;
    //   2473: aload_3
    //   2474: iload 7
    //   2476: invokestatic 115	com/google/protobuf/w0:U	(I)J
    //   2479: invokevirtual 397	com/google/protobuf/j0:e	(Ljava/lang/Object;J)Ljava/util/List;
    //   2482: astore 16
    //   2484: goto -509 -> 1975
    //   2487: aload 13
    //   2489: astore 14
    //   2491: aload 13
    //   2493: astore 15
    //   2495: aload_0
    //   2496: getfield 88	com/google/protobuf/w0:n	Lcom/google/protobuf/j0;
    //   2499: aload_3
    //   2500: iload 7
    //   2502: invokestatic 115	com/google/protobuf/w0:U	(I)J
    //   2505: invokevirtual 397	com/google/protobuf/j0:e	(Ljava/lang/Object;J)Ljava/util/List;
    //   2508: astore 16
    //   2510: goto -492 -> 2018
    //   2513: aload 13
    //   2515: astore 14
    //   2517: aload 13
    //   2519: astore 15
    //   2521: aload_0
    //   2522: aload_3
    //   2523: iload 6
    //   2525: invokespecial 161	com/google/protobuf/w0:B	(Ljava/lang/Object;I)Z
    //   2528: ifeq +74 -> 2602
    //   2531: aload 13
    //   2533: astore 14
    //   2535: aload 13
    //   2537: astore 15
    //   2539: aload_3
    //   2540: iload 7
    //   2542: invokestatic 115	com/google/protobuf/w0:U	(I)J
    //   2545: invokestatic 125	com/google/protobuf/x1:E	(Ljava/lang/Object;J)Ljava/lang/Object;
    //   2548: aload 4
    //   2550: aload_0
    //   2551: iload 6
    //   2553: invokespecial 173	com/google/protobuf/w0:u	(I)Lcom/google/protobuf/l1;
    //   2556: aload 5
    //   2558: invokeinterface 293 3 0
    //   2563: invokestatic 342	com/google/protobuf/c0:h	(Ljava/lang/Object;Ljava/lang/Object;)Ljava/lang/Object;
    //   2566: astore 16
    //   2568: aload 13
    //   2570: astore 14
    //   2572: aload 13
    //   2574: astore 15
    //   2576: iload 7
    //   2578: invokestatic 115	com/google/protobuf/w0:U	(I)J
    //   2581: lstore 11
    //   2583: aload 13
    //   2585: astore 14
    //   2587: aload 13
    //   2589: astore 15
    //   2591: aload_3
    //   2592: lload 11
    //   2594: aload 16
    //   2596: invokestatic 297	com/google/protobuf/x1:S	(Ljava/lang/Object;JLjava/lang/Object;)V
    //   2599: goto -2592 -> 7
    //   2602: aload 13
    //   2604: astore 14
    //   2606: aload 13
    //   2608: astore 15
    //   2610: aload_3
    //   2611: iload 7
    //   2613: invokestatic 115	com/google/protobuf/w0:U	(I)J
    //   2616: aload 4
    //   2618: aload_0
    //   2619: iload 6
    //   2621: invokespecial 173	com/google/protobuf/w0:u	(I)Lcom/google/protobuf/l1;
    //   2624: aload 5
    //   2626: invokeinterface 293 3 0
    //   2631: invokestatic 297	com/google/protobuf/x1:S	(Ljava/lang/Object;JLjava/lang/Object;)V
    //   2634: aload 13
    //   2636: astore 14
    //   2638: aload 13
    //   2640: astore 15
    //   2642: aload_0
    //   2643: aload_3
    //   2644: iload 6
    //   2646: invokespecial 346	com/google/protobuf/w0:n0	(Ljava/lang/Object;I)V
    //   2649: goto -2642 -> 7
    //   2652: aload 13
    //   2654: astore 14
    //   2656: aload 13
    //   2658: astore 15
    //   2660: aload_3
    //   2661: iload 7
    //   2663: invokestatic 115	com/google/protobuf/w0:U	(I)J
    //   2666: aload 4
    //   2668: invokeinterface 304 1 0
    //   2673: invokestatic 447	com/google/protobuf/x1:R	(Ljava/lang/Object;JJ)V
    //   2676: goto -42 -> 2634
    //   2679: aload 13
    //   2681: astore 14
    //   2683: aload 13
    //   2685: astore 15
    //   2687: aload_3
    //   2688: iload 7
    //   2690: invokestatic 115	com/google/protobuf/w0:U	(I)J
    //   2693: aload 4
    //   2695: invokeinterface 312 1 0
    //   2700: invokestatic 451	com/google/protobuf/x1:Q	(Ljava/lang/Object;JI)V
    //   2703: goto -69 -> 2634
    //   2706: aload 13
    //   2708: astore 14
    //   2710: aload 13
    //   2712: astore 15
    //   2714: aload_3
    //   2715: iload 7
    //   2717: invokestatic 115	com/google/protobuf/w0:U	(I)J
    //   2720: aload 4
    //   2722: invokeinterface 320 1 0
    //   2727: invokestatic 447	com/google/protobuf/x1:R	(Ljava/lang/Object;JJ)V
    //   2730: goto -96 -> 2634
    //   2733: aload 13
    //   2735: astore 14
    //   2737: aload 13
    //   2739: astore 15
    //   2741: aload_3
    //   2742: iload 7
    //   2744: invokestatic 115	com/google/protobuf/w0:U	(I)J
    //   2747: aload 4
    //   2749: invokeinterface 322 1 0
    //   2754: invokestatic 451	com/google/protobuf/x1:Q	(Ljava/lang/Object;JI)V
    //   2757: goto -123 -> 2634
    //   2760: aload 13
    //   2762: astore 14
    //   2764: aload 13
    //   2766: astore 15
    //   2768: aload 4
    //   2770: invokeinterface 324 1 0
    //   2775: istore 8
    //   2777: aload 13
    //   2779: astore 14
    //   2781: aload 13
    //   2783: astore 15
    //   2785: aload_0
    //   2786: iload 6
    //   2788: invokespecial 327	com/google/protobuf/w0:s	(I)Lcom/google/protobuf/c0$e;
    //   2791: pop
    //   2792: aload 13
    //   2794: astore 14
    //   2796: aload 13
    //   2798: astore 15
    //   2800: aload_3
    //   2801: iload 7
    //   2803: invokestatic 115	com/google/protobuf/w0:U	(I)J
    //   2806: iload 8
    //   2808: invokestatic 451	com/google/protobuf/x1:Q	(Ljava/lang/Object;JI)V
    //   2811: goto -177 -> 2634
    //   2814: aload 13
    //   2816: astore 14
    //   2818: aload 13
    //   2820: astore 15
    //   2822: aload_3
    //   2823: iload 7
    //   2825: invokestatic 115	com/google/protobuf/w0:U	(I)J
    //   2828: aload 4
    //   2830: invokeinterface 329 1 0
    //   2835: invokestatic 451	com/google/protobuf/x1:Q	(Ljava/lang/Object;JI)V
    //   2838: goto -204 -> 2634
    //   2841: aload 13
    //   2843: astore 14
    //   2845: aload 13
    //   2847: astore 15
    //   2849: aload_3
    //   2850: iload 7
    //   2852: invokestatic 115	com/google/protobuf/w0:U	(I)J
    //   2855: aload 4
    //   2857: invokeinterface 332 1 0
    //   2862: invokestatic 297	com/google/protobuf/x1:S	(Ljava/lang/Object;JLjava/lang/Object;)V
    //   2865: goto -231 -> 2634
    //   2868: aload 13
    //   2870: astore 14
    //   2872: aload 13
    //   2874: astore 15
    //   2876: aload_0
    //   2877: aload_3
    //   2878: iload 6
    //   2880: invokespecial 161	com/google/protobuf/w0:B	(Ljava/lang/Object;I)Z
    //   2883: ifeq +58 -> 2941
    //   2886: aload 13
    //   2888: astore 14
    //   2890: aload 13
    //   2892: astore 15
    //   2894: aload_3
    //   2895: iload 7
    //   2897: invokestatic 115	com/google/protobuf/w0:U	(I)J
    //   2900: invokestatic 125	com/google/protobuf/x1:E	(Ljava/lang/Object;J)Ljava/lang/Object;
    //   2903: aload 4
    //   2905: aload_0
    //   2906: iload 6
    //   2908: invokespecial 173	com/google/protobuf/w0:u	(I)Lcom/google/protobuf/l1;
    //   2911: aload 5
    //   2913: invokeinterface 337 3 0
    //   2918: invokestatic 342	com/google/protobuf/c0:h	(Ljava/lang/Object;Ljava/lang/Object;)Ljava/lang/Object;
    //   2921: astore 16
    //   2923: aload 13
    //   2925: astore 14
    //   2927: aload 13
    //   2929: astore 15
    //   2931: iload 7
    //   2933: invokestatic 115	com/google/protobuf/w0:U	(I)J
    //   2936: lstore 11
    //   2938: goto -355 -> 2583
    //   2941: aload 13
    //   2943: astore 14
    //   2945: aload 13
    //   2947: astore 15
    //   2949: aload_3
    //   2950: iload 7
    //   2952: invokestatic 115	com/google/protobuf/w0:U	(I)J
    //   2955: aload 4
    //   2957: aload_0
    //   2958: iload 6
    //   2960: invokespecial 173	com/google/protobuf/w0:u	(I)Lcom/google/protobuf/l1;
    //   2963: aload 5
    //   2965: invokeinterface 337 3 0
    //   2970: invokestatic 297	com/google/protobuf/x1:S	(Ljava/lang/Object;JLjava/lang/Object;)V
    //   2973: goto -339 -> 2634
    //   2976: aload 13
    //   2978: astore 14
    //   2980: aload 13
    //   2982: astore 15
    //   2984: aload_0
    //   2985: aload_3
    //   2986: iload 7
    //   2988: aload 4
    //   2990: invokespecial 350	com/google/protobuf/w0:k0	(Ljava/lang/Object;ILcom/google/protobuf/j1;)V
    //   2993: goto -359 -> 2634
    //   2996: aload 13
    //   2998: astore 14
    //   3000: aload 13
    //   3002: astore 15
    //   3004: aload_3
    //   3005: iload 7
    //   3007: invokestatic 115	com/google/protobuf/w0:U	(I)J
    //   3010: aload 4
    //   3012: invokeinterface 352 1 0
    //   3017: invokestatic 454	com/google/protobuf/x1:I	(Ljava/lang/Object;JZ)V
    //   3020: goto -386 -> 2634
    //   3023: aload 13
    //   3025: astore 14
    //   3027: aload 13
    //   3029: astore 15
    //   3031: aload_3
    //   3032: iload 7
    //   3034: invokestatic 115	com/google/protobuf/w0:U	(I)J
    //   3037: aload 4
    //   3039: invokeinterface 359 1 0
    //   3044: invokestatic 451	com/google/protobuf/x1:Q	(Ljava/lang/Object;JI)V
    //   3047: goto -413 -> 2634
    //   3050: aload 13
    //   3052: astore 14
    //   3054: aload 13
    //   3056: astore 15
    //   3058: aload_3
    //   3059: iload 7
    //   3061: invokestatic 115	com/google/protobuf/w0:U	(I)J
    //   3064: aload 4
    //   3066: invokeinterface 361 1 0
    //   3071: invokestatic 447	com/google/protobuf/x1:R	(Ljava/lang/Object;JJ)V
    //   3074: goto -440 -> 2634
    //   3077: aload 13
    //   3079: astore 14
    //   3081: aload 13
    //   3083: astore 15
    //   3085: aload_3
    //   3086: iload 7
    //   3088: invokestatic 115	com/google/protobuf/w0:U	(I)J
    //   3091: aload 4
    //   3093: invokeinterface 363 1 0
    //   3098: invokestatic 451	com/google/protobuf/x1:Q	(Ljava/lang/Object;JI)V
    //   3101: goto -467 -> 2634
    //   3104: aload 13
    //   3106: astore 14
    //   3108: aload 13
    //   3110: astore 15
    //   3112: aload_3
    //   3113: iload 7
    //   3115: invokestatic 115	com/google/protobuf/w0:U	(I)J
    //   3118: aload 4
    //   3120: invokeinterface 365 1 0
    //   3125: invokestatic 447	com/google/protobuf/x1:R	(Ljava/lang/Object;JJ)V
    //   3128: goto -494 -> 2634
    //   3131: aload 13
    //   3133: astore 14
    //   3135: aload 13
    //   3137: astore 15
    //   3139: aload_3
    //   3140: iload 7
    //   3142: invokestatic 115	com/google/protobuf/w0:U	(I)J
    //   3145: aload 4
    //   3147: invokeinterface 367 1 0
    //   3152: invokestatic 447	com/google/protobuf/x1:R	(Ljava/lang/Object;JJ)V
    //   3155: goto -521 -> 2634
    //   3158: aload 13
    //   3160: astore 14
    //   3162: aload 13
    //   3164: astore 15
    //   3166: aload_3
    //   3167: iload 7
    //   3169: invokestatic 115	com/google/protobuf/w0:U	(I)J
    //   3172: aload 4
    //   3174: invokeinterface 371 1 0
    //   3179: invokestatic 457	com/google/protobuf/x1:P	(Ljava/lang/Object;JF)V
    //   3182: goto -548 -> 2634
    //   3185: aload 13
    //   3187: astore 14
    //   3189: aload 13
    //   3191: astore 15
    //   3193: aload_3
    //   3194: iload 7
    //   3196: invokestatic 115	com/google/protobuf/w0:U	(I)J
    //   3199: aload 4
    //   3201: invokeinterface 380 1 0
    //   3206: invokestatic 460	com/google/protobuf/x1:O	(Ljava/lang/Object;JD)V
    //   3209: goto -575 -> 2634
    //   3212: aload 16
    //   3214: astore 14
    //   3216: aload 16
    //   3218: astore 15
    //   3220: aload_1
    //   3221: aload 16
    //   3223: aload 4
    //   3225: invokevirtual 288	com/google/protobuf/t1:m	(Ljava/lang/Object;Lcom/google/protobuf/j1;)Z
    //   3228: istore 10
    //   3230: aload 16
    //   3232: astore 13
    //   3234: iload 10
    //   3236: ifne -3229 -> 7
    //   3239: aload_0
    //   3240: getfield 82	com/google/protobuf/w0:k	I
    //   3243: istore 6
    //   3245: iload 6
    //   3247: aload_0
    //   3248: getfield 84	com/google/protobuf/w0:l	I
    //   3251: if_icmpge +29 -> 3280
    //   3254: aload_0
    //   3255: aload_3
    //   3256: aload_0
    //   3257: getfield 80	com/google/protobuf/w0:j	[I
    //   3260: iload 6
    //   3262: iaload
    //   3263: aload 16
    //   3265: aload_1
    //   3266: invokespecial 263	com/google/protobuf/w0:q	(Ljava/lang/Object;ILjava/lang/Object;Lcom/google/protobuf/t1;)Ljava/lang/Object;
    //   3269: astore 16
    //   3271: iload 6
    //   3273: iconst_1
    //   3274: iadd
    //   3275: istore 6
    //   3277: goto -32 -> 3245
    //   3280: aload 16
    //   3282: ifnull +10 -> 3292
    //   3285: aload_1
    //   3286: aload_3
    //   3287: aload 16
    //   3289: invokevirtual 268	com/google/protobuf/t1:o	(Ljava/lang/Object;Ljava/lang/Object;)V
    //   3292: return
    //   3293: aload 15
    //   3295: astore 14
    //   3297: aload_1
    //   3298: aload 4
    //   3300: invokevirtual 280	com/google/protobuf/t1:q	(Lcom/google/protobuf/j1;)Z
    //   3303: ifeq +79 -> 3382
    //   3306: aload 15
    //   3308: astore 14
    //   3310: aload 4
    //   3312: invokeinterface 282 1 0
    //   3317: istore 10
    //   3319: aload 15
    //   3321: astore 13
    //   3323: iload 10
    //   3325: ifne -3318 -> 7
    //   3328: aload_0
    //   3329: getfield 82	com/google/protobuf/w0:k	I
    //   3332: istore 6
    //   3334: iload 6
    //   3336: aload_0
    //   3337: getfield 84	com/google/protobuf/w0:l	I
    //   3340: if_icmpge +29 -> 3369
    //   3343: aload_0
    //   3344: aload_3
    //   3345: aload_0
    //   3346: getfield 80	com/google/protobuf/w0:j	[I
    //   3349: iload 6
    //   3351: iaload
    //   3352: aload 15
    //   3354: aload_1
    //   3355: invokespecial 263	com/google/protobuf/w0:q	(Ljava/lang/Object;ILjava/lang/Object;Lcom/google/protobuf/t1;)Ljava/lang/Object;
    //   3358: astore 15
    //   3360: iload 6
    //   3362: iconst_1
    //   3363: iadd
    //   3364: istore 6
    //   3366: goto -32 -> 3334
    //   3369: aload 15
    //   3371: ifnull +10 -> 3381
    //   3374: aload_1
    //   3375: aload_3
    //   3376: aload 15
    //   3378: invokevirtual 268	com/google/protobuf/t1:o	(Ljava/lang/Object;Ljava/lang/Object;)V
    //   3381: return
    //   3382: aload 15
    //   3384: astore 16
    //   3386: aload 15
    //   3388: ifnonnull +14 -> 3402
    //   3391: aload 15
    //   3393: astore 14
    //   3395: aload_1
    //   3396: aload_3
    //   3397: invokevirtual 285	com/google/protobuf/t1:f	(Ljava/lang/Object;)Ljava/lang/Object;
    //   3400: astore 16
    //   3402: aload 16
    //   3404: astore 14
    //   3406: aload_1
    //   3407: aload 16
    //   3409: aload 4
    //   3411: invokevirtual 288	com/google/protobuf/t1:m	(Ljava/lang/Object;Lcom/google/protobuf/j1;)Z
    //   3414: istore 10
    //   3416: aload 16
    //   3418: astore 13
    //   3420: iload 10
    //   3422: ifne -3415 -> 7
    //   3425: aload_0
    //   3426: getfield 82	com/google/protobuf/w0:k	I
    //   3429: istore 6
    //   3431: iload 6
    //   3433: aload_0
    //   3434: getfield 84	com/google/protobuf/w0:l	I
    //   3437: if_icmpge +29 -> 3466
    //   3440: aload_0
    //   3441: aload_3
    //   3442: aload_0
    //   3443: getfield 80	com/google/protobuf/w0:j	[I
    //   3446: iload 6
    //   3448: iaload
    //   3449: aload 16
    //   3451: aload_1
    //   3452: invokespecial 263	com/google/protobuf/w0:q	(Ljava/lang/Object;ILjava/lang/Object;Lcom/google/protobuf/t1;)Ljava/lang/Object;
    //   3455: astore 16
    //   3457: iload 6
    //   3459: iconst_1
    //   3460: iadd
    //   3461: istore 6
    //   3463: goto -32 -> 3431
    //   3466: aload 16
    //   3468: ifnull +10 -> 3478
    //   3471: aload_1
    //   3472: aload_3
    //   3473: aload 16
    //   3475: invokevirtual 268	com/google/protobuf/t1:o	(Ljava/lang/Object;Ljava/lang/Object;)V
    //   3478: return
    //   3479: astore_2
    //   3480: aload_0
    //   3481: getfield 82	com/google/protobuf/w0:k	I
    //   3484: istore 6
    //   3486: iload 6
    //   3488: aload_0
    //   3489: getfield 84	com/google/protobuf/w0:l	I
    //   3492: if_icmpge +29 -> 3521
    //   3495: aload_0
    //   3496: aload_3
    //   3497: aload_0
    //   3498: getfield 80	com/google/protobuf/w0:j	[I
    //   3501: iload 6
    //   3503: iaload
    //   3504: aload 14
    //   3506: aload_1
    //   3507: invokespecial 263	com/google/protobuf/w0:q	(Ljava/lang/Object;ILjava/lang/Object;Lcom/google/protobuf/t1;)Ljava/lang/Object;
    //   3510: astore 14
    //   3512: iload 6
    //   3514: iconst_1
    //   3515: iadd
    //   3516: istore 6
    //   3518: goto -32 -> 3486
    //   3521: aload 14
    //   3523: ifnull +10 -> 3533
    //   3526: aload_1
    //   3527: aload_3
    //   3528: aload 14
    //   3530: invokevirtual 268	com/google/protobuf/t1:o	(Ljava/lang/Object;Ljava/lang/Object;)V
    //   3533: aload_2
    //   3534: athrow
    //   3535: astore 13
    //   3537: goto -244 -> 3293
    //   3540: goto -2900 -> 640
    //   3543: goto -331 -> 3212
    // Local variable table:
    //   start	length	slot	name	signature
    //   0	3546	0	this	w0
    //   0	3546	1	paramT1	t1
    //   0	3546	2	paramS	s
    //   0	3546	3	paramObject	Object
    //   0	3546	4	paramJ1	j1
    //   0	3546	5	paramR	r
    //   30	3487	6	i1	int
    //   335	2860	7	i2	int
    //   18	2789	8	i3	int
    //   853	32	9	i4	int
    //   253	3168	10	bool	boolean
    //   2581	356	11	l1	long
    //   1	3418	13	localObject1	Object
    //   3535	1	13	localA	d0.a
    //   9	3520	14	localObject2	Object
    //   111	3281	15	localObject3	Object
    //   141	3333	16	localObject4	Object
    //   5	178	17	localObject5	Object
    // Exception table:
    //   from	to	target	type
    //   11	20	3479	finally
    //   24	32	3479	finally
    //   103	110	3479	finally
    //   120	134	3479	finally
    //   152	159	3479	finally
    //   163	180	3479	finally
    //   191	200	3479	finally
    //   208	218	3479	finally
    //   234	241	3479	finally
    //   245	255	3479	finally
    //   329	337	3479	finally
    //   345	640	3479	finally
    //   657	663	3479	finally
    //   674	698	3479	finally
    //   706	715	3479	finally
    //   726	745	3479	finally
    //   756	775	3479	finally
    //   786	805	3479	finally
    //   816	835	3479	finally
    //   846	855	3479	finally
    //   863	870	3479	finally
    //   878	892	3479	finally
    //   903	922	3479	finally
    //   933	949	3479	finally
    //   960	972	3479	finally
    //   980	1009	3479	finally
    //   1017	1028	3479	finally
    //   1039	1063	3479	finally
    //   1071	1078	3479	finally
    //   1089	1098	3479	finally
    //   1109	1128	3479	finally
    //   1139	1158	3479	finally
    //   1169	1188	3479	finally
    //   1199	1218	3479	finally
    //   1229	1248	3479	finally
    //   1259	1278	3479	finally
    //   1289	1308	3479	finally
    //   1319	1338	3479	finally
    //   1349	1366	3479	finally
    //   1377	1397	3479	finally
    //   1408	1423	3479	finally
    //   1431	1440	3479	finally
    //   1451	1466	3479	finally
    //   1474	1483	3479	finally
    //   1494	1509	3479	finally
    //   1517	1526	3479	finally
    //   1537	1552	3479	finally
    //   1560	1569	3479	finally
    //   1580	1595	3479	finally
    //   1603	1612	3479	finally
    //   1620	1627	3479	finally
    //   1635	1648	3479	finally
    //   1659	1674	3479	finally
    //   1682	1691	3479	finally
    //   1702	1717	3479	finally
    //   1725	1734	3479	finally
    //   1745	1760	3479	finally
    //   1768	1777	3479	finally
    //   1788	1803	3479	finally
    //   1811	1820	3479	finally
    //   1831	1846	3479	finally
    //   1854	1863	3479	finally
    //   1874	1889	3479	finally
    //   1897	1906	3479	finally
    //   1917	1932	3479	finally
    //   1940	1949	3479	finally
    //   1960	1975	3479	finally
    //   1983	1992	3479	finally
    //   2003	2018	3479	finally
    //   2026	2035	3479	finally
    //   2046	2061	3479	finally
    //   2072	2087	3479	finally
    //   2098	2113	3479	finally
    //   2124	2139	3479	finally
    //   2150	2165	3479	finally
    //   2173	2182	3479	finally
    //   2190	2197	3479	finally
    //   2208	2223	3479	finally
    //   2234	2254	3479	finally
    //   2265	2282	3479	finally
    //   2293	2302	3479	finally
    //   2313	2328	3479	finally
    //   2339	2354	3479	finally
    //   2365	2380	3479	finally
    //   2391	2406	3479	finally
    //   2417	2432	3479	finally
    //   2443	2458	3479	finally
    //   2469	2484	3479	finally
    //   2495	2510	3479	finally
    //   2521	2531	3479	finally
    //   2539	2568	3479	finally
    //   2576	2583	3479	finally
    //   2591	2599	3479	finally
    //   2610	2634	3479	finally
    //   2642	2649	3479	finally
    //   2660	2676	3479	finally
    //   2687	2703	3479	finally
    //   2714	2730	3479	finally
    //   2741	2757	3479	finally
    //   2768	2777	3479	finally
    //   2785	2792	3479	finally
    //   2800	2811	3479	finally
    //   2822	2838	3479	finally
    //   2849	2865	3479	finally
    //   2876	2886	3479	finally
    //   2894	2923	3479	finally
    //   2931	2938	3479	finally
    //   2949	2973	3479	finally
    //   2984	2993	3479	finally
    //   3004	3020	3479	finally
    //   3031	3047	3479	finally
    //   3058	3074	3479	finally
    //   3085	3101	3479	finally
    //   3112	3128	3479	finally
    //   3139	3155	3479	finally
    //   3166	3182	3479	finally
    //   3193	3209	3479	finally
    //   3220	3230	3479	finally
    //   3297	3306	3479	finally
    //   3310	3319	3479	finally
    //   3395	3402	3479	finally
    //   3406	3416	3479	finally
    //   345	640	3535	com/google/protobuf/d0$a
    //   657	663	3535	com/google/protobuf/d0$a
    //   674	698	3535	com/google/protobuf/d0$a
    //   706	715	3535	com/google/protobuf/d0$a
    //   726	745	3535	com/google/protobuf/d0$a
    //   756	775	3535	com/google/protobuf/d0$a
    //   786	805	3535	com/google/protobuf/d0$a
    //   816	835	3535	com/google/protobuf/d0$a
    //   846	855	3535	com/google/protobuf/d0$a
    //   863	870	3535	com/google/protobuf/d0$a
    //   878	892	3535	com/google/protobuf/d0$a
    //   903	922	3535	com/google/protobuf/d0$a
    //   933	949	3535	com/google/protobuf/d0$a
    //   960	972	3535	com/google/protobuf/d0$a
    //   980	1009	3535	com/google/protobuf/d0$a
    //   1017	1028	3535	com/google/protobuf/d0$a
    //   1039	1063	3535	com/google/protobuf/d0$a
    //   1071	1078	3535	com/google/protobuf/d0$a
    //   1089	1098	3535	com/google/protobuf/d0$a
    //   1109	1128	3535	com/google/protobuf/d0$a
    //   1139	1158	3535	com/google/protobuf/d0$a
    //   1169	1188	3535	com/google/protobuf/d0$a
    //   1199	1218	3535	com/google/protobuf/d0$a
    //   1229	1248	3535	com/google/protobuf/d0$a
    //   1259	1278	3535	com/google/protobuf/d0$a
    //   1289	1308	3535	com/google/protobuf/d0$a
    //   1319	1338	3535	com/google/protobuf/d0$a
    //   1349	1366	3535	com/google/protobuf/d0$a
    //   1377	1397	3535	com/google/protobuf/d0$a
    //   1408	1423	3535	com/google/protobuf/d0$a
    //   1431	1440	3535	com/google/protobuf/d0$a
    //   1451	1466	3535	com/google/protobuf/d0$a
    //   1474	1483	3535	com/google/protobuf/d0$a
    //   1494	1509	3535	com/google/protobuf/d0$a
    //   1517	1526	3535	com/google/protobuf/d0$a
    //   1537	1552	3535	com/google/protobuf/d0$a
    //   1560	1569	3535	com/google/protobuf/d0$a
    //   1580	1595	3535	com/google/protobuf/d0$a
    //   1603	1612	3535	com/google/protobuf/d0$a
    //   1620	1627	3535	com/google/protobuf/d0$a
    //   1635	1648	3535	com/google/protobuf/d0$a
    //   1659	1674	3535	com/google/protobuf/d0$a
    //   1682	1691	3535	com/google/protobuf/d0$a
    //   1702	1717	3535	com/google/protobuf/d0$a
    //   1725	1734	3535	com/google/protobuf/d0$a
    //   1745	1760	3535	com/google/protobuf/d0$a
    //   1768	1777	3535	com/google/protobuf/d0$a
    //   1788	1803	3535	com/google/protobuf/d0$a
    //   1811	1820	3535	com/google/protobuf/d0$a
    //   1831	1846	3535	com/google/protobuf/d0$a
    //   1854	1863	3535	com/google/protobuf/d0$a
    //   1874	1889	3535	com/google/protobuf/d0$a
    //   1897	1906	3535	com/google/protobuf/d0$a
    //   1917	1932	3535	com/google/protobuf/d0$a
    //   1940	1949	3535	com/google/protobuf/d0$a
    //   1960	1975	3535	com/google/protobuf/d0$a
    //   1983	1992	3535	com/google/protobuf/d0$a
    //   2003	2018	3535	com/google/protobuf/d0$a
    //   2026	2035	3535	com/google/protobuf/d0$a
    //   2046	2061	3535	com/google/protobuf/d0$a
    //   2072	2087	3535	com/google/protobuf/d0$a
    //   2098	2113	3535	com/google/protobuf/d0$a
    //   2124	2139	3535	com/google/protobuf/d0$a
    //   2150	2165	3535	com/google/protobuf/d0$a
    //   2173	2182	3535	com/google/protobuf/d0$a
    //   2190	2197	3535	com/google/protobuf/d0$a
    //   2208	2223	3535	com/google/protobuf/d0$a
    //   2234	2254	3535	com/google/protobuf/d0$a
    //   2265	2282	3535	com/google/protobuf/d0$a
    //   2293	2302	3535	com/google/protobuf/d0$a
    //   2313	2328	3535	com/google/protobuf/d0$a
    //   2339	2354	3535	com/google/protobuf/d0$a
    //   2365	2380	3535	com/google/protobuf/d0$a
    //   2391	2406	3535	com/google/protobuf/d0$a
    //   2417	2432	3535	com/google/protobuf/d0$a
    //   2443	2458	3535	com/google/protobuf/d0$a
    //   2469	2484	3535	com/google/protobuf/d0$a
    //   2495	2510	3535	com/google/protobuf/d0$a
    //   2521	2531	3535	com/google/protobuf/d0$a
    //   2539	2568	3535	com/google/protobuf/d0$a
    //   2576	2583	3535	com/google/protobuf/d0$a
    //   2591	2599	3535	com/google/protobuf/d0$a
    //   2610	2634	3535	com/google/protobuf/d0$a
    //   2642	2649	3535	com/google/protobuf/d0$a
    //   2660	2676	3535	com/google/protobuf/d0$a
    //   2687	2703	3535	com/google/protobuf/d0$a
    //   2714	2730	3535	com/google/protobuf/d0$a
    //   2741	2757	3535	com/google/protobuf/d0$a
    //   2768	2777	3535	com/google/protobuf/d0$a
    //   2785	2792	3535	com/google/protobuf/d0$a
    //   2800	2811	3535	com/google/protobuf/d0$a
    //   2822	2838	3535	com/google/protobuf/d0$a
    //   2849	2865	3535	com/google/protobuf/d0$a
    //   2876	2886	3535	com/google/protobuf/d0$a
    //   2894	2923	3535	com/google/protobuf/d0$a
    //   2931	2938	3535	com/google/protobuf/d0$a
    //   2949	2973	3535	com/google/protobuf/d0$a
    //   2984	2993	3535	com/google/protobuf/d0$a
    //   3004	3020	3535	com/google/protobuf/d0$a
    //   3031	3047	3535	com/google/protobuf/d0$a
    //   3058	3074	3535	com/google/protobuf/d0$a
    //   3085	3101	3535	com/google/protobuf/d0$a
    //   3112	3128	3535	com/google/protobuf/d0$a
    //   3139	3155	3535	com/google/protobuf/d0$a
    //   3166	3182	3535	com/google/protobuf/d0$a
    //   3193	3209	3535	com/google/protobuf/d0$a
    //   3220	3230	3535	com/google/protobuf/d0$a
  }
  
  private final void M(Object paramObject1, int paramInt, Object paramObject2, r paramR, j1 paramJ1)
  {
    long l1 = U(r0(paramInt));
    Object localObject2 = x1.E(paramObject1, l1);
    Object localObject1;
    if (localObject2 == null)
    {
      localObject1 = q.b(paramObject2);
      x1.S(paramObject1, l1, localObject1);
    }
    else
    {
      localObject1 = localObject2;
      if (q.d(localObject2))
      {
        localObject1 = q.b(paramObject2);
        q.a(localObject1, localObject2);
        x1.S(paramObject1, l1, localObject1);
      }
    }
    paramJ1.x(q.h(localObject1), q.f(paramObject2), paramR);
  }
  
  private void N(Object paramObject1, Object paramObject2, int paramInt)
  {
    long l1 = U(r0(paramInt));
    if (!B(paramObject2, paramInt)) {
      return;
    }
    Object localObject = x1.E(paramObject1, l1);
    paramObject2 = x1.E(paramObject2, l1);
    if ((localObject != null) && (paramObject2 != null)) {
      paramObject2 = c0.h(localObject, paramObject2);
    } else if (paramObject2 == null) {
      return;
    }
    x1.S(paramObject1, l1, paramObject2);
    n0(paramObject1, paramInt);
  }
  
  private void O(Object paramObject1, Object paramObject2, int paramInt)
  {
    int i1 = r0(paramInt);
    int i2 = T(paramInt);
    long l1 = U(i1);
    if (!H(paramObject2, i2, paramInt)) {
      return;
    }
    Object localObject;
    if (H(paramObject1, i2, paramInt)) {
      localObject = x1.E(paramObject1, l1);
    } else {
      localObject = null;
    }
    paramObject2 = x1.E(paramObject2, l1);
    if ((localObject != null) && (paramObject2 != null)) {
      paramObject2 = c0.h(localObject, paramObject2);
    } else if (paramObject2 == null) {
      return;
    }
    x1.S(paramObject1, l1, paramObject2);
    o0(paramObject1, i2, paramInt);
  }
  
  /* Error */
  private void P(Object paramObject1, Object paramObject2, int paramInt)
  {
    // Byte code:
    //   0: aload_0
    //   1: iload_3
    //   2: invokespecial 111	com/google/protobuf/w0:r0	(I)I
    //   5: istore 4
    //   7: iload 4
    //   9: invokestatic 115	com/google/protobuf/w0:U	(I)J
    //   12: lstore 6
    //   14: aload_0
    //   15: iload_3
    //   16: invokespecial 475	com/google/protobuf/w0:T	(I)I
    //   19: istore 5
    //   21: iload 4
    //   23: invokestatic 118	com/google/protobuf/w0:q0	(I)I
    //   26: tableswitch	default:+290->316, 0:+617->643, 1:+593->619, 2:+569->595, 3:+557->583, 4:+533->559, 5:+521->547, 6:+509->535, 7:+485->511, 8:+461->487, 9:+453->479, 10:+441->467, 11:+429->455, 12:+417->443, 13:+405->431, 14:+393->419, 15:+381->407, 16:+369->395, 17:+453->479, 18:+357->383, 19:+357->383, 20:+357->383, 21:+357->383, 22:+357->383, 23:+357->383, 24:+357->383, 25:+357->383, 26:+357->383, 27:+357->383, 28:+357->383, 29:+357->383, 30:+357->383, 31:+357->383, 32:+357->383, 33:+357->383, 34:+357->383, 35:+357->383, 36:+357->383, 37:+357->383, 38:+357->383, 39:+357->383, 40:+357->383, 41:+357->383, 42:+357->383, 43:+357->383, 44:+357->383, 45:+357->383, 46:+357->383, 47:+357->383, 48:+357->383, 49:+357->383, 50:+345->371, 51:+313->339, 52:+313->339, 53:+313->339, 54:+313->339, 55:+313->339, 56:+313->339, 57:+313->339, 58:+313->339, 59:+313->339, 60:+305->331, 61:+291->317, 62:+291->317, 63:+291->317, 64:+291->317, 65:+291->317, 66:+291->317, 67:+291->317, 68:+305->331
    //   316: return
    //   317: aload_0
    //   318: aload_2
    //   319: iload 5
    //   321: iload_3
    //   322: invokespecial 334	com/google/protobuf/w0:H	(Ljava/lang/Object;II)Z
    //   325: ifeq +345 -> 670
    //   328: goto +22 -> 350
    //   331: aload_0
    //   332: aload_1
    //   333: aload_2
    //   334: iload_3
    //   335: invokespecial 477	com/google/protobuf/w0:O	(Ljava/lang/Object;Ljava/lang/Object;I)V
    //   338: return
    //   339: aload_0
    //   340: aload_2
    //   341: iload 5
    //   343: iload_3
    //   344: invokespecial 334	com/google/protobuf/w0:H	(Ljava/lang/Object;II)Z
    //   347: ifeq +323 -> 670
    //   350: aload_1
    //   351: lload 6
    //   353: aload_2
    //   354: lload 6
    //   356: invokestatic 125	com/google/protobuf/x1:E	(Ljava/lang/Object;J)Ljava/lang/Object;
    //   359: invokestatic 297	com/google/protobuf/x1:S	(Ljava/lang/Object;JLjava/lang/Object;)V
    //   362: aload_0
    //   363: aload_1
    //   364: iload 5
    //   366: iload_3
    //   367: invokespecial 301	com/google/protobuf/w0:o0	(Ljava/lang/Object;II)V
    //   370: return
    //   371: aload_0
    //   372: getfield 96	com/google/protobuf/w0:q	Lcom/google/protobuf/o0;
    //   375: aload_1
    //   376: aload_2
    //   377: lload 6
    //   379: invokestatic 480	com/google/protobuf/n1:F	(Lcom/google/protobuf/o0;Ljava/lang/Object;Ljava/lang/Object;J)V
    //   382: return
    //   383: aload_0
    //   384: getfield 88	com/google/protobuf/w0:n	Lcom/google/protobuf/j0;
    //   387: aload_1
    //   388: aload_2
    //   389: lload 6
    //   391: invokevirtual 483	com/google/protobuf/j0:d	(Ljava/lang/Object;Ljava/lang/Object;J)V
    //   394: return
    //   395: aload_0
    //   396: aload_2
    //   397: iload_3
    //   398: invokespecial 161	com/google/protobuf/w0:B	(Ljava/lang/Object;I)Z
    //   401: ifeq +269 -> 670
    //   404: goto +200 -> 604
    //   407: aload_0
    //   408: aload_2
    //   409: iload_3
    //   410: invokespecial 161	com/google/protobuf/w0:B	(Ljava/lang/Object;I)Z
    //   413: ifeq +257 -> 670
    //   416: goto +36 -> 452
    //   419: aload_0
    //   420: aload_2
    //   421: iload_3
    //   422: invokespecial 161	com/google/protobuf/w0:B	(Ljava/lang/Object;I)Z
    //   425: ifeq +245 -> 670
    //   428: goto +176 -> 604
    //   431: aload_0
    //   432: aload_2
    //   433: iload_3
    //   434: invokespecial 161	com/google/protobuf/w0:B	(Ljava/lang/Object;I)Z
    //   437: ifeq +233 -> 670
    //   440: goto +12 -> 452
    //   443: aload_0
    //   444: aload_2
    //   445: iload_3
    //   446: invokespecial 161	com/google/protobuf/w0:B	(Ljava/lang/Object;I)Z
    //   449: ifeq +221 -> 670
    //   452: goto +116 -> 568
    //   455: aload_0
    //   456: aload_2
    //   457: iload_3
    //   458: invokespecial 161	com/google/protobuf/w0:B	(Ljava/lang/Object;I)Z
    //   461: ifeq +209 -> 670
    //   464: goto +104 -> 568
    //   467: aload_0
    //   468: aload_2
    //   469: iload_3
    //   470: invokespecial 161	com/google/protobuf/w0:B	(Ljava/lang/Object;I)Z
    //   473: ifeq +197 -> 670
    //   476: goto +20 -> 496
    //   479: aload_0
    //   480: aload_1
    //   481: aload_2
    //   482: iload_3
    //   483: invokespecial 485	com/google/protobuf/w0:N	(Ljava/lang/Object;Ljava/lang/Object;I)V
    //   486: return
    //   487: aload_0
    //   488: aload_2
    //   489: iload_3
    //   490: invokespecial 161	com/google/protobuf/w0:B	(Ljava/lang/Object;I)Z
    //   493: ifeq +177 -> 670
    //   496: aload_1
    //   497: lload 6
    //   499: aload_2
    //   500: lload 6
    //   502: invokestatic 125	com/google/protobuf/x1:E	(Ljava/lang/Object;J)Ljava/lang/Object;
    //   505: invokestatic 297	com/google/protobuf/x1:S	(Ljava/lang/Object;JLjava/lang/Object;)V
    //   508: goto +156 -> 664
    //   511: aload_0
    //   512: aload_2
    //   513: iload_3
    //   514: invokespecial 161	com/google/protobuf/w0:B	(Ljava/lang/Object;I)Z
    //   517: ifeq +153 -> 670
    //   520: aload_1
    //   521: lload 6
    //   523: aload_2
    //   524: lload 6
    //   526: invokestatic 150	com/google/protobuf/x1:r	(Ljava/lang/Object;J)Z
    //   529: invokestatic 454	com/google/protobuf/x1:I	(Ljava/lang/Object;JZ)V
    //   532: goto +132 -> 664
    //   535: aload_0
    //   536: aload_2
    //   537: iload_3
    //   538: invokespecial 161	com/google/protobuf/w0:B	(Ljava/lang/Object;I)Z
    //   541: ifeq +129 -> 670
    //   544: goto +24 -> 568
    //   547: aload_0
    //   548: aload_2
    //   549: iload_3
    //   550: invokespecial 161	com/google/protobuf/w0:B	(Ljava/lang/Object;I)Z
    //   553: ifeq +117 -> 670
    //   556: goto +48 -> 604
    //   559: aload_0
    //   560: aload_2
    //   561: iload_3
    //   562: invokespecial 161	com/google/protobuf/w0:B	(Ljava/lang/Object;I)Z
    //   565: ifeq +105 -> 670
    //   568: aload_1
    //   569: lload 6
    //   571: aload_2
    //   572: lload 6
    //   574: invokestatic 132	com/google/protobuf/x1:A	(Ljava/lang/Object;J)I
    //   577: invokestatic 451	com/google/protobuf/x1:Q	(Ljava/lang/Object;JI)V
    //   580: goto +84 -> 664
    //   583: aload_0
    //   584: aload_2
    //   585: iload_3
    //   586: invokespecial 161	com/google/protobuf/w0:B	(Ljava/lang/Object;I)Z
    //   589: ifeq +81 -> 670
    //   592: goto +12 -> 604
    //   595: aload_0
    //   596: aload_2
    //   597: iload_3
    //   598: invokespecial 161	com/google/protobuf/w0:B	(Ljava/lang/Object;I)Z
    //   601: ifeq +69 -> 670
    //   604: aload_1
    //   605: lload 6
    //   607: aload_2
    //   608: lload 6
    //   610: invokestatic 129	com/google/protobuf/x1:C	(Ljava/lang/Object;J)J
    //   613: invokestatic 447	com/google/protobuf/x1:R	(Ljava/lang/Object;JJ)V
    //   616: goto +48 -> 664
    //   619: aload_0
    //   620: aload_2
    //   621: iload_3
    //   622: invokespecial 161	com/google/protobuf/w0:B	(Ljava/lang/Object;I)Z
    //   625: ifeq +45 -> 670
    //   628: aload_1
    //   629: lload 6
    //   631: aload_2
    //   632: lload 6
    //   634: invokestatic 154	com/google/protobuf/x1:z	(Ljava/lang/Object;J)F
    //   637: invokestatic 457	com/google/protobuf/x1:P	(Ljava/lang/Object;JF)V
    //   640: goto +24 -> 664
    //   643: aload_0
    //   644: aload_2
    //   645: iload_3
    //   646: invokespecial 161	com/google/protobuf/w0:B	(Ljava/lang/Object;I)Z
    //   649: ifeq +21 -> 670
    //   652: aload_1
    //   653: lload 6
    //   655: aload_2
    //   656: lload 6
    //   658: invokestatic 158	com/google/protobuf/x1:y	(Ljava/lang/Object;J)D
    //   661: invokestatic 460	com/google/protobuf/x1:O	(Ljava/lang/Object;JD)V
    //   664: aload_0
    //   665: aload_1
    //   666: iload_3
    //   667: invokespecial 346	com/google/protobuf/w0:n0	(Ljava/lang/Object;I)V
    //   670: return
    // Local variable table:
    //   start	length	slot	name	signature
    //   0	671	0	this	w0
    //   0	671	1	paramObject1	Object
    //   0	671	2	paramObject2	Object
    //   0	671	3	paramInt	int
    //   5	17	4	i1	int
    //   19	346	5	i2	int
    //   12	645	6	l1	long
  }
  
  static w0 Q(Class paramClass, r0 paramR0, y0 paramY0, j0 paramJ0, t1 paramT1, s paramS, o0 paramO0)
  {
    if ((paramR0 instanceof i1)) {
      return S((i1)paramR0, paramY0, paramJ0, paramT1, paramS, paramO0);
    }
    b.a(paramR0);
    return R(null, paramY0, paramJ0, paramT1, paramS, paramO0);
  }
  
  static w0 R(p1 paramP1, y0 paramY0, j0 paramJ0, t1 paramT1, s paramS, o0 paramO0)
  {
    throw null;
  }
  
  static w0 S(i1 paramI1, y0 paramY0, j0 paramJ0, t1 paramT1, s paramS, o0 paramO0)
  {
    boolean bool;
    if (paramI1.b() == f1.f) {
      bool = true;
    } else {
      bool = false;
    }
    String str = paramI1.e();
    int i15 = str.length();
    if (str.charAt(0) >= 55296) {
      for (i1 = 1;; i1 = i3)
      {
        i3 = i1 + 1;
        i2 = i3;
        if (str.charAt(i1) < 55296) {
          break;
        }
      }
    }
    int i2 = 1;
    int i1 = i2 + 1;
    int i3 = str.charAt(i2);
    int i4 = i1;
    i2 = i3;
    if (i3 >= 55296)
    {
      i3 &= 0x1FFF;
      i2 = 13;
      for (i4 = i1;; i4 = i1)
      {
        i1 = i4 + 1;
        i4 = str.charAt(i4);
        if (i4 < 55296) {
          break;
        }
        i3 |= (i4 & 0x1FFF) << i2;
        i2 += 13;
      }
      i2 = i3 | i4 << i2;
      i4 = i1;
    }
    int[] arrayOfInt1;
    int i10;
    int i5;
    int i8;
    if (i2 == 0)
    {
      arrayOfInt1 = r;
      i10 = 0;
      i5 = 0;
      i8 = 0;
      i6 = 0;
      i11 = 0;
      i2 = 0;
      i7 = 0;
    }
    else
    {
      i2 = i4 + 1;
      i4 = str.charAt(i4);
      i1 = i4;
      i3 = i2;
      if (i4 >= 55296)
      {
        i3 = i4 & 0x1FFF;
        i1 = 13;
        for (i4 = i2;; i4 = i2)
        {
          i2 = i4 + 1;
          i4 = str.charAt(i4);
          if (i4 < 55296) {
            break;
          }
          i3 |= (i4 & 0x1FFF) << i1;
          i1 += 13;
        }
        i1 = i3 | i4 << i1;
        i3 = i2;
      }
      i2 = i3 + 1;
      i4 = str.charAt(i3);
      i8 = i4;
      i3 = i2;
      if (i4 >= 55296)
      {
        i4 &= 0x1FFF;
        i3 = 13;
        for (i5 = i2;; i5 = i2)
        {
          i2 = i5 + 1;
          i5 = str.charAt(i5);
          if (i5 < 55296) {
            break;
          }
          i4 |= (i5 & 0x1FFF) << i3;
          i3 += 13;
        }
        i8 = i4 | i5 << i3;
        i3 = i2;
      }
      i2 = i3 + 1;
      i5 = str.charAt(i3);
      i3 = i5;
      i4 = i2;
      if (i5 >= 55296)
      {
        i4 = i5 & 0x1FFF;
        i3 = 13;
        for (i5 = i2;; i5 = i2)
        {
          i2 = i5 + 1;
          i5 = str.charAt(i5);
          if (i5 < 55296) {
            break;
          }
          i4 |= (i5 & 0x1FFF) << i3;
          i3 += 13;
        }
        i3 = i4 | i5 << i3;
        i4 = i2;
      }
      i2 = i4 + 1;
      i6 = str.charAt(i4);
      i4 = i6;
      i5 = i2;
      if (i6 >= 55296)
      {
        i5 = i6 & 0x1FFF;
        i4 = 13;
        for (i6 = i2;; i6 = i2)
        {
          i2 = i6 + 1;
          i6 = str.charAt(i6);
          if (i6 < 55296) {
            break;
          }
          i5 |= (i6 & 0x1FFF) << i4;
          i4 += 13;
        }
        i4 = i5 | i6 << i4;
        i5 = i2;
      }
      i2 = i5 + 1;
      i7 = str.charAt(i5);
      i5 = i7;
      i6 = i2;
      if (i7 >= 55296)
      {
        i6 = i7 & 0x1FFF;
        i5 = 13;
        for (i7 = i2;; i7 = i2)
        {
          i2 = i7 + 1;
          i7 = str.charAt(i7);
          if (i7 < 55296) {
            break;
          }
          i6 |= (i7 & 0x1FFF) << i5;
          i5 += 13;
        }
        i5 = i6 | i7 << i5;
        i6 = i2;
      }
      i2 = i6 + 1;
      i9 = str.charAt(i6);
      i6 = i9;
      i7 = i2;
      if (i9 >= 55296)
      {
        i7 = i9 & 0x1FFF;
        i6 = 13;
        for (i9 = i2;; i9 = i2)
        {
          i2 = i9 + 1;
          i9 = str.charAt(i9);
          if (i9 < 55296) {
            break;
          }
          i7 |= (i9 & 0x1FFF) << i6;
          i6 += 13;
        }
        i6 = i7 | i9 << i6;
        i7 = i2;
      }
      i2 = i7 + 1;
      i10 = str.charAt(i7);
      i9 = i10;
      i7 = i2;
      if (i10 >= 55296)
      {
        i9 = i10 & 0x1FFF;
        i7 = 13;
        for (i10 = i2;; i10 = i2)
        {
          i2 = i10 + 1;
          i10 = str.charAt(i10);
          if (i10 < 55296) {
            break;
          }
          i9 |= (i10 & 0x1FFF) << i7;
          i7 += 13;
        }
        i9 |= i10 << i7;
        i7 = i2;
      }
      i10 = i7 + 1;
      i11 = str.charAt(i7);
      i2 = i11;
      i7 = i10;
      if (i11 >= 55296)
      {
        i7 = i11 & 0x1FFF;
        i2 = 13;
        i11 = i10;
        i10 = i7;
        for (;;)
        {
          i7 = i11 + 1;
          i11 = str.charAt(i11);
          if (i11 < 55296) {
            break;
          }
          i10 |= (i11 & 0x1FFF) << i2;
          i2 += 13;
          i11 = i7;
        }
        i2 = i10 | i11 << i2;
      }
      arrayOfInt1 = new int[i2 + i6 + i9];
      i8 = i1 * 2 + i8;
      i9 = i7;
      i7 = i8;
      i11 = i6;
      i6 = i5;
      i8 = i4;
      i5 = i3;
      i10 = i1;
      i4 = i9;
    }
    Unsafe localUnsafe = s;
    Object[] arrayOfObject2 = paramI1.d();
    Class localClass = paramI1.c().getClass();
    int[] arrayOfInt2 = new int[i6 * 3];
    Object[] arrayOfObject1 = new Object[i6 * 2];
    int i18 = i2 + i11;
    i1 = i2;
    i3 = i18;
    int i9 = 0;
    int i14 = 0;
    int i6 = i7;
    int i12 = i2;
    int i7 = i9;
    int i11 = i8;
    int i13 = i5;
    i2 = i15;
    while (i4 < i2)
    {
      i9 = i4 + 1;
      i15 = str.charAt(i4);
      if (i15 >= 55296)
      {
        i8 = i15 & 0x1FFF;
        i4 = 13;
        for (;;)
        {
          i5 = i9 + 1;
          i9 = str.charAt(i9);
          if (i9 < 55296) {
            break;
          }
          i8 |= (i9 & 0x1FFF) << i4;
          i4 += 13;
          i9 = i5;
        }
        i15 = i8 | i9 << i4;
      }
      else
      {
        i5 = i9;
      }
      i4 = i5 + 1;
      int i16 = str.charAt(i5);
      if (i16 >= 55296)
      {
        i8 = i16 & 0x1FFF;
        i5 = 13;
        for (;;)
        {
          i9 = i4 + 1;
          i16 = str.charAt(i4);
          i4 = i2;
          if (i16 < 55296) {
            break;
          }
          i8 |= (i16 & 0x1FFF) << i5;
          i5 += 13;
          i2 = i4;
          i4 = i9;
        }
        i16 = i8 | i16 << i5;
        i8 = i9;
      }
      else
      {
        i8 = i4;
        i4 = i2;
      }
      int i20 = i16 & 0xFF;
      i5 = i7;
      if ((i16 & 0x400) != 0)
      {
        arrayOfInt1[i7] = i14;
        i5 = i7 + 1;
      }
      label1750:
      Object localObject;
      int i17;
      if (i20 >= 51)
      {
        i7 = i8 + 1;
        i9 = str.charAt(i8);
        i8 = i9;
        i2 = i7;
        if (i9 >= 55296)
        {
          i8 = i9 & 0x1FFF;
          i2 = 13;
          for (i9 = i7;; i9 = i7)
          {
            i7 = i9 + 1;
            i9 = str.charAt(i9);
            if (i9 < 55296) {
              break;
            }
            i8 |= (i9 & 0x1FFF) << i2;
            i2 += 13;
          }
          i8 |= i9 << i2;
          i2 = i7;
        }
        i9 = i20 - 51;
        if ((i9 != 9) && (i9 != 17))
        {
          i7 = i6;
          if (i9 != 12) {
            break label1750;
          }
          i7 = i6;
          if (bool) {
            break label1750;
          }
          i9 = i14 / 3;
          i7 = i6 + 1;
          arrayOfObject1[(i9 * 2 + 1)] = arrayOfObject2[i6];
          i6 = i7;
        }
        else
        {
          i9 = i14 / 3;
          i7 = i6 + 1;
          arrayOfObject1[(i9 * 2 + 1)] = arrayOfObject2[i6];
          i6 = i7;
        }
        i7 = i6;
        i6 = i8 * 2;
        localObject = arrayOfObject2[i6];
        if ((localObject instanceof Field))
        {
          localObject = (Field)localObject;
        }
        else
        {
          localObject = m0(localClass, (String)localObject);
          arrayOfObject2[i6] = localObject;
        }
        i17 = (int)localUnsafe.objectFieldOffset((Field)localObject);
        i6 += 1;
        localObject = arrayOfObject2[i6];
        if ((localObject instanceof Field))
        {
          localObject = (Field)localObject;
        }
        else
        {
          localObject = m0(localClass, (String)localObject);
          arrayOfObject2[i6] = localObject;
        }
        i9 = (int)localUnsafe.objectFieldOffset((Field)localObject);
        i8 = 0;
        i6 = i7;
      }
      else
      {
        i7 = i6 + 1;
        localObject = m0(localClass, (String)arrayOfObject2[i6]);
        if ((i20 != 9) && (i20 != 17))
        {
          if ((i20 != 27) && (i20 != 49))
          {
            if ((i20 != 12) && (i20 != 30) && (i20 != 44))
            {
              i6 = i7;
              i2 = i1;
              if (i20 == 50)
              {
                i2 = i1 + 1;
                arrayOfInt1[i1] = i14;
                i9 = i14 / 3 * 2;
                i6 = i7 + 1;
                arrayOfObject1[i9] = arrayOfObject2[i7];
                if ((i16 & 0x800) == 0) {
                  break label2049;
                }
                i1 = i6 + 1;
                arrayOfObject1[(i9 + 1)] = arrayOfObject2[i6];
                i6 = i1;
              }
            }
            label2049:
            do
            {
              i1 = i2;
              break;
              i1 = i2;
              i2 = i6;
              break label2155;
              i6 = i7;
              i2 = i1;
            } while (bool);
            i6 = i14 / 3;
            i2 = i7 + 1;
            arrayOfObject1[(i6 * 2 + 1)] = arrayOfObject2[i7];
          }
          else
          {
            i6 = i14 / 3;
            i2 = i7 + 1;
            arrayOfObject1[(i6 * 2 + 1)] = arrayOfObject2[i7];
          }
        }
        else
        {
          arrayOfObject1[(i14 / 3 * 2 + 1)] = ((Field)localObject).getType();
          i6 = i7;
          i2 = i6;
        }
        label2155:
        i19 = (int)localUnsafe.objectFieldOffset((Field)localObject);
        if ((i16 & 0x1000) == 4096) {
          i6 = 1;
        } else {
          i6 = 0;
        }
        if ((i6 != 0) && (i20 <= 17))
        {
          i6 = i8 + 1;
          i7 = str.charAt(i8);
          if (i7 >= 55296)
          {
            i8 = i7 & 0x1FFF;
            i7 = 13;
            for (i9 = i6;; i9 = i6)
            {
              i6 = i9 + 1;
              i9 = str.charAt(i9);
              if (i9 < 55296) {
                break;
              }
              i8 |= (i9 & 0x1FFF) << i7;
              i7 += 13;
            }
            i7 = i8 | i9 << i7;
          }
          i8 = i10 * 2 + i7 / 32;
          localObject = arrayOfObject2[i8];
          if ((localObject instanceof Field))
          {
            localObject = (Field)localObject;
          }
          else
          {
            localObject = m0(localClass, (String)localObject);
            arrayOfObject2[i8] = localObject;
          }
          i8 = (int)localUnsafe.objectFieldOffset((Field)localObject);
          i7 %= 32;
        }
        else
        {
          i7 = 1048575;
          i6 = i8;
          i9 = 0;
          i8 = i7;
          i7 = i9;
        }
        i9 = i3;
        if (i20 >= 18)
        {
          i9 = i3;
          if (i20 <= 49)
          {
            arrayOfInt1[i3] = i19;
            i9 = i3 + 1;
          }
        }
        i17 = i2;
        i2 = i6;
        i3 = i9;
        i6 = i17;
        i9 = i8;
        i17 = i19;
        i8 = i7;
      }
      int i19 = i14 + 1;
      arrayOfInt2[i14] = i15;
      i15 = i19 + 1;
      if ((i16 & 0x200) != 0) {
        i7 = 536870912;
      } else {
        i7 = 0;
      }
      if ((i16 & 0x100) != 0) {
        i14 = 268435456;
      } else {
        i14 = 0;
      }
      arrayOfInt2[i19] = (i14 | i7 | i20 << 20 | i17);
      i14 = i15 + 1;
      arrayOfInt2[i15] = (i8 << 20 | i9);
      i7 = i2;
      i2 = i4;
      i4 = i7;
      i7 = i5;
    }
    return new w0(arrayOfInt2, arrayOfObject1, i13, i11, paramI1.c(), bool, false, arrayOfInt1, i12, i18, paramY0, paramJ0, paramT1, paramS, paramO0);
  }
  
  private int T(int paramInt)
  {
    return a[paramInt];
  }
  
  private static long U(int paramInt)
  {
    return paramInt & 0xFFFFF;
  }
  
  private static boolean V(Object paramObject, long paramLong)
  {
    return ((Boolean)x1.E(paramObject, paramLong)).booleanValue();
  }
  
  private static double W(Object paramObject, long paramLong)
  {
    return ((Double)x1.E(paramObject, paramLong)).doubleValue();
  }
  
  private static float X(Object paramObject, long paramLong)
  {
    return ((Float)x1.E(paramObject, paramLong)).floatValue();
  }
  
  private static int Y(Object paramObject, long paramLong)
  {
    return ((Integer)x1.E(paramObject, paramLong)).intValue();
  }
  
  private static long Z(Object paramObject, long paramLong)
  {
    return ((Long)x1.E(paramObject, paramLong)).longValue();
  }
  
  private int a0(Object paramObject, byte[] paramArrayOfByte, int paramInt1, int paramInt2, int paramInt3, long paramLong, f.a paramA)
  {
    Unsafe localUnsafe = s;
    Object localObject3 = t(paramInt3);
    Object localObject2 = localUnsafe.getObject(paramObject, paramLong);
    Object localObject1 = localObject2;
    if (q.d(localObject2))
    {
      localObject1 = q.b(localObject3);
      q.a(localObject1, localObject2);
      localUnsafe.putObject(paramObject, paramLong, localObject1);
    }
    return m(paramArrayOfByte, paramInt1, paramInt2, q.f(localObject3), q.h(localObject1), paramA);
  }
  
  private int b0(Object paramObject, byte[] paramArrayOfByte, int paramInt1, int paramInt2, int paramInt3, int paramInt4, int paramInt5, int paramInt6, int paramInt7, long paramLong, int paramInt8, f.a paramA)
  {
    Unsafe localUnsafe = s;
    long l2 = a[(paramInt8 + 2)] & 0xFFFFF;
    boolean bool = true;
    long l1;
    switch (paramInt7)
    {
    default: 
      break;
    case 68: 
      if (paramInt5 != 3) {
        return paramInt1;
      }
      paramInt1 = f.m(u(paramInt8), paramArrayOfByte, paramInt1, paramInt2, paramInt3 & 0xFFFFFFF8 | 0x4, paramA);
      if (localUnsafe.getInt(paramObject, l2) == paramInt4) {
        paramArrayOfByte = localUnsafe.getObject(paramObject, paramLong);
      } else {
        paramArrayOfByte = null;
      }
      paramA = c;
      if (paramArrayOfByte == null) {
        paramArrayOfByte = paramA;
      } else {
        paramArrayOfByte = c0.h(paramArrayOfByte, paramA);
      }
      break;
    case 67: 
      if (paramInt5 != 0) {
        return paramInt1;
      }
      paramInt1 = f.K(paramArrayOfByte, paramInt1, paramA);
      l1 = k.c(b);
      break;
    case 66: 
      if (paramInt5 != 0) {
        return paramInt1;
      }
      paramInt1 = f.H(paramArrayOfByte, paramInt1, paramA);
      paramInt2 = k.b(a);
      break;
    case 63: 
      if (paramInt5 != 0) {
        return paramInt1;
      }
      paramInt1 = f.H(paramArrayOfByte, paramInt1, paramA);
      paramInt2 = a;
      s(paramInt8);
      break;
    case 61: 
      if (paramInt5 != 2) {
        return paramInt1;
      }
      paramInt1 = f.b(paramArrayOfByte, paramInt1, paramA);
      paramArrayOfByte = c;
      break;
    case 60: 
      if (paramInt5 != 2) {
        return paramInt1;
      }
      paramInt1 = f.o(u(paramInt8), paramArrayOfByte, paramInt1, paramInt2, paramA);
      if (localUnsafe.getInt(paramObject, l2) == paramInt4) {
        paramArrayOfByte = localUnsafe.getObject(paramObject, paramLong);
      } else {
        paramArrayOfByte = null;
      }
      paramA = c;
      if (paramArrayOfByte == null) {
        paramArrayOfByte = paramA;
      } else {
        paramArrayOfByte = c0.h(paramArrayOfByte, paramA);
      }
      break;
    case 59: 
      if (paramInt5 != 2) {
        return paramInt1;
      }
      paramInt1 = f.H(paramArrayOfByte, paramInt1, paramA);
      paramInt2 = a;
      if (paramInt2 == 0)
      {
        paramArrayOfByte = "";
      }
      else
      {
        if (((paramInt6 & 0x20000000) != 0) && (!y1.t(paramArrayOfByte, paramInt1, paramInt1 + paramInt2))) {
          throw d0.c();
        }
        localUnsafe.putObject(paramObject, paramLong, new String(paramArrayOfByte, paramInt1, paramInt2, c0.a));
        paramInt1 += paramInt2;
      }
      break;
    case 58: 
      if (paramInt5 != 0) {
        return paramInt1;
      }
      paramInt1 = f.K(paramArrayOfByte, paramInt1, paramA);
      if (b == 0L) {
        bool = false;
      }
      paramArrayOfByte = Boolean.valueOf(bool);
      break;
    case 57: 
    case 64: 
      if (paramInt5 != 5) {
        return paramInt1;
      }
      paramArrayOfByte = Integer.valueOf(f.g(paramArrayOfByte, paramInt1));
      break;
    case 56: 
    case 65: 
      if (paramInt5 != 1) {
        return paramInt1;
      }
      paramArrayOfByte = Long.valueOf(f.i(paramArrayOfByte, paramInt1));
      break;
    case 55: 
    case 62: 
      if (paramInt5 != 0) {
        return paramInt1;
      }
      paramInt1 = f.H(paramArrayOfByte, paramInt1, paramA);
      paramInt2 = a;
      paramArrayOfByte = Integer.valueOf(paramInt2);
      break;
    case 53: 
    case 54: 
      if (paramInt5 != 0) {
        return paramInt1;
      }
      paramInt1 = f.K(paramArrayOfByte, paramInt1, paramA);
      l1 = b;
      paramArrayOfByte = Long.valueOf(l1);
      localUnsafe.putObject(paramObject, paramLong, paramArrayOfByte);
      break;
    case 52: 
      if (paramInt5 != 5) {
        return paramInt1;
      }
      paramArrayOfByte = Float.valueOf(f.k(paramArrayOfByte, paramInt1));
      localUnsafe.putObject(paramObject, paramLong, paramArrayOfByte);
      paramInt1 += 4;
      break;
    }
    if (paramInt5 == 1)
    {
      paramArrayOfByte = Double.valueOf(f.d(paramArrayOfByte, paramInt1));
      localUnsafe.putObject(paramObject, paramLong, paramArrayOfByte);
      paramInt1 += 8;
      localUnsafe.putInt(paramObject, l2, paramInt4);
      return paramInt1;
    }
    return paramInt1;
  }
  
  private int d0(Object paramObject, byte[] paramArrayOfByte, int paramInt1, int paramInt2, f.a paramA)
  {
    w0 localW0 = this;
    Object localObject2 = paramObject;
    byte[] arrayOfByte = paramArrayOfByte;
    int i7 = paramInt2;
    Unsafe localUnsafe = s;
    int i3 = paramInt1;
    paramInt1 = -1;
    int i4 = 0;
    int i1 = 0;
    int i2 = 1048575;
    for (;;)
    {
      Object localObject1 = paramA;
      if (i3 >= i7) {
        break;
      }
      int i5 = i3 + 1;
      int i8 = arrayOfByte[i3];
      if (i8 < 0)
      {
        i3 = f.G(i8, arrayOfByte, i5, (f.a)localObject1);
        i8 = a;
      }
      else
      {
        i3 = i5;
      }
      i5 = i8 >>> 3;
      int i11 = i8 & 0x7;
      if (i5 > paramInt1) {
        paramInt1 = localW0.g0(i5, i4 / 3);
      } else {
        paramInt1 = localW0.f0(i5);
      }
      if (paramInt1 == -1)
      {
        i4 = 0;
        paramInt1 = i1;
      }
      for (;;)
      {
        break label1266;
        int i12 = a[(paramInt1 + 1)];
        int i13 = q0(i12);
        long l1 = U(i12);
        label524:
        Object localObject3;
        if (i13 <= 17)
        {
          i4 = a[(paramInt1 + 2)];
          int i10 = 1 << (i4 >>> 20);
          int i9 = i4 & 0xFFFFF;
          i6 = i1;
          i4 = i2;
          if (i9 != i2)
          {
            if (i2 != 1048575) {
              localUnsafe.putInt(localObject2, i2, i1);
            }
            if (i9 != 1048575) {
              i1 = localUnsafe.getInt(localObject2, i9);
            }
            i4 = i9;
            i6 = i1;
          }
          switch (i13)
          {
          }
          for (;;)
          {
            break;
            if (i11 == 0)
            {
              localObject1 = paramA;
              i1 = f.K(arrayOfByte, i3, (f.a)localObject1);
              long l2 = k.c(b);
              localUnsafe.putLong(paramObject, l1, l2);
              i2 = i6 | i10;
              break label855;
              localObject1 = paramA;
              if (i11 == 0)
              {
                i1 = f.H(arrayOfByte, i3, (f.a)localObject1);
                localUnsafe.putInt(localObject2, l1, k.b(a));
                i2 = i6 | i10;
                break label924;
                localObject1 = paramA;
                if (i11 == 0)
                {
                  i1 = f.H(arrayOfByte, i3, (f.a)localObject1);
                  localUnsafe.putInt(localObject2, l1, a);
                  break label524;
                  localObject1 = paramA;
                  if (i11 == 2)
                  {
                    i1 = f.b(arrayOfByte, i3, (f.a)localObject1);
                    localObject1 = c;
                    for (;;)
                    {
                      localUnsafe.putObject(localObject2, l1, localObject1);
                      i2 = i6 | i10;
                      break label924;
                      localObject1 = paramA;
                      if (i11 != 2) {
                        break;
                      }
                      i1 = f.o(localW0.u(paramInt1), arrayOfByte, i3, i7, (f.a)localObject1);
                      localObject3 = localUnsafe.getObject(localObject2, l1);
                      if (localObject3 == null) {
                        localObject1 = c;
                      } else {
                        localObject1 = c0.h(localObject3, c);
                      }
                    }
                    localObject1 = paramA;
                    if (i11 == 2)
                    {
                      if ((0x20000000 & i12) == 0) {
                        i1 = f.B(arrayOfByte, i3, (f.a)localObject1);
                      } else {
                        i1 = f.E(arrayOfByte, i3, (f.a)localObject1);
                      }
                      localUnsafe.putObject(localObject2, l1, c);
                      break label917;
                      localObject1 = paramA;
                      boolean bool = true;
                      if (i11 == 0)
                      {
                        i1 = f.K(arrayOfByte, i3, (f.a)localObject1);
                        if (b == 0L) {
                          bool = false;
                        }
                        x1.I(localObject2, l1, bool);
                        i2 = i6 | i10;
                        if (i11 == 5)
                        {
                          localUnsafe.putInt(localObject2, l1, f.g(arrayOfByte, i3));
                          if (i11 == 1)
                          {
                            localUnsafe.putLong(paramObject, l1, f.i(arrayOfByte, i3));
                            i1 = i3 + 8;
                            break label917;
                            localObject1 = paramA;
                            if (i11 == 0)
                            {
                              i1 = f.H(arrayOfByte, i3, (f.a)localObject1);
                              localUnsafe.putInt(localObject2, l1, a);
                              break label917;
                              localObject1 = paramA;
                              if (i11 == 0)
                              {
                                i1 = f.K(arrayOfByte, i3, (f.a)localObject1);
                                localUnsafe.putLong(paramObject, l1, b);
                                i2 = i6 | i10;
                                label855:
                                i3 = paramInt1;
                                if (i11 == 5)
                                {
                                  x1.P(localObject2, l1, f.k(arrayOfByte, i3));
                                  i1 = i3 + 4;
                                  if (i11 == 1)
                                  {
                                    x1.O(localObject2, l1, f.d(arrayOfByte, i3));
                                    i1 = i3 + 8;
                                    label917:
                                    i2 = i6 | i10;
                                    label924:
                                    i3 = paramInt1;
                                    paramInt1 = i5;
                                    i6 = i1;
                                    i5 = i3;
                                    i1 = i2;
                                    i2 = i4;
                                    break label1311;
                                  }
                                }
                              }
                            }
                          }
                        }
                      }
                    }
                  }
                }
              }
            }
          }
          i1 = paramInt1;
          paramInt1 = i6;
          i2 = i4;
          i4 = i1;
        }
        else
        {
          i6 = i5;
          if (i13 == 27)
          {
            if (i11 == 2)
            {
              localObject3 = (c0.i)localUnsafe.getObject(localObject2, l1);
              localObject1 = localObject3;
              if (!((c0.i)localObject3).T())
              {
                i4 = ((List)localObject3).size();
                if (i4 == 0) {
                  i4 = 10;
                } else {
                  i4 *= 2;
                }
                localObject1 = ((c0.i)localObject3).a(i4);
                localUnsafe.putObject(localObject2, l1, localObject1);
              }
              i3 = f.p(localW0.u(paramInt1), i8, paramArrayOfByte, i3, paramInt2, (c0.i)localObject1, paramA);
              i4 = paramInt1;
              paramInt1 = i6;
              localW0 = this;
              break;
            }
            break label1208;
          }
          if (i13 <= 49)
          {
            i7 = e0(paramObject, paramArrayOfByte, i3, paramInt2, i8, i6, i11, paramInt1, i12, i13, l1, paramA);
            i4 = i7;
            if (i7 != i3) {
              i3 = i7;
            }
          }
          else
          {
            for (;;)
            {
              i4 = paramInt1;
              paramInt1 = i6;
              break label1290;
              i4 = paramInt1;
              i7 = i3;
              if (i13 != 50) {
                break label1217;
              }
              if (i11 != 2) {
                break;
              }
              i3 = a0(paramObject, paramArrayOfByte, i7, paramInt2, i4, l1, paramA);
              i4 = i3;
              if (i3 == i7) {
                break label1259;
              }
            }
          }
          for (;;)
          {
            label1208:
            i4 = paramInt1;
            paramInt1 = i1;
            break label1266;
            label1217:
            i3 = b0(paramObject, paramArrayOfByte, i7, paramInt2, i8, i6, i11, i12, i13, l1, i4, paramA);
            i4 = i3;
            if (i3 != i7) {
              break;
            }
            label1259:
            i3 = i4;
          }
        }
      }
      label1266:
      i3 = f.F(i8, paramArrayOfByte, i3, paramInt2, v(paramObject), paramA);
      i1 = paramInt1;
      paramInt1 = i5;
      label1290:
      localW0 = this;
      localObject2 = paramObject;
      i7 = paramInt2;
      arrayOfByte = paramArrayOfByte;
      i5 = i4;
      int i6 = i3;
      label1311:
      i3 = i6;
      i4 = i5;
    }
    if (i2 != 1048575) {
      localUnsafe.putInt(paramObject, i2, i1);
    }
    if (i3 == paramInt2) {
      return i3;
    }
    throw d0.g();
  }
  
  private int e0(Object paramObject, byte[] paramArrayOfByte, int paramInt1, int paramInt2, int paramInt3, int paramInt4, int paramInt5, int paramInt6, long paramLong1, int paramInt7, long paramLong2, f.a paramA)
  {
    Unsafe localUnsafe = s;
    c0.i localI2 = (c0.i)localUnsafe.getObject(paramObject, paramLong2);
    c0.i localI1 = localI2;
    if (!localI2.T())
    {
      int i1 = localI2.size();
      if (i1 == 0) {
        i1 = 10;
      } else {
        i1 *= 2;
      }
      localI1 = localI2.a(i1);
      localUnsafe.putObject(paramObject, paramLong2, localI1);
    }
    switch (paramInt7)
    {
    default: 
      break;
    case 49: 
      if (paramInt5 == 3) {
        return f.n(u(paramInt6), paramInt3, paramArrayOfByte, paramInt1, paramInt2, localI1, paramA);
      }
      break;
    case 34: 
    case 48: 
      if (paramInt5 == 2) {
        return f.w(paramArrayOfByte, paramInt1, localI1, paramA);
      }
      if (paramInt5 == 0) {
        return f.A(paramInt3, paramArrayOfByte, paramInt1, paramInt2, localI1, paramA);
      }
      break;
    case 33: 
    case 47: 
      if (paramInt5 == 2) {
        return f.v(paramArrayOfByte, paramInt1, localI1, paramA);
      }
      if (paramInt5 == 0) {
        return f.z(paramInt3, paramArrayOfByte, paramInt1, paramInt2, localI1, paramA);
      }
      break;
    case 30: 
    case 44: 
      if (paramInt5 == 2)
      {
        paramInt1 = f.x(paramArrayOfByte, paramInt1, localI1, paramA);
      }
      else
      {
        if (paramInt5 != 0) {
          break;
        }
        paramInt1 = f.I(paramInt3, paramArrayOfByte, paramInt1, paramInt2, localI1, paramA);
      }
      paramA = (z)paramObject;
      paramArrayOfByte = unknownFields;
      paramObject = paramArrayOfByte;
      if (paramArrayOfByte == u1.c()) {
        paramObject = null;
      }
      s(paramInt6);
      paramObject = (u1)n1.A(paramInt4, localI1, null, paramObject, o);
      if (paramObject != null) {
        unknownFields = paramObject;
      }
      return paramInt1;
    case 28: 
      if (paramInt5 == 2) {
        return f.c(paramInt3, paramArrayOfByte, paramInt1, paramInt2, localI1, paramA);
      }
      break;
    case 27: 
      if (paramInt5 == 2) {
        return f.p(u(paramInt6), paramInt3, paramArrayOfByte, paramInt1, paramInt2, localI1, paramA);
      }
      break;
    case 26: 
      if (paramInt5 == 2)
      {
        if ((paramLong1 & 0x20000000) == 0L) {
          return f.C(paramInt3, paramArrayOfByte, paramInt1, paramInt2, localI1, paramA);
        }
        return f.D(paramInt3, paramArrayOfByte, paramInt1, paramInt2, localI1, paramA);
      }
      break;
    case 25: 
    case 42: 
      if (paramInt5 == 2) {
        return f.q(paramArrayOfByte, paramInt1, localI1, paramA);
      }
      if (paramInt5 == 0) {
        return f.a(paramInt3, paramArrayOfByte, paramInt1, paramInt2, localI1, paramA);
      }
      break;
    case 24: 
    case 31: 
    case 41: 
    case 45: 
      if (paramInt5 == 2) {
        return f.s(paramArrayOfByte, paramInt1, localI1, paramA);
      }
      if (paramInt5 == 5) {
        return f.h(paramInt3, paramArrayOfByte, paramInt1, paramInt2, localI1, paramA);
      }
      break;
    case 23: 
    case 32: 
    case 40: 
    case 46: 
      if (paramInt5 == 2) {
        return f.t(paramArrayOfByte, paramInt1, localI1, paramA);
      }
      if (paramInt5 == 1) {
        return f.j(paramInt3, paramArrayOfByte, paramInt1, paramInt2, localI1, paramA);
      }
      break;
    case 22: 
    case 29: 
    case 39: 
    case 43: 
      if (paramInt5 == 2) {
        return f.x(paramArrayOfByte, paramInt1, localI1, paramA);
      }
      if (paramInt5 == 0) {
        return f.I(paramInt3, paramArrayOfByte, paramInt1, paramInt2, localI1, paramA);
      }
      break;
    case 20: 
    case 21: 
    case 37: 
    case 38: 
      if (paramInt5 == 2) {
        return f.y(paramArrayOfByte, paramInt1, localI1, paramA);
      }
      if (paramInt5 == 0) {
        return f.L(paramInt3, paramArrayOfByte, paramInt1, paramInt2, localI1, paramA);
      }
      break;
    case 19: 
    case 36: 
      if (paramInt5 == 2) {
        return f.u(paramArrayOfByte, paramInt1, localI1, paramA);
      }
      if (paramInt5 == 5) {
        return f.l(paramInt3, paramArrayOfByte, paramInt1, paramInt2, localI1, paramA);
      }
      break;
    case 18: 
    case 35: 
      if (paramInt5 == 2) {
        return f.r(paramArrayOfByte, paramInt1, localI1, paramA);
      }
      if (paramInt5 == 1) {
        return f.e(paramInt3, paramArrayOfByte, paramInt1, paramInt2, localI1, paramA);
      }
      break;
    }
    return paramInt1;
  }
  
  private int f0(int paramInt)
  {
    if ((paramInt >= c) && (paramInt <= d)) {
      return p0(paramInt, 0);
    }
    return -1;
  }
  
  private int g0(int paramInt1, int paramInt2)
  {
    if ((paramInt1 >= c) && (paramInt1 <= d)) {
      return p0(paramInt1, paramInt2);
    }
    return -1;
  }
  
  private int h0(int paramInt)
  {
    return a[(paramInt + 2)];
  }
  
  private void i0(Object paramObject, long paramLong, j1 paramJ1, l1 paramL1, r paramR)
  {
    paramJ1.j(n.e(paramObject, paramLong), paramL1, paramR);
  }
  
  private void j0(Object paramObject, int paramInt, j1 paramJ1, l1 paramL1, r paramR)
  {
    long l1 = U(paramInt);
    paramJ1.s(n.e(paramObject, l1), paramL1, paramR);
  }
  
  private boolean k(Object paramObject1, Object paramObject2, int paramInt)
  {
    return B(paramObject1, paramInt) == B(paramObject2, paramInt);
  }
  
  private void k0(Object paramObject, int paramInt, j1 paramJ1)
  {
    long l1;
    if (A(paramInt))
    {
      l1 = U(paramInt);
      paramJ1 = paramJ1.M();
    }
    for (;;)
    {
      x1.S(paramObject, l1, paramJ1);
      return;
      if (g)
      {
        l1 = U(paramInt);
        paramJ1 = paramJ1.o();
      }
      else
      {
        l1 = U(paramInt);
        paramJ1 = paramJ1.B();
      }
    }
  }
  
  private static boolean l(Object paramObject, long paramLong)
  {
    return x1.r(paramObject, paramLong);
  }
  
  private void l0(Object paramObject, int paramInt, j1 paramJ1)
  {
    if (A(paramInt))
    {
      paramJ1.z(n.e(paramObject, U(paramInt)));
      return;
    }
    paramJ1.u(n.e(paramObject, U(paramInt)));
  }
  
  private int m(byte[] paramArrayOfByte, int paramInt1, int paramInt2, m0.a paramA, Map paramMap, f.a paramA1)
  {
    paramInt1 = f.H(paramArrayOfByte, paramInt1, paramA1);
    int i1 = a;
    if ((i1 >= 0) && (i1 <= paramInt2 - paramInt1))
    {
      int i2 = paramInt1 + i1;
      Object localObject1 = b;
      Object localObject2 = d;
      while (paramInt1 < i2)
      {
        i1 = paramInt1 + 1;
        paramInt1 = paramArrayOfByte[paramInt1];
        if (paramInt1 < 0)
        {
          i1 = f.G(paramInt1, paramArrayOfByte, i1, paramA1);
          paramInt1 = a;
        }
        int i3 = paramInt1 >>> 3;
        int i4 = paramInt1 & 0x7;
        if (i3 != 1)
        {
          if ((i3 == 2) && (i4 == c.c()))
          {
            paramInt1 = n(paramArrayOfByte, i1, paramInt2, c, d.getClass(), paramA1);
            localObject2 = c;
          }
        }
        else if (i4 == a.c())
        {
          paramInt1 = n(paramArrayOfByte, i1, paramInt2, a, null, paramA1);
          localObject1 = c;
          continue;
        }
        paramInt1 = f.M(paramInt1, paramArrayOfByte, i1, paramInt2, paramA1);
      }
      if (paramInt1 == i2)
      {
        paramMap.put(localObject1, localObject2);
        return i2;
      }
      throw d0.g();
    }
    throw d0.k();
  }
  
  private static Field m0(Class paramClass, String paramString)
  {
    try
    {
      localObject1 = paramClass.getDeclaredField(paramString);
      return localObject1;
    }
    catch (NoSuchFieldException localNoSuchFieldException)
    {
      Object localObject1;
      int i2;
      int i1;
      Object localObject2;
      for (;;) {}
    }
    localObject1 = paramClass.getDeclaredFields();
    i2 = localObject1.length;
    i1 = 0;
    while (i1 < i2)
    {
      localObject2 = localObject1[i1];
      if (paramString.equals(((Field)localObject2).getName())) {
        return localObject2;
      }
      i1 += 1;
    }
    localObject2 = new StringBuilder();
    ((StringBuilder)localObject2).append("Field ");
    ((StringBuilder)localObject2).append(paramString);
    ((StringBuilder)localObject2).append(" for ");
    ((StringBuilder)localObject2).append(paramClass.getName());
    ((StringBuilder)localObject2).append(" not found. Known fields are ");
    ((StringBuilder)localObject2).append(Arrays.toString((Object[])localObject1));
    throw new RuntimeException(((StringBuilder)localObject2).toString());
  }
  
  private int n(byte[] paramArrayOfByte, int paramInt1, int paramInt2, z1.b paramB, Class paramClass, f.a paramA)
  {
    long l1;
    switch (a.a[paramB.ordinal()])
    {
    default: 
      throw new RuntimeException("unsupported field type.");
    case 17: 
      return f.E(paramArrayOfByte, paramInt1, paramA);
    case 16: 
      paramInt1 = f.K(paramArrayOfByte, paramInt1, paramA);
      l1 = k.c(b);
      break;
    case 15: 
      paramInt1 = f.H(paramArrayOfByte, paramInt1, paramA);
      paramInt2 = k.b(a);
      break;
    case 14: 
      return f.o(g1.a().d(paramClass), paramArrayOfByte, paramInt1, paramInt2, paramA);
    case 12: 
    case 13: 
      paramInt1 = f.K(paramArrayOfByte, paramInt1, paramA);
      l1 = b;
      paramArrayOfByte = Long.valueOf(l1);
      break;
    case 9: 
    case 10: 
    case 11: 
      paramInt1 = f.H(paramArrayOfByte, paramInt1, paramA);
      paramInt2 = a;
    }
    label253:
    label272:
    boolean bool;
    for (paramArrayOfByte = Integer.valueOf(paramInt2);; paramArrayOfByte = Boolean.valueOf(bool))
    {
      c = paramArrayOfByte;
      return paramInt1;
      paramArrayOfByte = Float.valueOf(f.k(paramArrayOfByte, paramInt1));
      break label253;
      paramArrayOfByte = Long.valueOf(f.i(paramArrayOfByte, paramInt1));
      break label272;
      paramArrayOfByte = Integer.valueOf(f.g(paramArrayOfByte, paramInt1));
      c = paramArrayOfByte;
      return paramInt1 + 4;
      paramArrayOfByte = Double.valueOf(f.d(paramArrayOfByte, paramInt1));
      c = paramArrayOfByte;
      return paramInt1 + 8;
      return f.b(paramArrayOfByte, paramInt1, paramA);
      paramInt1 = f.K(paramArrayOfByte, paramInt1, paramA);
      if (b != 0L) {
        bool = true;
      } else {
        bool = false;
      }
    }
  }
  
  private void n0(Object paramObject, int paramInt)
  {
    paramInt = h0(paramInt);
    long l1 = 0xFFFFF & paramInt;
    if (l1 == 1048575L) {
      return;
    }
    x1.Q(paramObject, l1, 1 << (paramInt >>> 20) | x1.A(paramObject, l1));
  }
  
  private static double o(Object paramObject, long paramLong)
  {
    return x1.y(paramObject, paramLong);
  }
  
  private void o0(Object paramObject, int paramInt1, int paramInt2)
  {
    x1.Q(paramObject, h0(paramInt2) & 0xFFFFF, paramInt1);
  }
  
  private boolean p(Object paramObject1, Object paramObject2, int paramInt)
  {
    int i1 = r0(paramInt);
    long l1 = U(i1);
    i1 = q0(i1);
    boolean bool3 = false;
    boolean bool4 = false;
    boolean bool5 = false;
    boolean bool6 = false;
    boolean bool7 = false;
    boolean bool8 = false;
    boolean bool9 = false;
    boolean bool10 = false;
    boolean bool11 = false;
    boolean bool12 = false;
    boolean bool13 = false;
    boolean bool14 = false;
    boolean bool15 = false;
    boolean bool16 = false;
    boolean bool17 = false;
    boolean bool18 = false;
    boolean bool19 = false;
    boolean bool20 = false;
    boolean bool2 = false;
    switch (i1)
    {
    default: 
      return true;
    case 51: 
    case 52: 
    case 53: 
    case 54: 
    case 55: 
    case 56: 
    case 57: 
    case 58: 
    case 59: 
    case 60: 
    case 61: 
    case 62: 
    case 63: 
    case 64: 
    case 65: 
    case 66: 
    case 67: 
    case 68: 
      bool1 = bool2;
      if (G(paramObject1, paramObject2, paramInt))
      {
        bool1 = bool2;
        if (n1.K(x1.E(paramObject1, l1), x1.E(paramObject2, l1))) {
          bool1 = true;
        }
      }
      return bool1;
    case 18: 
    case 19: 
    case 20: 
    case 21: 
    case 22: 
    case 23: 
    case 24: 
    case 25: 
    case 26: 
    case 27: 
    case 28: 
    case 29: 
    case 30: 
    case 31: 
    case 32: 
    case 33: 
    case 34: 
    case 35: 
    case 36: 
    case 37: 
    case 38: 
    case 39: 
    case 40: 
    case 41: 
    case 42: 
    case 43: 
    case 44: 
    case 45: 
    case 46: 
    case 47: 
    case 48: 
    case 49: 
    case 50: 
      return n1.K(x1.E(paramObject1, l1), x1.E(paramObject2, l1));
    case 17: 
      bool1 = bool3;
      if (k(paramObject1, paramObject2, paramInt))
      {
        bool1 = bool3;
        if (n1.K(x1.E(paramObject1, l1), x1.E(paramObject2, l1))) {
          bool1 = true;
        }
      }
      return bool1;
    case 16: 
      bool1 = bool4;
      if (k(paramObject1, paramObject2, paramInt))
      {
        bool1 = bool4;
        if (x1.C(paramObject1, l1) == x1.C(paramObject2, l1)) {
          bool1 = true;
        }
      }
      return bool1;
    case 15: 
      bool1 = bool5;
      if (k(paramObject1, paramObject2, paramInt))
      {
        bool1 = bool5;
        if (x1.A(paramObject1, l1) == x1.A(paramObject2, l1)) {
          bool1 = true;
        }
      }
      return bool1;
    case 14: 
      bool1 = bool6;
      if (k(paramObject1, paramObject2, paramInt))
      {
        bool1 = bool6;
        if (x1.C(paramObject1, l1) == x1.C(paramObject2, l1)) {
          bool1 = true;
        }
      }
      return bool1;
    case 13: 
      bool1 = bool7;
      if (k(paramObject1, paramObject2, paramInt))
      {
        bool1 = bool7;
        if (x1.A(paramObject1, l1) == x1.A(paramObject2, l1)) {
          bool1 = true;
        }
      }
      return bool1;
    case 12: 
      bool1 = bool8;
      if (k(paramObject1, paramObject2, paramInt))
      {
        bool1 = bool8;
        if (x1.A(paramObject1, l1) == x1.A(paramObject2, l1)) {
          bool1 = true;
        }
      }
      return bool1;
    case 11: 
      bool1 = bool9;
      if (k(paramObject1, paramObject2, paramInt))
      {
        bool1 = bool9;
        if (x1.A(paramObject1, l1) == x1.A(paramObject2, l1)) {
          bool1 = true;
        }
      }
      return bool1;
    case 10: 
      bool1 = bool10;
      if (k(paramObject1, paramObject2, paramInt))
      {
        bool1 = bool10;
        if (n1.K(x1.E(paramObject1, l1), x1.E(paramObject2, l1))) {
          bool1 = true;
        }
      }
      return bool1;
    case 9: 
      bool1 = bool11;
      if (k(paramObject1, paramObject2, paramInt))
      {
        bool1 = bool11;
        if (n1.K(x1.E(paramObject1, l1), x1.E(paramObject2, l1))) {
          bool1 = true;
        }
      }
      return bool1;
    case 8: 
      bool1 = bool12;
      if (k(paramObject1, paramObject2, paramInt))
      {
        bool1 = bool12;
        if (n1.K(x1.E(paramObject1, l1), x1.E(paramObject2, l1))) {
          bool1 = true;
        }
      }
      return bool1;
    case 7: 
      bool1 = bool13;
      if (k(paramObject1, paramObject2, paramInt))
      {
        bool1 = bool13;
        if (x1.r(paramObject1, l1) == x1.r(paramObject2, l1)) {
          bool1 = true;
        }
      }
      return bool1;
    case 6: 
      bool1 = bool14;
      if (k(paramObject1, paramObject2, paramInt))
      {
        bool1 = bool14;
        if (x1.A(paramObject1, l1) == x1.A(paramObject2, l1)) {
          bool1 = true;
        }
      }
      return bool1;
    case 5: 
      bool1 = bool15;
      if (k(paramObject1, paramObject2, paramInt))
      {
        bool1 = bool15;
        if (x1.C(paramObject1, l1) == x1.C(paramObject2, l1)) {
          bool1 = true;
        }
      }
      return bool1;
    case 4: 
      bool1 = bool16;
      if (k(paramObject1, paramObject2, paramInt))
      {
        bool1 = bool16;
        if (x1.A(paramObject1, l1) == x1.A(paramObject2, l1)) {
          bool1 = true;
        }
      }
      return bool1;
    case 3: 
      bool1 = bool17;
      if (k(paramObject1, paramObject2, paramInt))
      {
        bool1 = bool17;
        if (x1.C(paramObject1, l1) == x1.C(paramObject2, l1)) {
          bool1 = true;
        }
      }
      return bool1;
    case 2: 
      bool1 = bool18;
      if (k(paramObject1, paramObject2, paramInt))
      {
        bool1 = bool18;
        if (x1.C(paramObject1, l1) == x1.C(paramObject2, l1)) {
          bool1 = true;
        }
      }
      return bool1;
    case 1: 
      bool1 = bool19;
      if (k(paramObject1, paramObject2, paramInt))
      {
        bool1 = bool19;
        if (Float.floatToIntBits(x1.z(paramObject1, l1)) == Float.floatToIntBits(x1.z(paramObject2, l1))) {
          bool1 = true;
        }
      }
      return bool1;
    }
    boolean bool1 = bool20;
    if (k(paramObject1, paramObject2, paramInt))
    {
      bool1 = bool20;
      if (Double.doubleToLongBits(x1.y(paramObject1, l1)) == Double.doubleToLongBits(x1.y(paramObject2, l1))) {
        bool1 = true;
      }
    }
    return bool1;
  }
  
  private int p0(int paramInt1, int paramInt2)
  {
    int i1 = a.length / 3 - 1;
    while (paramInt2 <= i1)
    {
      int i2 = i1 + paramInt2 >>> 1;
      int i3 = i2 * 3;
      int i4 = T(i3);
      if (paramInt1 == i4) {
        return i3;
      }
      if (paramInt1 < i4) {
        i1 = i2 - 1;
      } else {
        paramInt2 = i2 + 1;
      }
    }
    return -1;
  }
  
  private final Object q(Object paramObject1, int paramInt, Object paramObject2, t1 paramT1)
  {
    T(paramInt);
    if (x1.E(paramObject1, U(r0(paramInt))) == null) {
      return paramObject2;
    }
    s(paramInt);
    return paramObject2;
  }
  
  private static int q0(int paramInt)
  {
    return (paramInt & 0xFF00000) >>> 20;
  }
  
  private static float r(Object paramObject, long paramLong)
  {
    return x1.z(paramObject, paramLong);
  }
  
  private int r0(int paramInt)
  {
    return a[(paramInt + 1)];
  }
  
  private c0.e s(int paramInt)
  {
    b.a(b[(paramInt / 3 * 2 + 1)]);
    return null;
  }
  
  private void s0(Object paramObject, a2 paramA2)
  {
    if (f)
    {
      localObject1 = p.c(paramObject);
      if (!((v)localObject1).m())
      {
        localIterator = ((v)localObject1).q();
        localObject1 = (Map.Entry)localIterator.next();
        break label53;
      }
    }
    Iterator localIterator = null;
    Object localObject1 = null;
    label53:
    int i6 = a.length;
    Unsafe localUnsafe = s;
    int i4 = 0;
    int i1 = 1048575;
    int i2 = 0;
    Object localObject2;
    for (;;)
    {
      localObject2 = localObject1;
      if (i4 >= i6) {
        break;
      }
      int i7 = r0(i4);
      int i8 = T(i4);
      int i9 = q0(i7);
      int i5;
      if (i9 <= 17)
      {
        int i10 = a[(i4 + 2)];
        i5 = i10 & 0xFFFFF;
        int i3 = i1;
        if (i5 != i1)
        {
          i2 = localUnsafe.getInt(paramObject, i5);
          i3 = i5;
        }
        i5 = 1 << (i10 >>> 20);
        i1 = i3;
      }
      else
      {
        i5 = 0;
      }
      while ((localObject1 != null) && (p.a((Map.Entry)localObject1) <= i8))
      {
        p.j(paramA2, (Map.Entry)localObject1);
        if (localIterator.hasNext()) {
          localObject1 = (Map.Entry)localIterator.next();
        } else {
          localObject1 = null;
        }
      }
      long l1 = U(i7);
      switch (i9)
      {
      }
      for (;;)
      {
        break;
        if (H(paramObject, i8, i4))
        {
          paramA2.i(i8, localUnsafe.getObject(paramObject, l1), u(i4));
          continue;
          if (H(paramObject, i8, i4))
          {
            paramA2.C(i8, Z(paramObject, l1));
            continue;
            if (H(paramObject, i8, i4))
            {
              paramA2.N(i8, Y(paramObject, l1));
              continue;
              if (H(paramObject, i8, i4))
              {
                paramA2.r(i8, Z(paramObject, l1));
                continue;
                if (H(paramObject, i8, i4))
                {
                  paramA2.j(i8, Y(paramObject, l1));
                  continue;
                  if (H(paramObject, i8, i4))
                  {
                    paramA2.J(i8, Y(paramObject, l1));
                    continue;
                    if (H(paramObject, i8, i4))
                    {
                      paramA2.g(i8, Y(paramObject, l1));
                      continue;
                      if (H(paramObject, i8, i4))
                      {
                        paramA2.l(i8, (j)localUnsafe.getObject(paramObject, l1));
                        continue;
                        if (H(paramObject, i8, i4))
                        {
                          paramA2.w(i8, localUnsafe.getObject(paramObject, l1), u(i4));
                          continue;
                          if (H(paramObject, i8, i4))
                          {
                            w0(i8, localUnsafe.getObject(paramObject, l1), paramA2);
                            continue;
                            if (H(paramObject, i8, i4))
                            {
                              paramA2.f(i8, V(paramObject, l1));
                              continue;
                              if (H(paramObject, i8, i4))
                              {
                                paramA2.p(i8, Y(paramObject, l1));
                                continue;
                                if (H(paramObject, i8, i4))
                                {
                                  paramA2.A(i8, Z(paramObject, l1));
                                  continue;
                                  if (H(paramObject, i8, i4))
                                  {
                                    paramA2.m(i8, Y(paramObject, l1));
                                    continue;
                                    if (H(paramObject, i8, i4))
                                    {
                                      paramA2.I(i8, Z(paramObject, l1));
                                      continue;
                                      if (H(paramObject, i8, i4))
                                      {
                                        paramA2.e(i8, Z(paramObject, l1));
                                        continue;
                                        if (H(paramObject, i8, i4))
                                        {
                                          paramA2.D(i8, X(paramObject, l1));
                                          continue;
                                          if (H(paramObject, i8, i4))
                                          {
                                            paramA2.q(i8, W(paramObject, l1));
                                            continue;
                                            v0(paramA2, i8, localUnsafe.getObject(paramObject, l1), i4);
                                            continue;
                                            n1.U(T(i4), (List)localUnsafe.getObject(paramObject, l1), paramA2, u(i4));
                                            continue;
                                            n1.b0(T(i4), (List)localUnsafe.getObject(paramObject, l1), paramA2, true);
                                            continue;
                                            n1.a0(T(i4), (List)localUnsafe.getObject(paramObject, l1), paramA2, true);
                                            continue;
                                            n1.Z(T(i4), (List)localUnsafe.getObject(paramObject, l1), paramA2, true);
                                            continue;
                                            n1.Y(T(i4), (List)localUnsafe.getObject(paramObject, l1), paramA2, true);
                                            continue;
                                            n1.Q(T(i4), (List)localUnsafe.getObject(paramObject, l1), paramA2, true);
                                            continue;
                                            n1.d0(T(i4), (List)localUnsafe.getObject(paramObject, l1), paramA2, true);
                                            continue;
                                            n1.N(T(i4), (List)localUnsafe.getObject(paramObject, l1), paramA2, true);
                                            continue;
                                            n1.R(T(i4), (List)localUnsafe.getObject(paramObject, l1), paramA2, true);
                                            continue;
                                            n1.S(T(i4), (List)localUnsafe.getObject(paramObject, l1), paramA2, true);
                                            continue;
                                            n1.V(T(i4), (List)localUnsafe.getObject(paramObject, l1), paramA2, true);
                                            continue;
                                            n1.e0(T(i4), (List)localUnsafe.getObject(paramObject, l1), paramA2, true);
                                            continue;
                                            n1.W(T(i4), (List)localUnsafe.getObject(paramObject, l1), paramA2, true);
                                            continue;
                                            n1.T(T(i4), (List)localUnsafe.getObject(paramObject, l1), paramA2, true);
                                            continue;
                                            n1.P(T(i4), (List)localUnsafe.getObject(paramObject, l1), paramA2, true);
                                            continue;
                                            n1.b0(T(i4), (List)localUnsafe.getObject(paramObject, l1), paramA2, false);
                                            break;
                                            n1.a0(T(i4), (List)localUnsafe.getObject(paramObject, l1), paramA2, false);
                                            break;
                                            n1.Z(T(i4), (List)localUnsafe.getObject(paramObject, l1), paramA2, false);
                                            break;
                                            n1.Y(T(i4), (List)localUnsafe.getObject(paramObject, l1), paramA2, false);
                                            break;
                                            n1.Q(T(i4), (List)localUnsafe.getObject(paramObject, l1), paramA2, false);
                                            break;
                                            n1.d0(T(i4), (List)localUnsafe.getObject(paramObject, l1), paramA2, false);
                                            break;
                                            n1.O(T(i4), (List)localUnsafe.getObject(paramObject, l1), paramA2);
                                            continue;
                                            n1.X(T(i4), (List)localUnsafe.getObject(paramObject, l1), paramA2, u(i4));
                                            continue;
                                            n1.c0(T(i4), (List)localUnsafe.getObject(paramObject, l1), paramA2);
                                            continue;
                                            n1.N(T(i4), (List)localUnsafe.getObject(paramObject, l1), paramA2, false);
                                            break;
                                            n1.R(T(i4), (List)localUnsafe.getObject(paramObject, l1), paramA2, false);
                                            break;
                                            n1.S(T(i4), (List)localUnsafe.getObject(paramObject, l1), paramA2, false);
                                            break;
                                            n1.V(T(i4), (List)localUnsafe.getObject(paramObject, l1), paramA2, false);
                                            break;
                                            n1.e0(T(i4), (List)localUnsafe.getObject(paramObject, l1), paramA2, false);
                                            break;
                                            n1.W(T(i4), (List)localUnsafe.getObject(paramObject, l1), paramA2, false);
                                            break;
                                            n1.T(T(i4), (List)localUnsafe.getObject(paramObject, l1), paramA2, false);
                                            break;
                                            n1.P(T(i4), (List)localUnsafe.getObject(paramObject, l1), paramA2, false);
                                            break;
                                            if ((i5 & i2) != 0)
                                            {
                                              paramA2.i(i8, localUnsafe.getObject(paramObject, l1), u(i4));
                                              break;
                                              if ((i5 & i2) != 0)
                                              {
                                                paramA2.C(i8, localUnsafe.getLong(paramObject, l1));
                                                break;
                                                if ((i5 & i2) != 0)
                                                {
                                                  paramA2.N(i8, localUnsafe.getInt(paramObject, l1));
                                                  break;
                                                  if ((i5 & i2) != 0)
                                                  {
                                                    paramA2.r(i8, localUnsafe.getLong(paramObject, l1));
                                                    break;
                                                    if ((i5 & i2) != 0)
                                                    {
                                                      paramA2.j(i8, localUnsafe.getInt(paramObject, l1));
                                                      break;
                                                      if ((i5 & i2) != 0)
                                                      {
                                                        paramA2.J(i8, localUnsafe.getInt(paramObject, l1));
                                                        break;
                                                        if ((i5 & i2) != 0)
                                                        {
                                                          paramA2.g(i8, localUnsafe.getInt(paramObject, l1));
                                                          break;
                                                          if ((i5 & i2) != 0)
                                                          {
                                                            paramA2.l(i8, (j)localUnsafe.getObject(paramObject, l1));
                                                            break;
                                                            if ((i5 & i2) != 0)
                                                            {
                                                              paramA2.w(i8, localUnsafe.getObject(paramObject, l1), u(i4));
                                                              break;
                                                              if ((i5 & i2) != 0)
                                                              {
                                                                w0(i8, localUnsafe.getObject(paramObject, l1), paramA2);
                                                                break;
                                                                if ((i5 & i2) != 0)
                                                                {
                                                                  paramA2.f(i8, l(paramObject, l1));
                                                                  break;
                                                                  if ((i5 & i2) != 0)
                                                                  {
                                                                    paramA2.p(i8, localUnsafe.getInt(paramObject, l1));
                                                                    break;
                                                                    if ((i5 & i2) != 0)
                                                                    {
                                                                      paramA2.A(i8, localUnsafe.getLong(paramObject, l1));
                                                                      break;
                                                                      if ((i5 & i2) != 0)
                                                                      {
                                                                        paramA2.m(i8, localUnsafe.getInt(paramObject, l1));
                                                                        break;
                                                                        if ((i5 & i2) != 0)
                                                                        {
                                                                          paramA2.I(i8, localUnsafe.getLong(paramObject, l1));
                                                                          break;
                                                                          if ((i5 & i2) != 0)
                                                                          {
                                                                            paramA2.e(i8, localUnsafe.getLong(paramObject, l1));
                                                                            break;
                                                                            if ((i5 & i2) != 0)
                                                                            {
                                                                              paramA2.D(i8, r(paramObject, l1));
                                                                              break;
                                                                              if ((i5 & i2) != 0) {
                                                                                paramA2.q(i8, o(paramObject, l1));
                                                                              }
                                                                            }
                                                                          }
                                                                        }
                                                                      }
                                                                    }
                                                                  }
                                                                }
                                                              }
                                                            }
                                                          }
                                                        }
                                                      }
                                                    }
                                                  }
                                                }
                                              }
                                            }
                                          }
                                        }
                                      }
                                    }
                                  }
                                }
                              }
                            }
                          }
                        }
                      }
                    }
                  }
                }
              }
            }
          }
        }
      }
      i4 += 3;
    }
    while (localObject2 != null)
    {
      p.j(paramA2, (Map.Entry)localObject2);
      if (localIterator.hasNext()) {
        localObject2 = (Map.Entry)localIterator.next();
      } else {
        localObject2 = null;
      }
    }
    x0(o, paramObject, paramA2);
  }
  
  private Object t(int paramInt)
  {
    return b[(paramInt / 3 * 2)];
  }
  
  private void t0(Object paramObject, a2 paramA2)
  {
    if (f)
    {
      localObject1 = p.c(paramObject);
      if (!((v)localObject1).m())
      {
        localIterator = ((v)localObject1).q();
        localObject1 = (Map.Entry)localIterator.next();
        break label54;
      }
    }
    Iterator localIterator = null;
    Object localObject1 = localIterator;
    label54:
    int i3 = a.length;
    int i1 = 0;
    Object localObject2;
    for (;;)
    {
      localObject2 = localObject1;
      if (i1 >= i3) {
        break;
      }
      int i2 = r0(i1);
      int i4 = T(i1);
      while ((localObject1 != null) && (p.a((Map.Entry)localObject1) <= i4))
      {
        p.j(paramA2, (Map.Entry)localObject1);
        if (localIterator.hasNext()) {
          localObject1 = (Map.Entry)localIterator.next();
        } else {
          localObject1 = null;
        }
      }
      long l1;
      boolean bool;
      float f1;
      double d1;
      switch (q0(i2))
      {
      default: 
        break;
      case 68: 
        if (!H(paramObject, i4, i1)) {
          break label2340;
        }
        break;
      case 67: 
        if (!H(paramObject, i4, i1)) {
          break label2340;
        }
        l1 = Z(paramObject, U(i2));
        break;
      case 66: 
        if (!H(paramObject, i4, i1)) {
          break label2340;
        }
        i2 = Y(paramObject, U(i2));
        break;
      case 65: 
        if (!H(paramObject, i4, i1)) {
          break label2340;
        }
        l1 = Z(paramObject, U(i2));
        break;
      case 64: 
        if (!H(paramObject, i4, i1)) {
          break label2340;
        }
        i2 = Y(paramObject, U(i2));
        break;
      case 63: 
        if (!H(paramObject, i4, i1)) {
          break label2340;
        }
        i2 = Y(paramObject, U(i2));
        break;
      case 62: 
        if (!H(paramObject, i4, i1)) {
          break label2340;
        }
        i2 = Y(paramObject, U(i2));
        break;
      case 61: 
        if (!H(paramObject, i4, i1)) {
          break label2340;
        }
        break;
      case 60: 
        if (!H(paramObject, i4, i1)) {
          break label2340;
        }
        break;
      case 59: 
        if (!H(paramObject, i4, i1)) {
          break label2340;
        }
        break;
      case 58: 
        if (!H(paramObject, i4, i1)) {
          break label2340;
        }
        bool = V(paramObject, U(i2));
        break;
      case 57: 
        if (!H(paramObject, i4, i1)) {
          break label2340;
        }
        i2 = Y(paramObject, U(i2));
        break;
      case 56: 
        if (!H(paramObject, i4, i1)) {
          break label2340;
        }
        l1 = Z(paramObject, U(i2));
        break;
      case 55: 
        if (!H(paramObject, i4, i1)) {
          break label2340;
        }
        i2 = Y(paramObject, U(i2));
        break;
      case 54: 
        if (!H(paramObject, i4, i1)) {
          break label2340;
        }
        l1 = Z(paramObject, U(i2));
        break;
      case 53: 
        if (!H(paramObject, i4, i1)) {
          break label2340;
        }
        l1 = Z(paramObject, U(i2));
        break;
      case 52: 
        if (!H(paramObject, i4, i1)) {
          break label2340;
        }
        f1 = X(paramObject, U(i2));
        break;
      case 51: 
        if (!H(paramObject, i4, i1)) {
          break label2340;
        }
        d1 = W(paramObject, U(i2));
        break;
      case 50: 
        v0(paramA2, i4, x1.E(paramObject, U(i2)), i1);
        break;
      case 49: 
        n1.U(T(i1), (List)x1.E(paramObject, U(i2)), paramA2, u(i1));
        break;
      case 48: 
        n1.b0(T(i1), (List)x1.E(paramObject, U(i2)), paramA2, true);
        break;
      case 47: 
        n1.a0(T(i1), (List)x1.E(paramObject, U(i2)), paramA2, true);
        break;
      case 46: 
        n1.Z(T(i1), (List)x1.E(paramObject, U(i2)), paramA2, true);
        break;
      case 45: 
        n1.Y(T(i1), (List)x1.E(paramObject, U(i2)), paramA2, true);
        break;
      case 44: 
        n1.Q(T(i1), (List)x1.E(paramObject, U(i2)), paramA2, true);
        break;
      case 43: 
        n1.d0(T(i1), (List)x1.E(paramObject, U(i2)), paramA2, true);
        break;
      case 42: 
        n1.N(T(i1), (List)x1.E(paramObject, U(i2)), paramA2, true);
        break;
      case 41: 
        n1.R(T(i1), (List)x1.E(paramObject, U(i2)), paramA2, true);
        break;
      case 40: 
        n1.S(T(i1), (List)x1.E(paramObject, U(i2)), paramA2, true);
        break;
      case 39: 
        n1.V(T(i1), (List)x1.E(paramObject, U(i2)), paramA2, true);
        break;
      case 38: 
        n1.e0(T(i1), (List)x1.E(paramObject, U(i2)), paramA2, true);
        break;
      case 37: 
        n1.W(T(i1), (List)x1.E(paramObject, U(i2)), paramA2, true);
        break;
      case 36: 
        n1.T(T(i1), (List)x1.E(paramObject, U(i2)), paramA2, true);
        break;
      case 35: 
        n1.P(T(i1), (List)x1.E(paramObject, U(i2)), paramA2, true);
        break;
      case 34: 
        n1.b0(T(i1), (List)x1.E(paramObject, U(i2)), paramA2, false);
        break;
      case 33: 
        n1.a0(T(i1), (List)x1.E(paramObject, U(i2)), paramA2, false);
        break;
      case 32: 
        n1.Z(T(i1), (List)x1.E(paramObject, U(i2)), paramA2, false);
        break;
      case 31: 
        n1.Y(T(i1), (List)x1.E(paramObject, U(i2)), paramA2, false);
        break;
      case 30: 
        n1.Q(T(i1), (List)x1.E(paramObject, U(i2)), paramA2, false);
        break;
      case 29: 
        n1.d0(T(i1), (List)x1.E(paramObject, U(i2)), paramA2, false);
        break;
      case 28: 
        n1.O(T(i1), (List)x1.E(paramObject, U(i2)), paramA2);
        break;
      case 27: 
        n1.X(T(i1), (List)x1.E(paramObject, U(i2)), paramA2, u(i1));
        break;
      case 26: 
        n1.c0(T(i1), (List)x1.E(paramObject, U(i2)), paramA2);
        break;
      case 25: 
        n1.N(T(i1), (List)x1.E(paramObject, U(i2)), paramA2, false);
        break;
      case 24: 
        n1.R(T(i1), (List)x1.E(paramObject, U(i2)), paramA2, false);
        break;
      case 23: 
        n1.S(T(i1), (List)x1.E(paramObject, U(i2)), paramA2, false);
        break;
      case 22: 
        n1.V(T(i1), (List)x1.E(paramObject, U(i2)), paramA2, false);
        break;
      case 21: 
        n1.e0(T(i1), (List)x1.E(paramObject, U(i2)), paramA2, false);
        break;
      case 20: 
        n1.W(T(i1), (List)x1.E(paramObject, U(i2)), paramA2, false);
        break;
      case 19: 
        n1.T(T(i1), (List)x1.E(paramObject, U(i2)), paramA2, false);
        break;
      case 18: 
        n1.P(T(i1), (List)x1.E(paramObject, U(i2)), paramA2, false);
        break;
      case 17: 
        if (!B(paramObject, i1)) {
          break label2340;
        }
        paramA2.i(i4, x1.E(paramObject, U(i2)), u(i1));
        break;
      case 16: 
        if (!B(paramObject, i1)) {
          break label2340;
        }
        l1 = K(paramObject, U(i2));
        paramA2.C(i4, l1);
        break;
      case 15: 
        if (!B(paramObject, i1)) {
          break label2340;
        }
        i2 = z(paramObject, U(i2));
        paramA2.N(i4, i2);
        break;
      case 14: 
        if (!B(paramObject, i1)) {
          break label2340;
        }
        l1 = K(paramObject, U(i2));
        paramA2.r(i4, l1);
        break;
      case 13: 
        if (!B(paramObject, i1)) {
          break label2340;
        }
        i2 = z(paramObject, U(i2));
        paramA2.j(i4, i2);
        break;
      case 12: 
        if (!B(paramObject, i1)) {
          break label2340;
        }
        i2 = z(paramObject, U(i2));
        paramA2.J(i4, i2);
        break;
      case 11: 
        if (!B(paramObject, i1)) {
          break label2340;
        }
        i2 = z(paramObject, U(i2));
        paramA2.g(i4, i2);
        break;
      case 10: 
        if (!B(paramObject, i1)) {
          break label2340;
        }
        paramA2.l(i4, (j)x1.E(paramObject, U(i2)));
        break;
      case 9: 
        if (!B(paramObject, i1)) {
          break label2340;
        }
        paramA2.w(i4, x1.E(paramObject, U(i2)), u(i1));
        break;
      case 8: 
        if (!B(paramObject, i1)) {
          break label2340;
        }
        w0(i4, x1.E(paramObject, U(i2)), paramA2);
        break;
      case 7: 
        if (!B(paramObject, i1)) {
          break label2340;
        }
        bool = l(paramObject, U(i2));
        paramA2.f(i4, bool);
        break;
      case 6: 
        if (!B(paramObject, i1)) {
          break label2340;
        }
        i2 = z(paramObject, U(i2));
        paramA2.p(i4, i2);
        break;
      case 5: 
        if (!B(paramObject, i1)) {
          break label2340;
        }
        l1 = K(paramObject, U(i2));
        paramA2.A(i4, l1);
        break;
      case 4: 
        if (!B(paramObject, i1)) {
          break label2340;
        }
        i2 = z(paramObject, U(i2));
        paramA2.m(i4, i2);
        break;
      case 3: 
        if (!B(paramObject, i1)) {
          break label2340;
        }
        l1 = K(paramObject, U(i2));
        paramA2.I(i4, l1);
        break;
      case 2: 
        if (!B(paramObject, i1)) {
          break label2340;
        }
        l1 = K(paramObject, U(i2));
        paramA2.e(i4, l1);
        break;
      case 1: 
        if (!B(paramObject, i1)) {
          break label2340;
        }
        f1 = r(paramObject, U(i2));
        paramA2.D(i4, f1);
        break;
      }
      if (B(paramObject, i1))
      {
        d1 = o(paramObject, U(i2));
        paramA2.q(i4, d1);
      }
      label2340:
      i1 += 3;
    }
    while (localObject2 != null)
    {
      p.j(paramA2, (Map.Entry)localObject2);
      if (localIterator.hasNext()) {
        localObject2 = (Map.Entry)localIterator.next();
      } else {
        localObject2 = null;
      }
    }
    x0(o, paramObject, paramA2);
  }
  
  private l1 u(int paramInt)
  {
    paramInt = paramInt / 3 * 2;
    l1 localL1 = (l1)b[paramInt];
    if (localL1 != null) {
      return localL1;
    }
    localL1 = g1.a().d((Class)b[(paramInt + 1)]);
    b[paramInt] = localL1;
    return localL1;
  }
  
  private void u0(Object paramObject, a2 paramA2)
  {
    x0(o, paramObject, paramA2);
    if (f)
    {
      localObject1 = p.c(paramObject);
      if (!((v)localObject1).m())
      {
        localIterator = ((v)localObject1).g();
        localObject1 = (Map.Entry)localIterator.next();
        break label64;
      }
    }
    Iterator localIterator = null;
    Object localObject1 = localIterator;
    label64:
    int i1 = a.length - 3;
    Object localObject2;
    for (;;)
    {
      localObject2 = localObject1;
      if (i1 < 0) {
        break;
      }
      int i2 = r0(i1);
      int i3 = T(i1);
      while ((localObject1 != null) && (p.a((Map.Entry)localObject1) > i3))
      {
        p.j(paramA2, (Map.Entry)localObject1);
        if (localIterator.hasNext()) {
          localObject1 = (Map.Entry)localIterator.next();
        } else {
          localObject1 = null;
        }
      }
      long l1;
      boolean bool;
      float f1;
      double d1;
      switch (q0(i2))
      {
      default: 
        break;
      case 68: 
        if (!H(paramObject, i3, i1)) {
          break label2344;
        }
        break;
      case 67: 
        if (!H(paramObject, i3, i1)) {
          break label2344;
        }
        l1 = Z(paramObject, U(i2));
        break;
      case 66: 
        if (!H(paramObject, i3, i1)) {
          break label2344;
        }
        i2 = Y(paramObject, U(i2));
        break;
      case 65: 
        if (!H(paramObject, i3, i1)) {
          break label2344;
        }
        l1 = Z(paramObject, U(i2));
        break;
      case 64: 
        if (!H(paramObject, i3, i1)) {
          break label2344;
        }
        i2 = Y(paramObject, U(i2));
        break;
      case 63: 
        if (!H(paramObject, i3, i1)) {
          break label2344;
        }
        i2 = Y(paramObject, U(i2));
        break;
      case 62: 
        if (!H(paramObject, i3, i1)) {
          break label2344;
        }
        i2 = Y(paramObject, U(i2));
        break;
      case 61: 
        if (!H(paramObject, i3, i1)) {
          break label2344;
        }
        break;
      case 60: 
        if (!H(paramObject, i3, i1)) {
          break label2344;
        }
        break;
      case 59: 
        if (!H(paramObject, i3, i1)) {
          break label2344;
        }
        break;
      case 58: 
        if (!H(paramObject, i3, i1)) {
          break label2344;
        }
        bool = V(paramObject, U(i2));
        break;
      case 57: 
        if (!H(paramObject, i3, i1)) {
          break label2344;
        }
        i2 = Y(paramObject, U(i2));
        break;
      case 56: 
        if (!H(paramObject, i3, i1)) {
          break label2344;
        }
        l1 = Z(paramObject, U(i2));
        break;
      case 55: 
        if (!H(paramObject, i3, i1)) {
          break label2344;
        }
        i2 = Y(paramObject, U(i2));
        break;
      case 54: 
        if (!H(paramObject, i3, i1)) {
          break label2344;
        }
        l1 = Z(paramObject, U(i2));
        break;
      case 53: 
        if (!H(paramObject, i3, i1)) {
          break label2344;
        }
        l1 = Z(paramObject, U(i2));
        break;
      case 52: 
        if (!H(paramObject, i3, i1)) {
          break label2344;
        }
        f1 = X(paramObject, U(i2));
        break;
      case 51: 
        if (!H(paramObject, i3, i1)) {
          break label2344;
        }
        d1 = W(paramObject, U(i2));
        break;
      case 50: 
        v0(paramA2, i3, x1.E(paramObject, U(i2)), i1);
        break;
      case 49: 
        n1.U(T(i1), (List)x1.E(paramObject, U(i2)), paramA2, u(i1));
        break;
      case 48: 
        n1.b0(T(i1), (List)x1.E(paramObject, U(i2)), paramA2, true);
        break;
      case 47: 
        n1.a0(T(i1), (List)x1.E(paramObject, U(i2)), paramA2, true);
        break;
      case 46: 
        n1.Z(T(i1), (List)x1.E(paramObject, U(i2)), paramA2, true);
        break;
      case 45: 
        n1.Y(T(i1), (List)x1.E(paramObject, U(i2)), paramA2, true);
        break;
      case 44: 
        n1.Q(T(i1), (List)x1.E(paramObject, U(i2)), paramA2, true);
        break;
      case 43: 
        n1.d0(T(i1), (List)x1.E(paramObject, U(i2)), paramA2, true);
        break;
      case 42: 
        n1.N(T(i1), (List)x1.E(paramObject, U(i2)), paramA2, true);
        break;
      case 41: 
        n1.R(T(i1), (List)x1.E(paramObject, U(i2)), paramA2, true);
        break;
      case 40: 
        n1.S(T(i1), (List)x1.E(paramObject, U(i2)), paramA2, true);
        break;
      case 39: 
        n1.V(T(i1), (List)x1.E(paramObject, U(i2)), paramA2, true);
        break;
      case 38: 
        n1.e0(T(i1), (List)x1.E(paramObject, U(i2)), paramA2, true);
        break;
      case 37: 
        n1.W(T(i1), (List)x1.E(paramObject, U(i2)), paramA2, true);
        break;
      case 36: 
        n1.T(T(i1), (List)x1.E(paramObject, U(i2)), paramA2, true);
        break;
      case 35: 
        n1.P(T(i1), (List)x1.E(paramObject, U(i2)), paramA2, true);
        break;
      case 34: 
        n1.b0(T(i1), (List)x1.E(paramObject, U(i2)), paramA2, false);
        break;
      case 33: 
        n1.a0(T(i1), (List)x1.E(paramObject, U(i2)), paramA2, false);
        break;
      case 32: 
        n1.Z(T(i1), (List)x1.E(paramObject, U(i2)), paramA2, false);
        break;
      case 31: 
        n1.Y(T(i1), (List)x1.E(paramObject, U(i2)), paramA2, false);
        break;
      case 30: 
        n1.Q(T(i1), (List)x1.E(paramObject, U(i2)), paramA2, false);
        break;
      case 29: 
        n1.d0(T(i1), (List)x1.E(paramObject, U(i2)), paramA2, false);
        break;
      case 28: 
        n1.O(T(i1), (List)x1.E(paramObject, U(i2)), paramA2);
        break;
      case 27: 
        n1.X(T(i1), (List)x1.E(paramObject, U(i2)), paramA2, u(i1));
        break;
      case 26: 
        n1.c0(T(i1), (List)x1.E(paramObject, U(i2)), paramA2);
        break;
      case 25: 
        n1.N(T(i1), (List)x1.E(paramObject, U(i2)), paramA2, false);
        break;
      case 24: 
        n1.R(T(i1), (List)x1.E(paramObject, U(i2)), paramA2, false);
        break;
      case 23: 
        n1.S(T(i1), (List)x1.E(paramObject, U(i2)), paramA2, false);
        break;
      case 22: 
        n1.V(T(i1), (List)x1.E(paramObject, U(i2)), paramA2, false);
        break;
      case 21: 
        n1.e0(T(i1), (List)x1.E(paramObject, U(i2)), paramA2, false);
        break;
      case 20: 
        n1.W(T(i1), (List)x1.E(paramObject, U(i2)), paramA2, false);
        break;
      case 19: 
        n1.T(T(i1), (List)x1.E(paramObject, U(i2)), paramA2, false);
        break;
      case 18: 
        n1.P(T(i1), (List)x1.E(paramObject, U(i2)), paramA2, false);
        break;
      case 17: 
        if (!B(paramObject, i1)) {
          break label2344;
        }
        paramA2.i(i3, x1.E(paramObject, U(i2)), u(i1));
        break;
      case 16: 
        if (!B(paramObject, i1)) {
          break label2344;
        }
        l1 = K(paramObject, U(i2));
        paramA2.C(i3, l1);
        break;
      case 15: 
        if (!B(paramObject, i1)) {
          break label2344;
        }
        i2 = z(paramObject, U(i2));
        paramA2.N(i3, i2);
        break;
      case 14: 
        if (!B(paramObject, i1)) {
          break label2344;
        }
        l1 = K(paramObject, U(i2));
        paramA2.r(i3, l1);
        break;
      case 13: 
        if (!B(paramObject, i1)) {
          break label2344;
        }
        i2 = z(paramObject, U(i2));
        paramA2.j(i3, i2);
        break;
      case 12: 
        if (!B(paramObject, i1)) {
          break label2344;
        }
        i2 = z(paramObject, U(i2));
        paramA2.J(i3, i2);
        break;
      case 11: 
        if (!B(paramObject, i1)) {
          break label2344;
        }
        i2 = z(paramObject, U(i2));
        paramA2.g(i3, i2);
        break;
      case 10: 
        if (!B(paramObject, i1)) {
          break label2344;
        }
        paramA2.l(i3, (j)x1.E(paramObject, U(i2)));
        break;
      case 9: 
        if (!B(paramObject, i1)) {
          break label2344;
        }
        paramA2.w(i3, x1.E(paramObject, U(i2)), u(i1));
        break;
      case 8: 
        if (!B(paramObject, i1)) {
          break label2344;
        }
        w0(i3, x1.E(paramObject, U(i2)), paramA2);
        break;
      case 7: 
        if (!B(paramObject, i1)) {
          break label2344;
        }
        bool = l(paramObject, U(i2));
        paramA2.f(i3, bool);
        break;
      case 6: 
        if (!B(paramObject, i1)) {
          break label2344;
        }
        i2 = z(paramObject, U(i2));
        paramA2.p(i3, i2);
        break;
      case 5: 
        if (!B(paramObject, i1)) {
          break label2344;
        }
        l1 = K(paramObject, U(i2));
        paramA2.A(i3, l1);
        break;
      case 4: 
        if (!B(paramObject, i1)) {
          break label2344;
        }
        i2 = z(paramObject, U(i2));
        paramA2.m(i3, i2);
        break;
      case 3: 
        if (!B(paramObject, i1)) {
          break label2344;
        }
        l1 = K(paramObject, U(i2));
        paramA2.I(i3, l1);
        break;
      case 2: 
        if (!B(paramObject, i1)) {
          break label2344;
        }
        l1 = K(paramObject, U(i2));
        paramA2.e(i3, l1);
        break;
      case 1: 
        if (!B(paramObject, i1)) {
          break label2344;
        }
        f1 = r(paramObject, U(i2));
        paramA2.D(i3, f1);
        break;
      }
      if (B(paramObject, i1))
      {
        d1 = o(paramObject, U(i2));
        paramA2.q(i3, d1);
      }
      label2344:
      i1 -= 3;
    }
    while (localObject2 != null)
    {
      p.j(paramA2, (Map.Entry)localObject2);
      if (localIterator.hasNext()) {
        localObject2 = (Map.Entry)localIterator.next();
      } else {
        localObject2 = null;
      }
    }
  }
  
  static u1 v(Object paramObject)
  {
    z localZ = (z)paramObject;
    u1 localU1 = unknownFields;
    paramObject = localU1;
    if (localU1 == u1.c())
    {
      paramObject = u1.n();
      unknownFields = paramObject;
    }
    return paramObject;
  }
  
  private void v0(a2 paramA2, int paramInt1, Object paramObject, int paramInt2)
  {
    if (paramObject != null) {
      paramA2.x(paramInt1, q.f(t(paramInt2)), q.g(paramObject));
    }
  }
  
  private int w(Object paramObject)
  {
    Unsafe localUnsafe = s;
    int i3 = 0;
    int i2 = 0;
    int i7 = 1048575;
    int i5 = 0;
    while (i3 < a.length)
    {
      int i12 = r0(i3);
      int i11 = T(i3);
      int i13 = q0(i12);
      int i4;
      int i6;
      int i8;
      if (i13 <= 17)
      {
        i1 = a[(i3 + 2)];
        int i10 = i1 & 0xFFFFF;
        int i9 = 1 << (i1 >>> 20);
        i4 = i7;
        i6 = i1;
        i8 = i9;
        if (i10 != i7)
        {
          i5 = localUnsafe.getInt(paramObject, i10);
          i4 = i10;
          i6 = i1;
          i8 = i9;
        }
      }
      else
      {
        if ((i) && (i13 >= w.S.a()) && (i13 <= w.f0.a())) {
          i1 = a[(i3 + 2)] & 0xFFFFF;
        } else {
          i1 = 0;
        }
        i8 = 0;
        i6 = i1;
        i4 = i7;
      }
      long l1 = U(i12);
      Object localObject;
      switch (i13)
      {
      default: 
        i1 = i2;
        break;
      case 68: 
        i1 = i2;
        if (!H(paramObject, i11, i3)) {}
        break;
      case 67: 
        i1 = i2;
        if (H(paramObject, i11, i3)) {
          l1 = Z(paramObject, l1);
        }
        break;
      case 66: 
        i1 = i2;
        if (H(paramObject, i11, i3)) {
          i1 = Y(paramObject, l1);
        }
        break;
      case 65: 
        i1 = i2;
        if (!H(paramObject, i11, i3)) {}
        break;
      case 64: 
        i1 = i2;
        if (!H(paramObject, i11, i3)) {}
        break;
      case 63: 
        i1 = i2;
        if (H(paramObject, i11, i3)) {
          i1 = Y(paramObject, l1);
        }
        break;
      case 62: 
        i1 = i2;
        if (H(paramObject, i11, i3)) {
          i1 = Y(paramObject, l1);
        }
        break;
      case 61: 
        i1 = i2;
        if (!H(paramObject, i11, i3)) {}
        break;
      case 60: 
        i1 = i2;
        if (!H(paramObject, i11, i3)) {}
        break;
      case 59: 
        i1 = i2;
        if (H(paramObject, i11, i3))
        {
          localObject = localUnsafe.getObject(paramObject, l1);
          if ((localObject instanceof j)) {
            i1 = m.h(i11, (j)localObject);
          } else {
            i1 = m.R(i11, (String)localObject);
          }
        }
        break;
      case 58: 
        i1 = i2;
        if (!H(paramObject, i11, i3)) {}
        break;
      case 57: 
        i1 = i2;
        if (H(paramObject, i11, i3)) {
          i1 = m.n(i11, 0);
        }
        break;
      case 56: 
        i1 = i2;
        if (H(paramObject, i11, i3)) {
          i1 = m.p(i11, 0L);
        }
        break;
      case 55: 
        i1 = i2;
        if (H(paramObject, i11, i3)) {
          i1 = m.w(i11, Y(paramObject, l1));
        }
        break;
      case 54: 
        i1 = i2;
        if (H(paramObject, i11, i3)) {
          i1 = m.W(i11, Z(paramObject, l1));
        }
        break;
      case 53: 
        i1 = i2;
        if (H(paramObject, i11, i3)) {
          i1 = m.y(i11, Z(paramObject, l1));
        }
        break;
      case 52: 
        i1 = i2;
        if (H(paramObject, i11, i3)) {
          i1 = m.r(i11, 0.0F);
        }
        break;
      case 51: 
        i1 = i2;
        if (H(paramObject, i11, i3)) {
          i1 = m.j(i11, 0.0D);
        }
        break;
      case 50: 
        i1 = q.c(i11, localUnsafe.getObject(paramObject, l1), t(i3));
        break;
      case 49: 
        i1 = n1.j(i11, (List)localUnsafe.getObject(paramObject, l1), u(i3));
        break;
      case 48: 
        i7 = n1.t((List)localUnsafe.getObject(paramObject, l1));
        i1 = i2;
        if (i7 > 0)
        {
          i1 = i7;
          if (i) {
            i1 = i7;
          }
        }
        break;
      case 47: 
        i7 = n1.r((List)localUnsafe.getObject(paramObject, l1));
        i1 = i2;
        if (i7 > 0)
        {
          i1 = i7;
          if (i) {
            i1 = i7;
          }
        }
        break;
      case 46: 
        i7 = n1.i((List)localUnsafe.getObject(paramObject, l1));
        i1 = i2;
        if (i7 > 0)
        {
          i1 = i7;
          if (i) {
            i1 = i7;
          }
        }
        break;
      case 45: 
        i7 = n1.g((List)localUnsafe.getObject(paramObject, l1));
        i1 = i2;
        if (i7 > 0)
        {
          i1 = i7;
          if (i) {
            i1 = i7;
          }
        }
        break;
      case 44: 
        i7 = n1.e((List)localUnsafe.getObject(paramObject, l1));
        i1 = i2;
        if (i7 > 0)
        {
          i1 = i7;
          if (i) {
            i1 = i7;
          }
        }
        break;
      case 43: 
        i7 = n1.w((List)localUnsafe.getObject(paramObject, l1));
        i1 = i2;
        if (i7 > 0)
        {
          i1 = i7;
          if (i) {
            i1 = i7;
          }
        }
        break;
      case 42: 
        i7 = n1.b((List)localUnsafe.getObject(paramObject, l1));
        i1 = i2;
        if (i7 > 0)
        {
          i1 = i7;
          if (i) {
            i1 = i7;
          }
        }
        break;
      case 41: 
        i7 = n1.g((List)localUnsafe.getObject(paramObject, l1));
        i1 = i2;
        if (i7 > 0)
        {
          i1 = i7;
          if (i) {
            i1 = i7;
          }
        }
        break;
      case 40: 
        i7 = n1.i((List)localUnsafe.getObject(paramObject, l1));
        i1 = i2;
        if (i7 > 0)
        {
          i1 = i7;
          if (i) {
            i1 = i7;
          }
        }
        break;
      case 39: 
        i7 = n1.l((List)localUnsafe.getObject(paramObject, l1));
        i1 = i2;
        if (i7 > 0)
        {
          i1 = i7;
          if (i) {
            i1 = i7;
          }
        }
        break;
      case 38: 
        i7 = n1.y((List)localUnsafe.getObject(paramObject, l1));
        i1 = i2;
        if (i7 > 0)
        {
          i1 = i7;
          if (i) {
            i1 = i7;
          }
        }
        break;
      case 37: 
        i7 = n1.n((List)localUnsafe.getObject(paramObject, l1));
        i1 = i2;
        if (i7 > 0)
        {
          i1 = i7;
          if (i) {
            i1 = i7;
          }
        }
        break;
      case 36: 
        i7 = n1.g((List)localUnsafe.getObject(paramObject, l1));
        i1 = i2;
        if (i7 > 0)
        {
          i1 = i7;
          if (i) {
            i1 = i7;
          }
        }
        break;
      case 35: 
        i7 = n1.i((List)localUnsafe.getObject(paramObject, l1));
        i1 = i2;
        if (i7 > 0)
        {
          i1 = i7;
          if (i)
          {
            i1 = i7;
            localUnsafe.putInt(paramObject, i6, i1);
          }
          i1 = m.T(i11) + m.V(i1) + i1;
        }
        break;
      case 34: 
        i1 = n1.s(i11, (List)localUnsafe.getObject(paramObject, l1), false);
        break;
      case 33: 
        i1 = n1.q(i11, (List)localUnsafe.getObject(paramObject, l1), false);
        break;
      case 30: 
        i1 = n1.d(i11, (List)localUnsafe.getObject(paramObject, l1), false);
        break;
      case 29: 
        i1 = n1.v(i11, (List)localUnsafe.getObject(paramObject, l1), false);
        break;
      case 28: 
        i1 = n1.c(i11, (List)localUnsafe.getObject(paramObject, l1));
        break;
      case 27: 
        i1 = n1.p(i11, (List)localUnsafe.getObject(paramObject, l1), u(i3));
        break;
      case 26: 
        i1 = n1.u(i11, (List)localUnsafe.getObject(paramObject, l1));
        break;
      case 25: 
        i1 = n1.a(i11, (List)localUnsafe.getObject(paramObject, l1), false);
        break;
      case 22: 
        i1 = n1.k(i11, (List)localUnsafe.getObject(paramObject, l1), false);
        break;
      case 21: 
        i1 = n1.x(i11, (List)localUnsafe.getObject(paramObject, l1), false);
        break;
      case 20: 
        i1 = n1.m(i11, (List)localUnsafe.getObject(paramObject, l1), false);
        break;
      case 19: 
      case 24: 
      case 31: 
        i1 = n1.f(i11, (List)localUnsafe.getObject(paramObject, l1), false);
        break;
      case 18: 
      case 23: 
      case 32: 
        i1 = n1.h(i11, (List)localUnsafe.getObject(paramObject, l1), false);
        i1 = i2 + i1;
      }
      for (;;)
      {
        break label2330;
        i1 = i2;
        if ((i5 & i8) != 0)
        {
          i1 = m.t(i11, (t0)localUnsafe.getObject(paramObject, l1), u(i3));
          break;
          i1 = i2;
          if ((i5 & i8) != 0)
          {
            l1 = localUnsafe.getLong(paramObject, l1);
            i1 = m.P(i11, l1);
            break;
            i1 = i2;
            if ((i5 & i8) != 0)
            {
              i1 = localUnsafe.getInt(paramObject, l1);
              i1 = m.N(i11, i1);
              break;
              i1 = i2;
              if ((i5 & i8) != 0)
              {
                i1 = m.L(i11, 0L);
                break;
                i1 = i2;
                if ((i5 & i8) != 0)
                {
                  i1 = m.J(i11, 0);
                  i1 = i2 + i1;
                  continue;
                  i1 = i2;
                  if ((i5 & i8) != 0)
                  {
                    i1 = localUnsafe.getInt(paramObject, l1);
                    i1 = m.l(i11, i1);
                    break;
                    i1 = i2;
                    if ((i5 & i8) != 0)
                    {
                      i1 = localUnsafe.getInt(paramObject, l1);
                      i1 = m.U(i11, i1);
                      break;
                      i1 = i2;
                      if ((i5 & i8) != 0)
                      {
                        i1 = m.h(i11, (j)localUnsafe.getObject(paramObject, l1));
                        break;
                        i1 = i2;
                        if ((i5 & i8) != 0)
                        {
                          i1 = n1.o(i11, localUnsafe.getObject(paramObject, l1), u(i3));
                          break;
                          i1 = i2;
                          if ((i5 & i8) != 0)
                          {
                            localObject = localUnsafe.getObject(paramObject, l1);
                            if ((localObject instanceof j))
                            {
                              i1 = m.h(i11, (j)localObject);
                              break;
                            }
                            i1 = m.R(i11, (String)localObject);
                            break;
                            i1 = i2;
                            if ((i5 & i8) != 0)
                            {
                              i1 = m.e(i11, true);
                              break;
                              i1 = i2;
                              if ((i5 & i8) != 0)
                              {
                                i1 = m.n(i11, 0);
                                break label2326;
                                i1 = i2;
                                if ((i5 & i8) != 0)
                                {
                                  i1 = m.p(i11, 0L);
                                  break label2326;
                                  i1 = i2;
                                  if ((i5 & i8) != 0)
                                  {
                                    i1 = m.w(i11, localUnsafe.getInt(paramObject, l1));
                                    break label2326;
                                    i1 = i2;
                                    if ((i5 & i8) != 0)
                                    {
                                      i1 = m.W(i11, localUnsafe.getLong(paramObject, l1));
                                      break label2326;
                                      i1 = i2;
                                      if ((i5 & i8) != 0)
                                      {
                                        i1 = m.y(i11, localUnsafe.getLong(paramObject, l1));
                                        break label2326;
                                        i1 = i2;
                                        if ((i5 & i8) != 0)
                                        {
                                          i1 = m.r(i11, 0.0F);
                                          break label2326;
                                          i1 = i2;
                                          if ((i5 & i8) != 0)
                                          {
                                            i1 = m.j(i11, 0.0D);
                                            label2326:
                                            i1 = i2 + i1;
                                          }
                                        }
                                      }
                                    }
                                  }
                                }
                              }
                            }
                          }
                        }
                      }
                    }
                  }
                }
              }
            }
          }
        }
      }
      label2330:
      i3 += 3;
      i2 = i1;
      i7 = i4;
    }
    i2 += y(o, paramObject);
    int i1 = i2;
    if (f) {
      i1 = i2 + p.c(paramObject).k();
    }
    return i1;
  }
  
  private void w0(int paramInt, Object paramObject, a2 paramA2)
  {
    if ((paramObject instanceof String))
    {
      paramA2.G(paramInt, (String)paramObject);
      return;
    }
    paramA2.l(paramInt, (j)paramObject);
  }
  
  private int x(Object paramObject)
  {
    Unsafe localUnsafe = s;
    int i2 = 0;
    int i1;
    for (int i3 = 0; i2 < a.length; i3 = i1)
    {
      int i4 = r0(i2);
      i1 = q0(i4);
      int i6 = T(i2);
      long l1 = U(i4);
      if ((i1 >= w.S.a()) && (i1 <= w.f0.a())) {
        i4 = a[(i2 + 2)] & 0xFFFFF;
      } else {
        i4 = 0;
      }
      Object localObject2;
      Object localObject1;
      label605:
      int i5;
      switch (i1)
      {
      default: 
        i1 = i3;
        break;
      case 68: 
        i1 = i3;
        if (!H(paramObject, i6, i2)) {
          break label2125;
        }
        break;
      case 67: 
        i1 = i3;
        if (!H(paramObject, i6, i2)) {
          break label2125;
        }
        l1 = Z(paramObject, l1);
        break;
      case 66: 
        i1 = i3;
        if (!H(paramObject, i6, i2)) {
          break label2125;
        }
        i1 = Y(paramObject, l1);
        break;
      case 65: 
        i1 = i3;
        if (!H(paramObject, i6, i2)) {
          break label2125;
        }
        break;
      case 64: 
        i1 = i3;
        if (!H(paramObject, i6, i2)) {
          break label2125;
        }
        break;
      case 63: 
        i1 = i3;
        if (!H(paramObject, i6, i2)) {
          break label2125;
        }
        i1 = Y(paramObject, l1);
        break;
      case 62: 
        i1 = i3;
        if (!H(paramObject, i6, i2)) {
          break label2125;
        }
        i1 = Y(paramObject, l1);
        break;
      case 61: 
        i1 = i3;
        if (!H(paramObject, i6, i2)) {
          break label2125;
        }
        break;
      case 60: 
        i1 = i3;
        if (!H(paramObject, i6, i2)) {
          break label2125;
        }
        break;
      case 59: 
        i1 = i3;
        if (!H(paramObject, i6, i2)) {
          break label2125;
        }
        localObject2 = x1.E(paramObject, l1);
        localObject1 = localObject2;
        if ((localObject2 instanceof j)) {
          localObject1 = localObject2;
        } else {
          i1 = m.R(i6, (String)localObject1);
        }
        break;
      case 58: 
        i1 = i3;
        if (!H(paramObject, i6, i2)) {
          break label2125;
        }
        break;
      case 57: 
        i1 = i3;
        if (!H(paramObject, i6, i2)) {
          break label2125;
        }
        break;
      case 56: 
        i1 = i3;
        if (!H(paramObject, i6, i2)) {
          break label2125;
        }
        break;
      case 55: 
        i1 = i3;
        if (!H(paramObject, i6, i2)) {
          break label2125;
        }
        i1 = Y(paramObject, l1);
        break;
      case 54: 
        i1 = i3;
        if (!H(paramObject, i6, i2)) {
          break label2125;
        }
        l1 = Z(paramObject, l1);
        break;
      case 53: 
        i1 = i3;
        if (!H(paramObject, i6, i2)) {
          break label2125;
        }
        l1 = Z(paramObject, l1);
        break;
      case 52: 
        i1 = i3;
        if (!H(paramObject, i6, i2)) {
          break label2125;
        }
        break;
      case 51: 
        i1 = i3;
        if (!H(paramObject, i6, i2)) {
          break label2125;
        }
        break;
      case 50: 
        i1 = q.c(i6, x1.E(paramObject, l1), t(i2));
        break;
      case 49: 
        i1 = n1.j(i6, J(paramObject, l1), u(i2));
        break;
      case 48: 
        i5 = n1.t((List)localUnsafe.getObject(paramObject, l1));
        i1 = i3;
        if (i5 <= 0) {
          break label2125;
        }
        i1 = i5;
        if (i) {
          i1 = i5;
        }
        break;
      case 47: 
        i5 = n1.r((List)localUnsafe.getObject(paramObject, l1));
        i1 = i3;
        if (i5 <= 0) {
          break label2125;
        }
        i1 = i5;
        if (i) {
          i1 = i5;
        }
        break;
      case 46: 
        i5 = n1.i((List)localUnsafe.getObject(paramObject, l1));
        i1 = i3;
        if (i5 <= 0) {
          break label2125;
        }
        i1 = i5;
        if (i) {
          i1 = i5;
        }
        break;
      case 45: 
        i5 = n1.g((List)localUnsafe.getObject(paramObject, l1));
        i1 = i3;
        if (i5 <= 0) {
          break label2125;
        }
        i1 = i5;
        if (i) {
          i1 = i5;
        }
        break;
      case 44: 
        i5 = n1.e((List)localUnsafe.getObject(paramObject, l1));
        i1 = i3;
        if (i5 <= 0) {
          break label2125;
        }
        i1 = i5;
        if (i) {
          i1 = i5;
        }
        break;
      case 43: 
        i5 = n1.w((List)localUnsafe.getObject(paramObject, l1));
        i1 = i3;
        if (i5 <= 0) {
          break label2125;
        }
        i1 = i5;
        if (i) {
          i1 = i5;
        }
        break;
      case 42: 
        i5 = n1.b((List)localUnsafe.getObject(paramObject, l1));
        i1 = i3;
        if (i5 <= 0) {
          break label2125;
        }
        i1 = i5;
        if (i) {
          i1 = i5;
        }
        break;
      case 41: 
        i5 = n1.g((List)localUnsafe.getObject(paramObject, l1));
        i1 = i3;
        if (i5 <= 0) {
          break label2125;
        }
        i1 = i5;
        if (i) {
          i1 = i5;
        }
        break;
      case 40: 
        i5 = n1.i((List)localUnsafe.getObject(paramObject, l1));
        i1 = i3;
        if (i5 <= 0) {
          break label2125;
        }
        i1 = i5;
        if (i) {
          i1 = i5;
        }
        break;
      case 39: 
        i5 = n1.l((List)localUnsafe.getObject(paramObject, l1));
        i1 = i3;
        if (i5 <= 0) {
          break label2125;
        }
        i1 = i5;
        if (i) {
          i1 = i5;
        }
        break;
      case 38: 
        i5 = n1.y((List)localUnsafe.getObject(paramObject, l1));
        i1 = i3;
        if (i5 <= 0) {
          break label2125;
        }
        i1 = i5;
        if (i) {
          i1 = i5;
        }
        break;
      case 37: 
        i5 = n1.n((List)localUnsafe.getObject(paramObject, l1));
        i1 = i3;
        if (i5 <= 0) {
          break label2125;
        }
        i1 = i5;
        if (i) {
          i1 = i5;
        }
        break;
      case 36: 
        i5 = n1.g((List)localUnsafe.getObject(paramObject, l1));
        i1 = i3;
        if (i5 <= 0) {
          break label2125;
        }
        i1 = i5;
        if (i) {
          i1 = i5;
        }
        break;
      case 35: 
        i5 = n1.i((List)localUnsafe.getObject(paramObject, l1));
        i1 = i3;
        if (i5 <= 0) {
          break label2125;
        }
        i1 = i5;
        if (i)
        {
          i1 = i5;
          localUnsafe.putInt(paramObject, i4, i1);
        }
        i1 = m.T(i6) + m.V(i1) + i1;
        break;
      case 34: 
        i1 = n1.s(i6, J(paramObject, l1), false);
        break;
      case 33: 
        i1 = n1.q(i6, J(paramObject, l1), false);
        break;
      case 30: 
        i1 = n1.d(i6, J(paramObject, l1), false);
        break;
      case 29: 
        i1 = n1.v(i6, J(paramObject, l1), false);
        break;
      case 28: 
        i1 = n1.c(i6, J(paramObject, l1));
        break;
      case 27: 
        i1 = n1.p(i6, J(paramObject, l1), u(i2));
        break;
      case 26: 
        i1 = n1.u(i6, J(paramObject, l1));
        break;
      case 25: 
        i1 = n1.a(i6, J(paramObject, l1), false);
        break;
      case 22: 
        i1 = n1.k(i6, J(paramObject, l1), false);
        break;
      case 21: 
        i1 = n1.x(i6, J(paramObject, l1), false);
        break;
      case 20: 
        i1 = n1.m(i6, J(paramObject, l1), false);
        break;
      case 19: 
      case 24: 
      case 31: 
        i1 = n1.f(i6, J(paramObject, l1), false);
        break;
      case 18: 
      case 23: 
      case 32: 
        i1 = n1.h(i6, J(paramObject, l1), false);
      }
      for (;;)
      {
        i1 = i3 + i1;
        break label2125;
        i1 = i3;
        if (!B(paramObject, i2)) {
          break label2125;
        }
        i1 = m.t(i6, (t0)x1.E(paramObject, l1), u(i2));
        continue;
        i1 = i3;
        if (!B(paramObject, i2)) {
          break label2125;
        }
        l1 = x1.C(paramObject, l1);
        i1 = m.P(i6, l1);
        continue;
        i1 = i3;
        if (!B(paramObject, i2)) {
          break label2125;
        }
        i1 = x1.A(paramObject, l1);
        i1 = m.N(i6, i1);
        continue;
        i1 = i3;
        if (!B(paramObject, i2)) {
          break label2125;
        }
        i1 = m.L(i6, 0L);
        continue;
        i1 = i3;
        if (!B(paramObject, i2)) {
          break label2125;
        }
        i1 = m.J(i6, 0);
        continue;
        i1 = i3;
        if (!B(paramObject, i2)) {
          break label2125;
        }
        i1 = x1.A(paramObject, l1);
        i1 = m.l(i6, i1);
        continue;
        i1 = i3;
        if (!B(paramObject, i2)) {
          break label2125;
        }
        i1 = x1.A(paramObject, l1);
        i1 = m.U(i6, i1);
        continue;
        i1 = i3;
        if (!B(paramObject, i2)) {
          break label2125;
        }
        localObject1 = x1.E(paramObject, l1);
        i1 = m.h(i6, (j)localObject1);
        continue;
        i1 = i3;
        if (!B(paramObject, i2)) {
          break label2125;
        }
        i1 = n1.o(i6, x1.E(paramObject, l1), u(i2));
        continue;
        i1 = i3;
        if (!B(paramObject, i2)) {
          break label2125;
        }
        localObject2 = x1.E(paramObject, l1);
        localObject1 = localObject2;
        if (!(localObject2 instanceof j)) {
          break label605;
        }
        localObject1 = localObject2;
        break;
        i1 = i3;
        if (!B(paramObject, i2)) {
          break label2125;
        }
        i1 = m.e(i6, true);
        continue;
        i1 = i3;
        if (!B(paramObject, i2)) {
          break label2125;
        }
        i1 = m.n(i6, 0);
        continue;
        i1 = i3;
        if (!B(paramObject, i2)) {
          break label2125;
        }
        i1 = m.p(i6, 0L);
        continue;
        i1 = i3;
        if (!B(paramObject, i2)) {
          break label2125;
        }
        i1 = x1.A(paramObject, l1);
        i1 = m.w(i6, i1);
        continue;
        i1 = i3;
        if (!B(paramObject, i2)) {
          break label2125;
        }
        l1 = x1.C(paramObject, l1);
        i1 = m.W(i6, l1);
        continue;
        i1 = i3;
        if (!B(paramObject, i2)) {
          break label2125;
        }
        l1 = x1.C(paramObject, l1);
        i1 = m.y(i6, l1);
        continue;
        i1 = i3;
        if (!B(paramObject, i2)) {
          break label2125;
        }
        i1 = m.r(i6, 0.0F);
        continue;
        i1 = i3;
        if (!B(paramObject, i2)) {
          break label2125;
        }
        i1 = m.j(i6, 0.0D);
      }
      label2125:
      i2 += 3;
    }
    return i3 + y(o, paramObject);
  }
  
  private void x0(t1 paramT1, Object paramObject, a2 paramA2)
  {
    paramT1.t(paramT1.g(paramObject), paramA2);
  }
  
  private int y(t1 paramT1, Object paramObject)
  {
    return paramT1.h(paramT1.g(paramObject));
  }
  
  private static int z(Object paramObject, long paramLong)
  {
    return x1.A(paramObject, paramLong);
  }
  
  public void a(Object paramObject1, Object paramObject2)
  {
    paramObject2.getClass();
    int i1 = 0;
    while (i1 < a.length)
    {
      P(paramObject1, paramObject2, i1);
      i1 += 3;
    }
    n1.G(o, paramObject1, paramObject2);
    if (f) {
      n1.E(p, paramObject1, paramObject2);
    }
  }
  
  public void b(Object paramObject, a2 paramA2)
  {
    if (paramA2.B() == a2.a.f)
    {
      u0(paramObject, paramA2);
      return;
    }
    if (h)
    {
      t0(paramObject, paramA2);
      return;
    }
    s0(paramObject, paramA2);
  }
  
  public void c(Object paramObject)
  {
    int i1 = k;
    int i2;
    for (;;)
    {
      i2 = l;
      if (i1 >= i2) {
        break;
      }
      long l1 = U(r0(j[i1]));
      Object localObject = x1.E(paramObject, l1);
      if (localObject != null) {
        x1.S(paramObject, l1, q.e(localObject));
      }
      i1 += 1;
    }
    int i3 = j.length;
    i1 = i2;
    while (i1 < i3)
    {
      n.c(paramObject, j[i1]);
      i1 += 1;
    }
    o.j(paramObject);
    if (f) {
      p.f(paramObject);
    }
  }
  
  int c0(Object paramObject, byte[] paramArrayOfByte, int paramInt1, int paramInt2, int paramInt3, f.a paramA)
  {
    Object localObject1 = paramObject;
    int i5 = paramInt2;
    int i4 = paramInt3;
    Unsafe localUnsafe = s;
    int i6 = -1;
    int i7 = 0;
    int i2 = 0;
    int i1 = 0;
    int i3 = 1048575;
    Object localObject2;
    for (;;)
    {
      Object localObject4 = paramArrayOfByte;
      localObject2 = this;
      Object localObject3 = paramA;
      if (paramInt1 >= i5) {
        break;
      }
      int i8 = paramInt1 + 1;
      paramInt1 = localObject4[paramInt1];
      if (paramInt1 < 0)
      {
        i8 = f.G(paramInt1, (byte[])localObject4, i8, (f.a)localObject3);
        paramInt1 = a;
      }
      i5 = paramInt1 >>> 3;
      int i10 = paramInt1 & 0x7;
      if (i5 > i6) {
        i2 = ((w0)localObject2).g0(i5, i7 / 3);
      } else {
        i2 = ((w0)localObject2).f0(i5);
      }
      if (i2 == -1)
      {
        i6 = paramInt1;
        i2 = i1;
        paramInt1 = i4;
        i7 = 0;
        i4 = i8;
        i1 = i6;
        i6 = i7;
      }
      else
      {
        int i11 = a[(i2 + 1)];
        int i12 = q0(i11);
        long l1 = U(i11);
        if (i12 <= 17)
        {
          i4 = a[(i2 + 2)];
          i7 = 1 << (i4 >>> 20);
          i4 &= 0xFFFFF;
          if (i4 != i3)
          {
            if (i3 != 1048575) {
              localUnsafe.putInt(localObject1, i3, i1);
            }
            i1 = localUnsafe.getInt(localObject1, i4);
            i3 = i4;
            i4 = i1;
          }
          else
          {
            i4 = i1;
          }
          switch (i12)
          {
          default: 
            break;
          case 17: 
            if (i10 == 3)
            {
              i6 = f.m(((w0)localObject2).u(i2), paramArrayOfByte, i8, paramInt2, i5 << 3 | 0x4, paramA);
              if ((i4 & i7) == 0) {
                localObject2 = c;
              } else {
                localObject2 = c0.h(localUnsafe.getObject(localObject1, l1), c);
              }
              localUnsafe.putObject(localObject1, l1, localObject2);
              i9 = i4 | i7;
              i8 = paramInt2;
              i4 = paramInt3;
              i1 = paramInt1;
              paramInt1 = i6;
              i6 = i5;
              i7 = i2;
              i2 = i1;
              i1 = i9;
              i5 = i8;
              continue;
            }
            break;
          case 16: 
            if (i10 == 0)
            {
              i1 = f.K(paramArrayOfByte, i8, (f.a)localObject3);
              localUnsafe.putLong(paramObject, l1, k.c(b));
              i4 |= i7;
              localObject1 = paramObject;
              i6 = i2;
            }
            break;
          case 15: 
            if (i10 == 0)
            {
              i1 = f.H(paramArrayOfByte, i8, (f.a)localObject3);
              i6 = k.b(a);
              localObject1 = paramObject;
            }
            break;
          case 12: 
            if (i10 == 0)
            {
              i1 = f.H(paramArrayOfByte, i8, (f.a)localObject3);
              i6 = a;
              ((w0)localObject2).s(i2);
            }
            break;
          case 10: 
            if (i10 == 2)
            {
              i1 = f.b(paramArrayOfByte, i8, (f.a)localObject3);
              localUnsafe.putObject(localObject1, l1, c);
            }
            break;
          case 9: 
            if (i10 == 2)
            {
              i1 = f.o(((w0)localObject2).u(i2), paramArrayOfByte, i8, paramInt2, (f.a)localObject3);
              if ((i4 & i7) == 0) {
                localObject2 = c;
              } else {
                localObject2 = c0.h(localUnsafe.getObject(localObject1, l1), c);
              }
            }
            break;
          case 8: 
            localObject2 = paramArrayOfByte;
            if (i10 == 2)
            {
              if ((i11 & 0x20000000) == 0) {
                i1 = f.B((byte[])localObject2, i8, (f.a)localObject3);
              } else {
                i1 = f.E((byte[])localObject2, i8, (f.a)localObject3);
              }
              localObject2 = c;
              localUnsafe.putObject(localObject1, l1, localObject2);
            }
            break;
          case 7: 
            if (i10 == 0)
            {
              i1 = f.K(paramArrayOfByte, i8, (f.a)localObject3);
              boolean bool;
              if (b != 0L) {
                bool = true;
              } else {
                bool = false;
              }
              x1.I(localObject1, l1, bool);
            }
            break;
          case 6: 
          case 13: 
            if (i10 == 5)
            {
              localUnsafe.putInt(localObject1, l1, f.g(paramArrayOfByte, i8));
              i1 = i8 + 4;
              i8 = paramInt2;
              i10 = paramInt1;
              i9 = paramInt3;
              i4 |= i7;
              paramInt1 = i1;
              i6 = i5;
              i7 = i2;
              i2 = i10;
              i1 = i4;
              i4 = i9;
              i5 = i8;
            }
            break;
          case 5: 
          case 14: 
            if (i10 == 1)
            {
              localUnsafe.putLong(paramObject, l1, f.i(paramArrayOfByte, i8));
              i1 = i8 + 8;
              i6 = i4 | i7;
              i4 = i1;
              i1 = i6;
            }
            break;
          case 4: 
          case 11: 
            if (i10 == 0)
            {
              i1 = f.H(paramArrayOfByte, i8, (f.a)localObject3);
              i6 = a;
              localUnsafe.putInt(localObject1, l1, i6);
            }
            break;
          case 2: 
          case 3: 
            if (i10 == 0)
            {
              i1 = f.K(paramArrayOfByte, i8, (f.a)localObject3);
              localUnsafe.putLong(paramObject, l1, b);
              i6 = i4 | i7;
              i4 = i1;
              i1 = i6;
              i6 = i2;
              i7 = paramInt1;
              i2 = i5;
              paramInt1 = i4;
              i5 = i6;
              i4 = i7;
            }
            break;
          case 1: 
            if (i10 == 5)
            {
              x1.P(localObject1, l1, f.k(paramArrayOfByte, i8));
              i1 = i8 + 4;
            }
            break;
          case 0: 
            if (i10 == 1)
            {
              x1.O(localObject1, l1, f.d(paramArrayOfByte, i8));
              i1 = i8 + 8;
              i4 |= i7;
              i6 = i2;
              i7 = paramInt1;
              i2 = i5;
              paramInt1 = i1;
              i5 = i6;
              i6 = i7;
              i1 = i4;
              break label1311;
            }
            i1 = paramInt3;
            i7 = i4;
            i6 = paramInt1;
            i4 = i8;
            paramInt1 = i1;
            i1 = i6;
            i6 = i2;
            i2 = i7;
            break;
          }
        }
        i6 = i5;
        if (i12 == 27)
        {
          if (i10 == 2)
          {
            localObject4 = (c0.i)localUnsafe.getObject(localObject1, l1);
            localObject3 = localObject4;
            if (!((c0.i)localObject4).T())
            {
              i4 = ((List)localObject4).size();
              if (i4 == 0) {
                i4 = 10;
              } else {
                i4 *= 2;
              }
              localObject3 = ((c0.i)localObject4).a(i4);
              localUnsafe.putObject(localObject1, l1, localObject3);
            }
            localObject1 = ((w0)localObject2).u(i2);
            i7 = f.p((l1)localObject1, paramInt1, paramArrayOfByte, i8, paramInt2, (c0.i)localObject3, paramA);
            localObject1 = paramObject;
            i4 = paramInt1;
            paramInt1 = i6;
            i6 = i4;
            i5 = i2;
            i2 = paramInt1;
            paramInt1 = i7;
            label1311:
            i4 = i6;
            i8 = paramInt2;
            i9 = paramInt3;
            i6 = i2;
            i7 = i5;
            i2 = i4;
            i4 = i9;
            i5 = i8;
            continue;
          }
        }
        else
        {
          i7 = i2;
          if (i12 <= 49)
          {
            i9 = e0(paramObject, paramArrayOfByte, i8, paramInt2, paramInt1, i6, i10, i7, i11, i12, l1, paramA);
            i4 = i9;
            if (i9 == i8) {
              break label1558;
            }
          }
          for (i2 = i9;; i2 = i8)
          {
            localObject1 = paramObject;
            i5 = paramInt2;
            i4 = paramInt3;
            i8 = paramInt1;
            paramInt1 = i2;
            i2 = i8;
            break;
            i9 = i8;
            if (i12 != 50) {
              break label1513;
            }
            if (i10 != 2) {
              break label1480;
            }
            i8 = a0(paramObject, paramArrayOfByte, i9, paramInt2, i7, l1, paramA);
            i4 = i8;
            if (i8 == i9) {
              break label1558;
            }
          }
        }
        label1480:
        i4 = i8;
        label1513:
        label1558:
        for (;;)
        {
          i7 = i1;
          i1 = paramInt3;
          i6 = paramInt1;
          paramInt1 = i1;
          i1 = i6;
          i6 = i2;
          i2 = i7;
          break label1561;
          i8 = b0(paramObject, paramArrayOfByte, i9, paramInt2, paramInt1, i6, i10, i11, i12, l1, i7, paramA);
          i4 = i8;
          if (i8 != i9)
          {
            i2 = i8;
            break;
          }
        }
      }
      label1561:
      if ((i1 == paramInt1) && (paramInt1 != 0))
      {
        paramArrayOfByte = this;
        paramInt3 = i4;
        i4 = i2;
        i2 = i1;
        i1 = i4;
        i4 = paramInt1;
        break label1715;
      }
      if ((f) && (d != r.b())) {
        i4 = f.f(i1, paramArrayOfByte, i4, paramInt2, paramObject, e, o, paramA);
      } else {
        i4 = f.F(i1, paramArrayOfByte, i4, paramInt2, v(paramObject), paramA);
      }
      localObject1 = paramObject;
      i8 = paramInt2;
      i7 = i5;
      i10 = i6;
      i5 = i2;
      int i9 = paramInt1;
      paramInt1 = i4;
      i6 = i7;
      i7 = i10;
      i2 = i1;
      i1 = i5;
      i4 = i9;
      i5 = i8;
    }
    paramArrayOfByte = (byte[])localObject2;
    paramInt3 = paramInt1;
    label1715:
    if (i3 != 1048575) {
      localUnsafe.putInt(paramObject, i3, i1);
    }
    paramA = paramObject;
    paramInt1 = k;
    paramObject = null;
    while (paramInt1 < l)
    {
      paramObject = (u1)paramArrayOfByte.q(paramA, j[paramInt1], paramObject, o);
      paramInt1 += 1;
    }
    if (paramObject != null) {
      o.o(paramA, paramObject);
    }
    if (i4 == 0)
    {
      if (paramInt3 == paramInt2) {
        return paramInt3;
      }
      throw d0.g();
    }
    if ((paramInt3 <= paramInt2) && (i2 == i4)) {
      return paramInt3;
    }
    throw d0.g();
  }
  
  public final boolean d(Object paramObject)
  {
    int i2 = 1048575;
    int i1 = 0;
    int i3 = 0;
    while (i3 < k)
    {
      int i5 = j[i3];
      int i6 = T(i5);
      int i7 = r0(i5);
      int i8 = a[(i5 + 2)];
      int i4 = i8 & 0xFFFFF;
      i8 = 1 << (i8 >>> 20);
      if (i4 != i2)
      {
        if (i4 != 1048575) {
          i1 = s.getInt(paramObject, i4);
        }
        i2 = i4;
      }
      if ((I(i7)) && (!C(paramObject, i5, i2, i1, i8))) {
        return false;
      }
      i4 = q0(i7);
      if ((i4 != 9) && (i4 != 17))
      {
        if (i4 != 27) {
          if ((i4 != 60) && (i4 != 68))
          {
            if (i4 != 49)
            {
              if ((i4 != 50) || (F(paramObject, i7, i5))) {
                break label270;
              }
              return false;
            }
          }
          else
          {
            if ((!H(paramObject, i6, i5)) || (D(paramObject, i7, u(i5)))) {
              break label270;
            }
            return false;
          }
        }
        if (!E(paramObject, i7, i5)) {
          return false;
        }
      }
      else if ((C(paramObject, i5, i2, i1, i8)) && (!D(paramObject, i7, u(i5))))
      {
        return false;
      }
      label270:
      i3 += 1;
    }
    return (!f) || (p.c(paramObject).n());
  }
  
  public void e(Object paramObject, j1 paramJ1, r paramR)
  {
    paramR.getClass();
    L(o, p, paramObject, paramJ1, paramR);
  }
  
  public boolean f(Object paramObject1, Object paramObject2)
  {
    int i2 = a.length;
    int i1 = 0;
    while (i1 < i2)
    {
      if (!p(paramObject1, paramObject2, i1)) {
        return false;
      }
      i1 += 3;
    }
    if (!o.g(paramObject1).equals(o.g(paramObject2))) {
      return false;
    }
    if (f) {
      return p.c(paramObject1).equals(p.c(paramObject2));
    }
    return true;
  }
  
  public void g(Object paramObject, byte[] paramArrayOfByte, int paramInt1, int paramInt2, f.a paramA)
  {
    if (h)
    {
      d0(paramObject, paramArrayOfByte, paramInt1, paramInt2, paramA);
      return;
    }
    c0(paramObject, paramArrayOfByte, paramInt1, paramInt2, 0, paramA);
  }
  
  public int h(Object paramObject)
  {
    if (h) {
      return x(paramObject);
    }
    return w(paramObject);
  }
  
  public Object i()
  {
    return m.a(e);
  }
  
  public int j(Object paramObject)
  {
    int i4 = a.length;
    int i3 = 0;
    for (int i2 = 0; i3 < i4; i2 = i1)
    {
      i1 = r0(i3);
      int i5 = T(i3);
      long l1 = U(i1);
      int i6 = q0(i1);
      i1 = 37;
      Object localObject;
      boolean bool;
      float f1;
      switch (i6)
      {
      default: 
        i1 = i2;
        break;
      case 68: 
        i1 = i2;
        if (!H(paramObject, i5, i3)) {
          break label1004;
        }
        break;
      case 67: 
        i1 = i2;
        if (!H(paramObject, i5, i3)) {
          break label1004;
        }
        break;
      case 66: 
        i1 = i2;
        if (!H(paramObject, i5, i3)) {
          break label1004;
        }
        break;
      case 65: 
        i1 = i2;
        if (!H(paramObject, i5, i3)) {
          break label1004;
        }
        break;
      case 64: 
        i1 = i2;
        if (!H(paramObject, i5, i3)) {
          break label1004;
        }
        break;
      case 63: 
        i1 = i2;
        if (!H(paramObject, i5, i3)) {
          break label1004;
        }
        break;
      case 62: 
        i1 = i2;
        if (!H(paramObject, i5, i3)) {
          break label1004;
        }
        break;
      case 61: 
        i1 = i2;
        if (!H(paramObject, i5, i3)) {
          break label1004;
        }
        break;
      case 60: 
        i1 = i2;
        if (!H(paramObject, i5, i3)) {
          break label1004;
        }
        localObject = x1.E(paramObject, l1);
        i1 = i2 * 53;
        break;
      case 59: 
        i1 = i2;
        if (!H(paramObject, i5, i3)) {
          break label1004;
        }
        break;
      case 58: 
        i1 = i2;
        if (!H(paramObject, i5, i3)) {
          break label1004;
        }
        i1 = i2 * 53;
        bool = V(paramObject, l1);
        break;
      case 57: 
        i1 = i2;
        if (!H(paramObject, i5, i3)) {
          break label1004;
        }
        break;
      case 56: 
        i1 = i2;
        if (!H(paramObject, i5, i3)) {
          break label1004;
        }
        break;
      case 55: 
        i1 = i2;
        if (!H(paramObject, i5, i3)) {
          break label1004;
        }
        i1 = i2 * 53;
        i2 = Y(paramObject, l1);
        break;
      case 54: 
        i1 = i2;
        if (!H(paramObject, i5, i3)) {
          break label1004;
        }
        break;
      case 53: 
        i1 = i2;
        if (!H(paramObject, i5, i3)) {
          break label1004;
        }
        i1 = i2 * 53;
        l1 = Z(paramObject, l1);
        break;
      case 52: 
        i1 = i2;
        if (!H(paramObject, i5, i3)) {
          break label1004;
        }
        i1 = i2 * 53;
        f1 = X(paramObject, l1);
        break;
      case 51: 
        i1 = i2;
        if (!H(paramObject, i5, i3)) {
          break label1004;
        }
        i1 = i2 * 53;
        d1 = W(paramObject, l1);
        break;
      case 17: 
        localObject = x1.E(paramObject, l1);
        if (localObject == null) {}
        break;
      case 10: 
      case 18: 
      case 19: 
      case 20: 
      case 21: 
      case 22: 
      case 23: 
      case 24: 
      case 25: 
      case 26: 
      case 27: 
      case 28: 
      case 29: 
      case 30: 
      case 31: 
      case 32: 
      case 33: 
      case 34: 
      case 35: 
      case 36: 
      case 37: 
      case 38: 
      case 39: 
      case 40: 
      case 41: 
      case 42: 
      case 43: 
      case 44: 
      case 45: 
      case 46: 
      case 47: 
      case 48: 
      case 49: 
      case 50: 
        i1 = i2 * 53;
        localObject = x1.E(paramObject, l1);
        i2 = localObject.hashCode();
        break;
      case 9: 
        localObject = x1.E(paramObject, l1);
        if (localObject != null) {
          i1 = localObject.hashCode();
        }
        i1 = i2 * 53 + i1;
        break;
      case 8: 
        i1 = i2 * 53;
        i2 = ((String)x1.E(paramObject, l1)).hashCode();
        break;
      case 7: 
        i1 = i2 * 53;
        bool = x1.r(paramObject, l1);
        i2 = c0.c(bool);
        break;
      case 4: 
      case 6: 
      case 11: 
      case 12: 
      case 13: 
      case 15: 
        i1 = i2 * 53;
        i2 = x1.A(paramObject, l1);
        break;
      case 2: 
      case 3: 
      case 5: 
      case 14: 
      case 16: 
        i1 = i2 * 53;
        l1 = x1.C(paramObject, l1);
        break;
      case 1: 
        i1 = i2 * 53;
        f1 = x1.z(paramObject, l1);
        i2 = Float.floatToIntBits(f1);
        break;
      }
      i1 = i2 * 53;
      double d1 = x1.y(paramObject, l1);
      l1 = Double.doubleToLongBits(d1);
      i2 = c0.f(l1);
      i1 += i2;
      label1004:
      i3 += 3;
    }
    i2 = i2 * 53 + o.g(paramObject).hashCode();
    int i1 = i2;
    if (f) {
      i1 = i2 * 53 + p.c(paramObject).hashCode();
    }
    return i1;
  }
}
